FPGA-Game-D1-master/HW/RTL/06PCM-AUDIO-MICROFONO/Version_01/02 verilog/Pruebas/Pruebafuncion/div_freq.v
module div_freq #(
              parameter   fi     = 50000000,        //<- fFPGA/2=fi  
              parameter   fs	 = 3125000        //<- flckout=fs
  )(input clk, output reg clkout,input reset, output reg led);



initial led=0;

reg [31:0] count;
initial count<= fi/fs;

always @(posedge  clk)
begin
	if (reset) begin
	led=1;
		
		if (count==0)begin
			clkout <=~clkout;
			count <= fi/fs;
		end	
		else begin
		count <=count-1;
		end

	end
	else begin
	led=0;
		count <= fi/fs;
		clkout <=0;
	end	
end


endmodule

FPGA-Game-D1-master/HW/RTL/06PCM-AUDIO-MICROFONO/Version_01/02 verilog/Pruebas/Pruebacorrimiento/pwm.v
module pwm
(
	input 		reset,	
	output 		ledres,
	input		clk,
	output		mclk,
        output    reg   ampPWM,
        output    reg	ampSD,
	input     [7:0] dout,
	input 		done1
 

);


reg [7:0] count;
initial ampSD <= 1;


always @(posedge  mclk )
begin

	if (reset)
		begin
     		ampPWM<=0;
    		end 
	else 
		begin
			if (count<8 && count >=0  )
				begin
				ampPWM<=dout[count];
				count<=count-1;
				end
			else
				begin
				count<=7;
				end
		end
		

		
	
end

endmodule

FPGA-Game-D1-master/HW/RTL/06PCM-AUDIO-MICROFONO/Version_01/02 verilog/Pruebas/Pruebacorrimiento/microfono.v
module microfono
(
	input 		reset,	
	output 		ledres,
	input		clk,
	output		mclk,
	output    reg   micLRSel,
        input           micData,    
        output          ampPWM,
        output          ampSD
	 

);

wire mclk1;
wire mclk2;
assign mclk3=mclk2;
assign mclk2=mclk1;
assign mclk=mclk1;



reg [7:0] sregt;



initial micLRSel <= 0;

initial sregt <= 0;

pwm pw(.ampSD(ampSD), .reset(reset),.mclk(mclk3),.ampPWM(ampPWM),.clk(clk),.dout(sregt));
div_freq df(.clk(clk), .reset(reset),.clkout(mclk1),.led(ledres));


reg micData1;

always @(posedge  mclk)
begin

	if (reset)
		begin
     		sregt<=0;
    		end 
	else 
		begin
		micData1=micData;
		sregt<= {sregt[7:0],micData};
		end
	
	
end

endmodule

FPGA-Game-D1-master/HW/RTL/06PCM-AUDIO-MICROFONO/Version_01/02 verilog/Pruebas/Pruebacorrimiento/microfono_TB.v

module microfono_TB;

reg reset, clk, micData, micData1;  
   

microfono uut(.reset(reset),.micData(micData),.clk(clk));

always
begin

clk =1'b1;
#2;
clk=1'b0;
#2;
end

initial
begin
reset =1'b1;
#10000;
reset =1'b0;
end



initial begin
micData = 1'b0;#64;
micData = 1'b1;#80;
micData = 1'b0;#75; 
micData = 1'b1;#34;
micData = 1'b0;#75;
micData = 1'b1;#80;
micData = 1'b0;#75;
micData = 1'b0;#450;
micData = 1'b1;#100;
micData = 1'b0;#64;
micData = 1'b1;#80;
micData = 1'b0;#75; 
micData = 1'b1;#34;
micData = 1'b0;#75;
micData = 1'b1;#80;
micData = 1'b0;#75;
micData = 1'b0;#450;
micData = 1'b1;#100;
micData = 1'b0;#64;
micData = 1'b1;#80;
micData = 1'b0;#75; 
micData = 1'b1;#34;
micData = 1'b0;#75;
micData = 1'b1;#80;
micData = 1'b0;#75;
micData = 1'b0;#450;
micData = 1'b1;#100;
micData = 1'b0;#64;
micData = 1'b1;#80;
micData = 1'b0;#75; 
micData = 1'b1;#34;
micData = 1'b0;#75;
micData = 1'b1;#80;
micData = 1'b0;#75;
micData = 1'b0;#450;
micData = 1'b1;#100;
micData = 1'b0;#64;
micData = 1'b1;#80;
micData = 1'b0;#75; 
micData = 1'b1;#34;
micData = 1'b0;#75;
micData = 1'b1;#80;
micData = 1'b0;#75;
micData = 1'b0;#450;
micData = 1'b1;#100;
micData = 1'b0;#64;
micData = 1'b1;#80;
micData = 1'b0;#75; 
micData = 1'b1;#34;
micData = 1'b0;#75;
micData = 1'b1;#80;
micData = 1'b0;#75;
micData = 1'b0;#450;
micData = 1'b1;#100;
micData = 1'b0;#64;
micData = 1'b1;#80;
micData = 1'b0;#75; 
micData = 1'b1;#34;
micData = 1'b0;#75;
micData = 1'b1;#80;
micData = 1'b0;#75;
micData = 1'b0;#450;
micData = 1'b1;#100;
micData = 1'b0;#64;
micData = 1'b1;#80;
micData = 1'b0;#75; 
micData = 1'b1;#34;
micData = 1'b0;#75;
micData = 1'b1;#80;
micData = 1'b0;#75;
micData = 1'b0;#450;
micData = 1'b1;#100;
micData = 1'b0;#64;
micData = 1'b1;#80;
micData = 1'b0;#75; 
micData = 1'b1;#34;
micData = 1'b0;#75;
micData = 1'b1;#80;
micData = 1'b0;#75;
micData = 1'b0;#450;
micData = 1'b1;#100;
micData = 1'b0;#64;
micData = 1'b1;#80;
micData = 1'b0;#75; 
micData = 1'b1;#34;
micData = 1'b0;#75;
micData = 1'b1;#80;
micData = 1'b0;#75;
micData = 1'b0;#450;
micData = 1'b1;#100;
micData = 1'b0;#64;
micData = 1'b1;#80;
micData = 1'b0;#75; 
micData = 1'b1;#34;
micData = 1'b0;#75;
micData = 1'b1;#80;
micData = 1'b0;#75;
micData = 1'b0;#450;
micData = 1'b1;#100;
micData = 1'b0;#64;
micData = 1'b1;#80;
micData = 1'b0;#75; 
micData = 1'b1;#34;
micData = 1'b0;#75;
micData = 1'b1;#80;
micData = 1'b0;#75;
micData = 1'b0;#450;
micData = 1'b1;#100;
micData = 1'b0;#64;
micData = 1'b1;#80;
micData = 1'b0;#75; 
micData = 1'b1;#34;
micData = 1'b0;#75;
micData = 1'b1;#80;
micData = 1'b0;#75;
micData = 1'b0;#450;
micData = 1'b1;#100;
micData = 1'b0;#64;
micData = 1'b1;#80;
micData = 1'b0;#75; 
micData = 1'b1;#34;
micData = 1'b0;#75;
micData = 1'b1;#80;
micData = 1'b0;#75;
micData = 1'b0;#450;
micData = 1'b1;#100;
micData = 1'b0;#64;
micData = 1'b1;#80;
micData = 1'b0;#75; 
micData = 1'b1;#34;
micData = 1'b0;#75;
micData = 1'b1;#80;
micData = 1'b0;#75;
micData = 1'b0;#450;
micData = 1'b1;#100;
micData = 1'b0;#64;
micData = 1'b1;#80;
micData = 1'b0;#75; 
micData = 1'b1;#34;
micData = 1'b0;#75;
micData = 1'b1;#80;
micData = 1'b0;#75;
micData = 1'b0;#450;
micData = 1'b1;#100;
micData = 1'b0;#64;
micData = 1'b1;#80;
micData = 1'b0;#75; 
micData = 1'b1;#34;
micData = 1'b0;#75;
micData = 1'b1;#80;
micData = 1'b0;#75;
micData = 1'b0;#450;
micData = 1'b1;#100;
micData = 1'b0;#64;
micData = 1'b1;#80;
micData = 1'b0;#75; 
micData = 1'b1;#34;
micData = 1'b0;#75;
micData = 1'b1;#80;
micData = 1'b0;#75;
micData = 1'b0;#450;
micData = 1'b1;#100;
micData = 1'b0;#64;
micData = 1'b1;#80;
micData = 1'b0;#75; 
micData = 1'b1;#34;
micData = 1'b0;#75;
micData = 1'b1;#80;
micData = 1'b0;#75;
micData = 1'b0;#450;
micData = 1'b1;#100;
micData = 1'b0;#64;
micData = 1'b1;#80;
micData = 1'b0;#75; 
micData = 1'b1;#34;
micData = 1'b0;#75;
micData = 1'b1;#80;
micData = 1'b0;#75;
micData = 1'b0;#450;
micData = 1'b1;#100;
micData = 1'b0;#64;
micData = 1'b1;#80;
micData = 1'b0;#75; 
micData = 1'b1;#34;
micData = 1'b0;#75;
micData = 1'b1;#80;
micData = 1'b0;#75;
micData = 1'b0;#450;
micData = 1'b1;#100;
micData = 1'b0;#64;
micData = 1'b1;#80;
micData = 1'b0;#75; 
micData = 1'b1;#34;
micData = 1'b0;#75;
micData = 1'b1;#80;
micData = 1'b0;#75;
micData = 1'b0;#450;
micData = 1'b1;#100;
micData = 1'b0;#64;
micData = 1'b1;#80;
micData = 1'b0;#75; 
micData = 1'b1;#34;
micData = 1'b0;#75;
micData = 1'b1;#80;
micData = 1'b0;#75;
micData = 1'b0;#450;
micData = 1'b1;#100;
micData = 1'b0;#64;
micData = 1'b1;#80;
micData = 1'b0;#75; 
micData = 1'b1;#34;
micData = 1'b0;#75;
micData = 1'b1;#80;
micData = 1'b0;#75;
micData = 1'b0;#450;
micData = 1'b1;#100;
micData = 1'b0;#64;
micData = 1'b1;#80;
micData = 1'b0;#75; 
micData = 1'b1;#34;
micData = 1'b0;#75;
micData = 1'b1;#80;
micData = 1'b0;#75;
micData = 1'b0;#450;
micData = 1'b1;#100;
micData = 1'b0;#64;
micData = 1'b1;#80;
micData = 1'b0;#75; 
micData = 1'b1;#34;
micData = 1'b0;#75;
micData = 1'b1;#80;
micData = 1'b0;#75;
micData = 1'b0;#450;
micData = 1'b1;#100;
micData = 1'b0;#64;
micData = 1'b1;#80;
micData = 1'b0;#75; 
micData = 1'b1;#34;
micData = 1'b0;#75;
micData = 1'b1;#80;
micData = 1'b0;#75;
micData = 1'b0;#450;
micData = 1'b1;#100;
micData = 1'b0;#64;
micData = 1'b1;#80;
micData = 1'b0;#75; 
micData = 1'b1;#34;
micData = 1'b0;#75;
micData = 1'b1;#80;
micData = 1'b0;#75;
micData = 1'b0;#450;
micData = 1'b1;#100;
micData = 1'b0;#64;
micData = 1'b1;#80;
micData = 1'b0;#75; 
micData = 1'b1;#34;
micData = 1'b0;#75;
micData = 1'b1;#80;
micData = 1'b0;#75;
micData = 1'b0;#450;
micData = 1'b1;#100;
micData = 1'b0;#64;
micData = 1'b1;#80;
micData = 1'b0;#75; 
micData = 1'b1;#34;
micData = 1'b0;#75;
micData = 1'b1;#80;
micData = 1'b0;#75;
micData = 1'b0;#450;
micData = 1'b1;#100;
micData = 1'b0;#64;
micData = 1'b1;#80;
micData = 1'b0;#75; 
micData = 1'b1;#34;
micData = 1'b0;#75;
micData = 1'b1;#80;
micData = 1'b0;#75;
micData = 1'b0;#450;
micData = 1'b1;#100;
micData = 1'b0;#64;
micData = 1'b1;#80;
micData = 1'b0;#75; 
micData = 1'b1;#34;
micData = 1'b0;#75;
micData = 1'b1;#80;
micData = 1'b0;#75;
micData = 1'b0;#450;
micData = 1'b1;#100;
micData = 1'b0;#64;
micData = 1'b1;#80;
micData = 1'b0;#75; 
micData = 1'b1;#34;
micData = 1'b0;#75;
micData = 1'b1;#80;
micData = 1'b0;#75;
micData = 1'b0;#450;
micData = 1'b1;#100;
micData = 1'b0;#64;
micData = 1'b1;#80;
micData = 1'b0;#75; 
micData = 1'b1;#34;
micData = 1'b0;#75;
micData = 1'b1;#80;
micData = 1'b0;#75;
micData = 1'b0;#450;
micData = 1'b1;#100;
micData = 1'b0;#64;
micData = 1'b1;#80;
micData = 1'b0;#75; 
micData = 1'b1;#34;
micData = 1'b0;#75;
micData = 1'b1;#80;
micData = 1'b0;#75;
micData = 1'b0;#450;
micData = 1'b1;#100;
micData = 1'b0;#64;
micData = 1'b1;#80;
micData = 1'b0;#75; 
micData = 1'b1;#34;
micData = 1'b0;#75;
micData = 1'b1;#80;
micData = 1'b0;#75;
micData = 1'b0;#450;
micData = 1'b1;#100;
micData = 1'b1;#100;
micData = 1'b0;#64;
micData = 1'b1;#80;
micData = 1'b0;#75; 
micData = 1'b1;#34;
micData = 1'b0;#75;
micData = 1'b1;#80;
micData = 1'b0;#75;
micData = 1'b0;#450;
micData = 1'b1;#100;
micData = 1'b0;#64;
micData = 1'b1;#80;
micData = 1'b0;#75; 
micData = 1'b1;#34;
micData = 1'b0;#75;
micData = 1'b1;#80;
micData = 1'b0;#75;
micData = 1'b0;#450;
micData = 1'b1;#100;
micData = 1'b0;#64;
micData = 1'b1;#80;
micData = 1'b0;#75; 
micData = 1'b1;#34;
micData = 1'b0;#75;
micData = 1'b1;#80;
micData = 1'b0;#75;
micData = 1'b0;#450;
micData = 1'b1;#100;
micData = 1'b0;#64;
micData = 1'b1;#80;
micData = 1'b0;#75; 
micData = 1'b1;#34;
micData = 1'b0;#75;
micData = 1'b1;#80;
micData = 1'b0;#75;
micData = 1'b0;#450;
micData = 1'b1;#100;
micData = 1'b0;#64;
micData = 1'b1;#80;
micData = 1'b0;#75; 
micData = 1'b1;#34;
micData = 1'b0;#75;
micData = 1'b1;#80;
micData = 1'b0;#75;
micData = 1'b0;#450;
micData = 1'b1;#100;
micData = 1'b0;#64;
micData = 1'b1;#80;
micData = 1'b0;#75; 
micData = 1'b1;#34;
micData = 1'b0;#75;
micData = 1'b1;#80;
micData = 1'b0;#75;
micData = 1'b0;#450;
micData = 1'b1;#100;
micData = 1'b0;#64;
micData = 1'b1;#80;
micData = 1'b0;#75; 
micData = 1'b1;#34;
micData = 1'b0;#75;
micData = 1'b1;#80;
micData = 1'b0;#75;
micData = 1'b0;#450;
micData = 1'b1;#100;
micData = 1'b0;#64;
micData = 1'b1;#80;
micData = 1'b0;#75; 
micData = 1'b1;#34;
micData = 1'b0;#75;
micData = 1'b1;#80;
micData = 1'b0;#75;
micData = 1'b0;#450;
micData = 1'b1;#100;
micData = 1'b0;#64;
micData = 1'b1;#80;
micData = 1'b0;#75; 
micData = 1'b1;#34;
micData = 1'b0;#75;
micData = 1'b1;#80;
micData = 1'b0;#75;
micData = 1'b0;#450;
micData = 1'b1;#100;
micData = 1'b0;#64;
micData = 1'b1;#80;
micData = 1'b0;#75; 
micData = 1'b1;#34;
micData = 1'b0;#75;
micData = 1'b1;#80;
micData = 1'b0;#75;
micData = 1'b0;#450;
micData = 1'b1;#100;
end
	
initial begin: TEST_CASE
     $dumpfile("microfono_TB.vcd");
     $dumpvars(-1, uut);
     #(100000) $finish;
   end

endmodule //

FPGA-Game-D1-master/HW/RTL/06PCM-AUDIO-MICROFONO/Version_01/02 verilog/Pruebas/Pruebacorrimiento/simulation/microfono_TB.vcd
$date
	Thu Nov 30 09:22:04 2017
$end
$version
	Icarus Verilog
$end
$timescale
	1s
$end
$scope module microfono_TB $end
$scope module uut $end
$var wire 1 ! clk $end
$var wire 1 " mclk $end
$var wire 1 # mclk2 $end
$var wire 1 $ mclk3 $end
$var wire 1 % micData $end
$var wire 1 & reset $end
$var wire 1 ' mclk1 $end
$var wire 1 ( ledres $end
$var wire 1 ) ampSD $end
$var wire 1 * ampPWM $end
$var reg 1 + micData1 $end
$var reg 1 , micLRSel $end
$var reg 8 - sregt [7:0] $end
$scope module df $end
$var wire 1 ! clk $end
$var wire 1 & reset $end
$var reg 1 ' clkout $end
$var reg 32 . count [31:0] $end
$var reg 1 ( led $end
$upscope $end
$scope module pw $end
$var wire 1 ! clk $end
$var wire 1 / done1 $end
$var wire 8 0 dout [7:0] $end
$var wire 1 1 ledres $end
$var wire 1 $ mclk $end
$var wire 1 & reset $end
$var reg 1 * ampPWM $end
$var reg 1 ) ampSD $end
$var reg 8 2 count [7:0] $end
$upscope $end
$upscope $end
$upscope $end
$enddefinitions $end
#0
$dumpvars
bx 2
z1
b0 0
z/
b10000 .
b0 -
0,
x+
x*
1)
0(
0'
1&
0%
0$
0#
0"
1!
$end
#2
0!
#4
1!
#6
0!
#8
1!
#10
0!
#12
1!
#14
0!
#16
1!
#18
0!
#20
1!
#22
0!
#24
1!
#26
0!
#28
1!
#30
0!
#32
1!
#34
0!
#36
1!
#38
0!
#40
1!
#42
0!
#44
1!
#46
0!
#48
1!
#50
0!
#52
1!
#54
0!
#56
1!
#58
0!
#60
1!
#62
0!
#64
1!
1%
#66
0!
#68
1!
#70
0!
#72
1!
#74
0!
#76
1!
#78
0!
#80
1!
#82
0!
#84
1!
#86
0!
#88
1!
#90
0!
#92
1!
#94
0!
#96
1!
#98
0!
#100
1!
#102
0!
#104
1!
#106
0!
#108
1!
#110
0!
#112
1!
#114
0!
#116
1!
#118
0!
#120
1!
#122
0!
#124
1!
#126
0!
#128
1!
#130
0!
#132
1!
#134
0!
#136
1!
#138
0!
#140
1!
#142
0!
#144
1!
0%
#146
0!
#148
1!
#150
0!
#152
1!
#154
0!
#156
1!
#158
0!
#160
1!
#162
0!
#164
1!
#166
0!
#168
1!
#170
0!
#172
1!
#174
0!
#176
1!
#178
0!
#180
1!
#182
0!
#184
1!
#186
0!
#188
1!
#190
0!
#192
1!
#194
0!
#196
1!
#198
0!
#200
1!
#202
0!
#204
1!
#206
0!
#208
1!
#210
0!
#212
1!
#214
0!
#216
1!
#218
0!
#219
1%
#220
1!
#222
0!
#224
1!
#226
0!
#228
1!
#230
0!
#232
1!
#234
0!
#236
1!
#238
0!
#240
1!
#242
0!
#244
1!
#246
0!
#248
1!
#250
0!
#252
1!
#253
0%
#254
0!
#256
1!
#258
0!
#260
1!
#262
0!
#264
1!
#266
0!
#268
1!
#270
0!
#272
1!
#274
0!
#276
1!
#278
0!
#280
1!
#282
0!
#284
1!
#286
0!
#288
1!
#290
0!
#292
1!
#294
0!
#296
1!
#298
0!
#300
1!
#302
0!
#304
1!
#306
0!
#308
1!
#310
0!
#312
1!
#314
0!
#316
1!
#318
0!
#320
1!
#322
0!
#324
1!
#326
0!
#328
1!
1%
#330
0!
#332
1!
#334
0!
#336
1!
#338
0!
#340
1!
#342
0!
#344
1!
#346
0!
#348
1!
#350
0!
#352
1!
#354
0!
#356
1!
#358
0!
#360
1!
#362
0!
#364
1!
#366
0!
#368
1!
#370
0!
#372
1!
#374
0!
#376
1!
#378
0!
#380
1!
#382
0!
#384
1!
#386
0!
#388
1!
#390
0!
#392
1!
#394
0!
#396
1!
#398
0!
#400
1!
#402
0!
#404
1!
#406
0!
#408
1!
0%
#410
0!
#412
1!
#414
0!
#416
1!
#418
0!
#420
1!
#422
0!
#424
1!
#426
0!
#428
1!
#430
0!
#432
1!
#434
0!
#436
1!
#438
0!
#440
1!
#442
0!
#444
1!
#446
0!
#448
1!
#450
0!
#452
1!
#454
0!
#456
1!
#458
0!
#460
1!
#462
0!
#464
1!
#466
0!
#468
1!
#470
0!
#472
1!
#474
0!
#476
1!
#478
0!
#480
1!
#482
0!
#484
1!
#486
0!
#488
1!
#490
0!
#492
1!
#494
0!
#496
1!
#498
0!
#500
1!
#502
0!
#504
1!
#506
0!
#508
1!
#510
0!
#512
1!
#514
0!
#516
1!
#518
0!
#520
1!
#522
0!
#524
1!
#526
0!
#528
1!
#530
0!
#532
1!
#534
0!
#536
1!
#538
0!
#540
1!
#542
0!
#544
1!
#546
0!
#548
1!
#550
0!
#552
1!
#554
0!
#556
1!
#558
0!
#560
1!
#562
0!
#564
1!
#566
0!
#568
1!
#570
0!
#572
1!
#574
0!
#576
1!
#578
0!
#580
1!
#582
0!
#584
1!
#586
0!
#588
1!
#590
0!
#592
1!
#594
0!
#596
1!
#598
0!
#600
1!
#602
0!
#604
1!
#606
0!
#608
1!
#610
0!
#612
1!
#614
0!
#616
1!
#618
0!
#620
1!
#622
0!
#624
1!
#626
0!
#628
1!
#630
0!
#632
1!
#634
0!
#636
1!
#638
0!
#640
1!
#642
0!
#644
1!
#646
0!
#648
1!
#650
0!
#652
1!
#654
0!
#656
1!
#658
0!
#660
1!
#662
0!
#664
1!
#666
0!
#668
1!
#670
0!
#672
1!
#674
0!
#676
1!
#678
0!
#680
1!
#682
0!
#684
1!
#686
0!
#688
1!
#690
0!
#692
1!
#694
0!
#696
1!
#698
0!
#700
1!
#702
0!
#704
1!
#706
0!
#708
1!
#710
0!
#712
1!
#714
0!
#716
1!
#718
0!
#720
1!
#722
0!
#724
1!
#726
0!
#728
1!
#730
0!
#732
1!
#734
0!
#736
1!
#738
0!
#740
1!
#742
0!
#744
1!
#746
0!
#748
1!
#750
0!
#752
1!
#754
0!
#756
1!
#758
0!
#760
1!
#762
0!
#764
1!
#766
0!
#768
1!
#770
0!
#772
1!
#774
0!
#776
1!
#778
0!
#780
1!
#782
0!
#784
1!
#786
0!
#788
1!
#790
0!
#792
1!
#794
0!
#796
1!
#798
0!
#800
1!
#802
0!
#804
1!
#806
0!
#808
1!
#810
0!
#812
1!
#814
0!
#816
1!
#818
0!
#820
1!
#822
0!
#824
1!
#826
0!
#828
1!
#830
0!
#832
1!
#834
0!
#836
1!
#838
0!
#840
1!
#842
0!
#844
1!
#846
0!
#848
1!
#850
0!
#852
1!
#854
0!
#856
1!
#858
0!
#860
1!
#862
0!
#864
1!
#866
0!
#868
1!
#870
0!
#872
1!
#874
0!
#876
1!
#878
0!
#880
1!
#882
0!
#884
1!
#886
0!
#888
1!
#890
0!
#892
1!
#894
0!
#896
1!
#898
0!
#900
1!
#902
0!
#904
1!
#906
0!
#908
1!
#910
0!
#912
1!
#914
0!
#916
1!
#918
0!
#920
1!
#922
0!
#924
1!
#926
0!
#928
1!
#930
0!
#932
1!
#933
1%
