FPGA-Game-D1-master/HW/RTL/06PCM-AUDIO-MICROFONO/Version_01/02 verilog/Otros/Audio-SB/Microfono/div_freq.v
module div_freq #(
              parameter   fi     = 100000000 ,           
              parameter   fs	 = 20000000        
  )(input clk, output reg clkout,input reset);





reg [15:0] count;

always @(posedge  clk)
begin
	if (reset) begin
		count <= fi/fs;
		clkout <=0;
	end
	else begin
		count <=count-1;
		if (count==0)begin
			clkout <=~clkout;
			count <= fi/fs;
		end	
	end	
end


endmodule

FPGA-Game-D1-master/HW/RTL/06PCM-AUDIO-MICROFONO/Version_01/02 verilog/Otros/Audio-SB/Altavoz/altavoz.v
module altavoz
(
	input		enable,
	input 		[15:0] sregt,
	input		clk,
	output		bclk,
	output		rlclk,
	output  	dataout,
	input		reset,
	output		done

);

reg [16:0] count=0;
reg done=0;
reg rlclk=0;
reg [15:0] sreg=16'h0;
wire init;



div_freq df(.clk(clk), .reset(reset),.clkout(bclk));
assign init =(count==0)?1:0;
assign dataout = sreg[15];

	
always @(posedge  bclk)
begin
	
	if (init)
		sreg <= sregt;	
	 if (enable) 
		begin
		if (count<=15)  /*envia bit por bit*/
			begin
			sreg<=sreg<<1;		
			count<=count+1;
			end
		
		else 
			begin
			rlclk=!rlclk;     /* habilita canal R/L*/
			count<=0;   
			done<=1;     /* confirma que ya se enviaron todos los bits*/
			end								
						
	end	


end

endmodule

FPGA-Game-D1-master/HW/RTL/06PCM-AUDIO-MICROFONO/Version_01/02 verilog/Otros/Audio-SB/v1/Altavoz/altavoz_TB.v
module altavoz_TB;

reg clk;
reg [15:0] sregt;
reg enable;
reg bclk;
reg rlclk;
reg done;
reg reset;

altavoz uut(.enable(enable),.reset(reset),.sregt(sregt),.clk(clk));

always
begin

clk =1'b1;
#2;
clk=1'b0;
#2;
end

initial
begin
reset =1'b1;
#10;
reset =1'b0;

sregt=16'b101000100101010;
#50; enable=1;
end 

	
initial begin: TEST_CASE
     $dumpfile("altavoz_TB.vcd");
     $dumpvars(-1, uut);
     #(1000) $finish;
   end

endmodule //

FPGA-Game-D1-master/HW/RTL/06PCM-AUDIO-MICROFONO/Version_01/02 verilog/Otros/Audio-SB/v1/Altavoz/simulation/altavoz_TB.vcd
$date
	Wed Oct 11 09:34:01 2017
$end
$version
	Icarus Verilog
$end
$timescale
	1s
$end
$scope module altavoz_TB $end
$scope module uut $end
$var wire 1 ! clk $end
$var wire 1 " enable $end
$var wire 1 # reset $end
$var wire 16 $ sregt [15:0] $end
$var wire 1 % init $end
$var wire 1 & dataout $end
$var wire 1 ' bclk $end
$var reg 17 ( count [16:0] $end
$var reg 1 ) done $end
$var reg 1 * rlclk $end
$var reg 16 + sreg [15:0] $end
$scope module df $end
$var wire 1 ! clk $end
$var wire 1 # reset $end
$var reg 1 ' clkout $end
$var reg 16 , count [15:0] $end
$upscope $end
$upscope $end
$upscope $end
$enddefinitions $end
#0
$dumpvars
b100 ,
b0 +
0*
0)
b0 (
0'
0&
1%
bx $
1#
x"
1!
$end
#2
0!
#4
1!
#6
0!
#8
1!
#10
0!
b101000100101010 $
0#
#12
b11 ,
1!
#14
0!
#16
b10 ,
1!
#18
0!
#20
b1 ,
1!
#22
0!
#24
b0 ,
1!
#26
0!
#28
b101000100101010 +
1'
b100 ,
1!
#30
0!
#32
b11 ,
1!
#34
0!
#36
b10 ,
1!
#38
0!
#40
b1 ,
1!
#42
0!
#44
b0 ,
1!
#46
0!
#48
0'
b100 ,
1!
#50
0!
#52
b11 ,
1!
#54
0!
#56
b10 ,
1!
#58
0!
#60
b1 ,
1!
1"
#62
0!
#64
b0 ,
1!
#66
0!
#68
0%
1&
b1 (
b1010001001010100 +
1'
b100 ,
1!
#70
0!
#72
b11 ,
1!
#74
0!
#76
b10 ,
1!
#78
0!
#80
b1 ,
1!
#82
0!
#84
b0 ,
1!
#86
0!
#88
0'
b100 ,
1!
#90
0!
#92
b11 ,
1!
#94
0!
#96
b10 ,
1!
#98
0!
#100
b1 ,
1!
#102
0!
#104
b0 ,
1!
#106
0!
#108
0&
b10 (
b100010010101000 +
1'
b100 ,
1!
#110
0!
#112
b11 ,
1!
#114
0!
#116
b10 ,
1!
#118
0!
#120
b1 ,
1!
#122
0!
#124
b0 ,
1!
#126
0!
#128
0'
b100 ,
1!
#130
0!
#132
b11 ,
1!
#134
0!
#136
b10 ,
1!
#138
0!
#140
b1 ,
1!
#142
0!
#144
b0 ,
1!
#146
0!
#148
1&
b11 (
b1000100101010000 +
1'
b100 ,
1!
#150
0!
#152
b11 ,
1!
#154
0!
#156
b10 ,
1!
#158
0!
#160
b1 ,
1!
#162
0!
#164
b0 ,
1!
#166
0!
#168
0'
b100 ,
1!
#170
0!
#172
b11 ,
1!
#174
0!
#176
b10 ,
1!
#178
0!
#180
b1 ,
1!
#182
0!
#184
b0 ,
1!
#186
0!
#188
0&
b100 (
b1001010100000 +
1'
b100 ,
1!
#190
0!
#192
b11 ,
1!
#194
0!
#196
b10 ,
1!
#198
0!
#200
b1 ,
1!
#202
0!
#204
b0 ,
1!
#206
0!
#208
0'
b100 ,
1!
#210
0!
#212
b11 ,
1!
#214
0!
#216
b10 ,
1!
#218
0!
#220
b1 ,
1!
#222
0!
#224
b0 ,
1!
#226
0!
#228
b101 (
b10010101000000 +
1'
b100 ,
1!
#230
0!
#232
b11 ,
1!
#234
0!
#236
b10 ,
1!
#238
0!
#240
b1 ,
1!
#242
0!
#244
b0 ,
1!
#246
0!
#248
0'
b100 ,
1!
#250
0!
#252
b11 ,
1!
#254
0!
#256
b10 ,
1!
#258
0!
#260
b1 ,
1!
#262
0!
#264
b0 ,
1!
#266
0!
#268
b110 (
b100101010000000 +
1'
b100 ,
1!
#270
0!
#272
b11 ,
1!
#274
0!
#276
b10 ,
1!
#278
0!
#280
b1 ,
1!
#282
0!
#284
b0 ,
1!
#286
0!
#288
0'
b100 ,
1!
#290
0!
#292
b11 ,
1!
#294
0!
#296
b10 ,
1!
#298
0!
#300
b1 ,
1!
#302
0!
#304
b0 ,
1!
#306
0!
#308
1&
b111 (
b1001010100000000 +
1'
b100 ,
1!
#310
0!
#312
b11 ,
1!
#314
0!
#316
b10 ,
1!
#318
0!
#320
b1 ,
1!
#322
0!
#324
b0 ,
1!
#326
0!
#328
0'
b100 ,
1!
#330
0!
#332
b11 ,
1!
#334
0!
#336
b10 ,
1!
#338
0!
#340
b1 ,
1!
#342
0!
#344
b0 ,
1!
#346
0!
#348
0&
b1000 (
b10101000000000 +
1'
b100 ,
1!
#350
0!
#352
b11 ,
1!
#354
0!
#356
b10 ,
1!
#358
0!
#360
b1 ,
1!
#362
0!
#364
b0 ,
1!
#366
0!
#368
0'
b100 ,
1!
#370
0!
#372
b11 ,
1!
#374
0!
#376
b10 ,
1!
#378
0!
#380
b1 ,
1!
#382
0!
#384
b0 ,
1!
#386
0!
#388
b1001 (
b101010000000000 +
1'
b100 ,
1!
#390
0!
#392
b11 ,
1!
#394
0!
#396
b10 ,
1!
#398
0!
#400
b1 ,
1!
#402
0!
#404
b0 ,
1!
#406
0!
#408
0'
b100 ,
1!
#410
0!
#412
b11 ,
1!
#414
0!
#416
b10 ,
1!
#418
0!
#420
b1 ,
1!
#422
0!
#424
b0 ,
1!
#426
0!
#428
1&
b1010 (
b1010100000000000 +
1'
b100 ,
1!
#430
0!
#432
b11 ,
1!
#434
0!
#436
b10 ,
1!
#438
0!
#440
b1 ,
1!
#442
0!
#444
b0 ,
1!
#446
0!
#448
0'
b100 ,
1!
#450
0!
#452
b11 ,
1!
#454
0!
#456
b10 ,
1!
#458
0!
#460
b1 ,
1!
#462
0!
#464
b0 ,
1!
#466
0!
#468
0&
b1011 (
b101000000000000 +
1'
b100 ,
1!
#470
0!
#472
b11 ,
1!
#474
0!
#476
b10 ,
1!
#478
0!
#480
b1 ,
1!
#482
0!
#484
b0 ,
1!
#486
0!
#488
0'
b100 ,
1!
#490
0!
#492
b11 ,
1!
#494
0!
#496
b10 ,
1!
#498
0!
#500
b1 ,
1!
#502
0!
#504
b0 ,
1!
#506
0!
#508
1&
b1100 (
b1010000000000000 +
1'
b100 ,
1!
#510
0!
#512
b11 ,
1!
#514
0!
#516
b10 ,
1!
#518
0!
#520
b1 ,
1!
#522
0!
#524
b0 ,
1!
#526
0!
#528
0'
b100 ,
1!
#530
0!
#532
b11 ,
1!
#534
0!
#536
b10 ,
1!
#538
0!
#540
b1 ,
1!
#542
0!
#544
b0 ,
1!
#546
0!
#548
0&
b1101 (
b100000000000000 +
1'
b100 ,
1!
#550
0!
#552
b11 ,
1!
#554
0!
#556
b10 ,
1!
#558
0!
#560
b1 ,
1!
#562
0!
#564
b0 ,
1!
#566
0!
#568
0'
b100 ,
1!
#570
0!
#572
b11 ,
1!
#574
0!
#576
b10 ,
1!
#578
0!
#580
b1 ,
1!
#582
0!
#584
b0 ,
1!
#586
0!
#588
1&
b1110 (
b1000000000000000 +
1'
b100 ,
1!
#590
0!
#592
b11 ,
1!
#594
0!
#596
b10 ,
1!
#598
0!
#600
b1 ,
1!
#602
0!
#604
b0 ,
1!
#606
0!
#608
0'
b100 ,
1!
#610
0!
#612
b11 ,
1!
#614
0!
#616
b10 ,
1!
#618
0!
#620
b1 ,
1!
#622
0!
#624
b0 ,
1!
#626
0!
#628
0&
b1111 (
b0 +
1'
b100 ,
1!
#630
0!
#632
b11 ,
1!
#634
0!
#636
b10 ,
1!
#638
0!
#640
b1 ,
1!
#642
0!
#644
b0 ,
1!
#646
0!
#648
0'
b100 ,
1!
#650
0!
#652
b11 ,
1!
#654
0!
#656
b10 ,
1!
#658
0!
#660
b1 ,
1!
#662
0!
#664
b0 ,
1!
#666
0!
#668
b10000 (
1'
b100 ,
1!
#670
0!
#672
b11 ,
1!
#674
0!
#676
b10 ,
1!
#678
0!
#680
b1 ,
1!
#682
0!
#684
b0 ,
1!
#686
0!
#688
0'
b100 ,
1!
#690
0!
#692
b11 ,
1!
#694
0!
#696
b10 ,
1!
#698
0!
#700
b1 ,
1!
#702
0!
#704
b0 ,
1!
#706
0!
#708
1%
1)
b0 (
1*
1'
b100 ,
1!
#710
0!
#712
b11 ,
1!
#714
0!
#716
b10 ,
1!
#718
0!
#720
b1 ,
1!
#722
0!
#724
b0 ,
1!
#726
0!
#728
0'
b100 ,
1!
#730
0!
#732
b11 ,
1!
#734
0!
#736
b10 ,
1!
#738
0!
#740
b1 ,
1!
#742
0!
#744
b0 ,
1!
#746
0!
#748
0%
b1 (
b0 +
1'
b100 ,
1!
#750
0!
#752
b11 ,
1!
#754
0!
#756
b10 ,
1!
#758
0!
#760
b1 ,
1!
#762
0!
#764
b0 ,
1!
#766
0!
#768
0'
b100 ,
1!
#770
0!
#772
b11 ,
1!
#774
0!
#776
b10 ,
1!
#778
0!
#780
b1 ,
1!
#782
0!
#784
b0 ,
1!
#786
0!
#788
b10 (
1'
b100 ,
1!
#790
0!
#792
b11 ,
1!
#794
0!
#796
b10 ,
1!
#798
0!
#800
b1 ,
1!
#802
0!
#804
b0 ,
1!
#806
0!
#808
0'
b100 ,
1!
#810
0!
#812
b11 ,
1!
#814
0!
#816
b10 ,
1!
#818
0!
#820
b1 ,
1!
#822
0!
#824
b0 ,
1!
#826
0!
#828
b11 (
1'
b100 ,
1!
#830
0!
#832
b11 ,
1!
#834
0!
#836
b10 ,
1!
#838
0!
#840
b1 ,
1!
#842
0!
#844
b0 ,
1!
#846
0!
#848
0'
b100 ,
1!
#850
0!
#852
b11 ,
1!
#854
0!
#856
b10 ,
1!
#858
0!
#860
b1 ,
1!
#862
0!
#864
b0 ,
1!
#866
0!
#868
b100 (
1'
b100 ,
1!
#870
0!
#872
b11 ,
1!
#874
0!
#876
b10 ,
1!
#878
0!
#880
b1 ,
1!
#882
0!
#884
b0 ,
1!
#886
0!
#888
0'
b100 ,
1!
#890
0!
#892
b11 ,
1!
#894
0!
#896
b10 ,
1!
#898
0!
#900
b1 ,
1!
#902
0!
#904
b0 ,
1!
#906
0!
#908
b101 (
1'
b100 ,
1!
#910
0!
#912
b11 ,
1!
#914
0!
#916
b10 ,
1!
#918
0!
#920
b1 ,
1!
#922
0!
#924
b0 ,
1!
#926
0!
#928
0'
b100 ,
1!
#930
0!
#932
b11 ,
1!
#934
0!
#936
b10 ,
1!
#938
0!
#940
b1 ,
1!
#942
0!
#944
b0 ,
1!
#946
0!
#948
b110 (
1'
b100 ,
1!
#950
0!
#952
b11 ,
1!
#954
0!
#956
b10 ,
1!
#958
0!
#960
b1 ,
1!
#962
0!
#964
b0 ,
1!
#966
0!
#968
0'
b100 ,
1!
#970
0!
#972
b11 ,
1!
#974
0!
#976
b10 ,
1!
#978
0!
#980
b1 ,
1!
#982
0!
#984
b0 ,
1!
#986
0!
#988
b111 (
1'
b100 ,
1!
#990
0!
#992
b11 ,
1!
#994
0!
#996
b10 ,
1!
#998
0!
#1000
b1 ,
1!
