FPGA-Game-D1-master/HW/RTL/06PCM-AUDIO-MICROFONO/Version_02/02 verilog/ProyectoDigital1/Microfono/DivFreq.v
module DivFreq (reset,clk,en_clk,bclk);

	// ENTRADAS Y SALIDAS DEL SISTEMA

	input wire reset;
	input wire clk;
	input wire en_clk;
	output reg bclk;

	reg [5:0] count = 6'h00;

	//-- Registro

	always @(posedge clk)
		begin
		  if (reset)
			begin
				count = 6'h00;
				bclk = 1'b0;
			end	
		  else
			if (en_clk)
				if (count == 50)
					begin
						count = 6'h01;
						bclk = ~bclk;
					end
				else
					begin
						count = count + 6'h01;
						bclk = bclk;
					end
			else
				begin
					count = count;
					bclk = bclk;
				end
		end
		
endmodule

FPGA-Game-D1-master/HW/RTL/06PCM-AUDIO-MICROFONO/Version_02/02 verilog/ProyectoDigital1/DivFreq/DivFreq_TB.v
`timescale 1ns / 1ns
module DivFreq_TB;

	reg reset;
	reg clk;
	reg en_clk;
	wire bclk;

	DivFreq DUT(
		.reset(reset),
		.clk(clk),
		.en_clk(en_clk),
		.bclk(bclk)
	);

	always
		begin
			#1 clk = ~clk;
		end	

	initial
		begin: TEST_CASE
   			$dumpfile("DivFreq_TB.vcd");
     		$dumpvars(-1, DUT);
			#(500) $finish;
		end
	
	initial
		begin
			clk = 1'b0;
			reset = 1'b1;
			en_clk = 1'b0;

			#5 reset = 1'b0;

			#5 en_clk = 1'b1;
			#10 en_clk = 1'b0;
			#10 en_clk = 1'b1;
			#500 reset = 1'b1;

		end

endmodule

FPGA-Game-D1-master/HW/RTL/06PCM-AUDIO-MICROFONO/Version_02/02 verilog/ProyectoDigital1/DivFreq/simulation/DivFreq_TB.vcd
$date
	Wed Oct 18 06:56:06 2017
$end
$version
	Icarus Verilog
$end
$timescale
	1ns
$end
$scope module DivFreq_TB $end
$scope module DUT $end
$var wire 1 ! clk $end
$var wire 1 " en_clk $end
$var wire 1 # reset $end
$var reg 1 $ bclk $end
$var reg 6 % count [5:0] $end
$upscope $end
$upscope $end
$enddefinitions $end
#0
$dumpvars
b0 %
x$
1#
0"
0!
$end
#1
0$
1!
#2
0!
#3
1!
#4
0!
#5
1!
0#
#6
0!
#7
1!
#8
0!
#9
1!
#10
0!
1"
#11
b1 %
1!
#12
0!
#13
b10 %
1!
#14
0!
#15
b11 %
1!
#16
0!
#17
b100 %
1!
#18
0!
#19
b101 %
1!
#20
0!
0"
#21
1!
#22
0!
#23
1!
#24
0!
#25
1!
#26
0!
#27
1!
#28
0!
#29
1!
#30
0!
1"
#31
b110 %
1!
#32
0!
#33
b111 %
1!
#34
0!
#35
b1000 %
1!
#36
0!
#37
b1001 %
1!
#38
0!
#39
b1010 %
1!
#40
0!
#41
b1011 %
1!
#42
0!
#43
b1100 %
1!
#44
0!
#45
b1101 %
1!
#46
0!
#47
b1110 %
1!
#48
0!
#49
b1111 %
1!
#50
0!
#51
b10000 %
1!
#52
0!
#53
b10001 %
1!
#54
0!
#55
b10010 %
1!
#56
0!
#57
b10011 %
1!
#58
0!
#59
b10100 %
1!
#60
0!
#61
b10101 %
1!
#62
0!
#63
b10110 %
1!
#64
0!
#65
b10111 %
1!
#66
0!
#67
b11000 %
1!
#68
0!
#69
b11001 %
1!
#70
0!
#71
b11010 %
1!
#72
0!
#73
b11011 %
1!
#74
0!
#75
b11100 %
1!
#76
0!
#77
b11101 %
1!
#78
0!
#79
b11110 %
1!
#80
0!
#81
b11111 %
1!
#82
0!
#83
b100000 %
1!
#84
0!
#85
b100001 %
1!
#86
0!
#87
b100010 %
1!
#88
0!
#89
b100011 %
1!
#90
0!
#91
b100100 %
1!
#92
0!
#93
b100101 %
1!
#94
0!
#95
b100110 %
1!
#96
0!
#97
b100111 %
1!
#98
0!
#99
b101000 %
1!
#100
0!
#101
b101001 %
1!
#102
0!
#103
b101010 %
1!
#104
0!
#105
b101011 %
1!
#106
0!
#107
b101100 %
1!
#108
0!
#109
b101101 %
1!
#110
0!
#111
b101110 %
1!
#112
0!
#113
b101111 %
1!
#114
0!
#115
b110000 %
1!
#116
0!
#117
b110001 %
1!
#118
0!
#119
b110010 %
1!
#120
0!
#121
1$
b1 %
1!
#122
0!
#123
b10 %
1!
#124
0!
#125
b11 %
1!
#126
0!
#127
b100 %
1!
#128
0!
#129
b101 %
1!
#130
0!
#131
b110 %
1!
#132
0!
#133
b111 %
1!
#134
0!
#135
b1000 %
1!
#136
0!
#137
b1001 %
1!
#138
0!
#139
b1010 %
1!
#140
0!
#141
b1011 %
1!
#142
0!
#143
b1100 %
1!
#144
0!
#145
b1101 %
1!
#146
0!
#147
b1110 %
1!
#148
0!
#149
b1111 %
1!
#150
0!
#151
b10000 %
1!
#152
0!
#153
b10001 %
1!
#154
0!
#155
b10010 %
1!
#156
0!
#157
b10011 %
1!
#158
0!
#159
b10100 %
1!
#160
0!
#161
b10101 %
1!
#162
0!
#163
b10110 %
1!
#164
0!
#165
b10111 %
1!
#166
0!
#167
b11000 %
1!
#168
0!
#169
b11001 %
1!
#170
0!
#171
b11010 %
1!
#172
0!
#173
b11011 %
1!
#174
0!
#175
b11100 %
1!
#176
0!
#177
b11101 %
1!
#178
0!
#179
b11110 %
1!
#180
0!
#181
b11111 %
1!
#182
0!
#183
b100000 %
1!
#184
0!
#185
b100001 %
1!
#186
0!
#187
b100010 %
1!
#188
0!
#189
b100011 %
1!
#190
0!
#191
b100100 %
1!
#192
0!
#193
b100101 %
1!
#194
0!
#195
b100110 %
1!
#196
0!
#197
b100111 %
1!
#198
0!
#199
b101000 %
1!
#200
0!
#201
b101001 %
1!
#202
0!
#203
b101010 %
1!
#204
0!
#205
b101011 %
1!
#206
0!
#207
b101100 %
1!
#208
0!
#209
b101101 %
1!
#210
0!
#211
b101110 %
1!
#212
0!
#213
b101111 %
1!
#214
0!
#215
b110000 %
1!
#216
0!
#217
b110001 %
1!
#218
0!
#219
b110010 %
1!
#220
0!
#221
0$
b1 %
1!
#222
0!
#223
b10 %
1!
#224
0!
#225
b11 %
1!
#226
0!
#227
b100 %
1!
#228
0!
#229
b101 %
1!
#230
0!
#231
b110 %
1!
#232
0!
#233
b111 %
1!
#234
0!
#235
b1000 %
1!
#236
0!
#237
b1001 %
1!
#238
0!
#239
b1010 %
1!
#240
0!
#241
b1011 %
1!
#242
0!
#243
b1100 %
1!
#244
0!
#245
b1101 %
1!
#246
0!
#247
b1110 %
1!
#248
0!
#249
b1111 %
1!
#250
0!
#251
b10000 %
1!
#252
0!
#253
b10001 %
1!
#254
0!
#255
b10010 %
1!
#256
0!
#257
b10011 %
1!
#258
0!
#259
b10100 %
1!
#260
0!
#261
b10101 %
1!
#262
0!
#263
b10110 %
1!
#264
0!
#265
b10111 %
1!
#266
0!
#267
b11000 %
1!
#268
0!
#269
b11001 %
1!
#270
0!
#271
b11010 %
1!
#272
0!
#273
b11011 %
1!
#274
0!
#275
b11100 %
1!
#276
0!
#277
b11101 %
1!
#278
0!
#279
b11110 %
1!
#280
0!
#281
b11111 %
1!
#282
0!
#283
b100000 %
1!
#284
0!
#285
b100001 %
1!
#286
0!
#287
b100010 %
1!
#288
0!
#289
b100011 %
1!
#290
0!
#291
b100100 %
1!
#292
0!
#293
b100101 %
1!
#294
0!
#295
b100110 %
1!
#296
0!
#297
b100111 %
1!
#298
0!
#299
b101000 %
1!
#300
0!
#301
b101001 %
1!
#302
0!
#303
b101010 %
1!
#304
0!
#305
b101011 %
1!
#306
0!
#307
b101100 %
1!
#308
0!
#309
b101101 %
1!
#310
0!
#311
b101110 %
1!
#312
0!
#313
b101111 %
1!
#314
0!
#315
b110000 %
1!
#316
0!
#317
b110001 %
1!
#318
0!
#319
b110010 %
1!
#320
0!
#321
1$
b1 %
1!
#322
0!
#323
b10 %
1!
#324
0!
#325
b11 %
1!
#326
0!
#327
b100 %
1!
#328
0!
#329
b101 %
1!
#330
0!
#331
b110 %
1!
#332
0!
#333
b111 %
1!
#334
0!
#335
b1000 %
1!
#336
0!
#337
b1001 %
1!
#338
0!
#339
b1010 %
1!
#340
0!
#341
b1011 %
1!
#342
0!
#343
b1100 %
1!
#344
0!
#345
b1101 %
1!
#346
0!
#347
b1110 %
1!
#348
0!
#349
b1111 %
1!
#350
0!
#351
b10000 %
1!
#352
0!
#353
b10001 %
1!
#354
0!
#355
b10010 %
1!
#356
0!
#357
b10011 %
1!
#358
0!
#359
b10100 %
1!
#360
0!
#361
b10101 %
1!
#362
0!
#363
b10110 %
1!
#364
0!
#365
b10111 %
1!
#366
0!
#367
b11000 %
1!
#368
0!
#369
b11001 %
1!
#370
0!
#371
b11010 %
1!
#372
0!
#373
b11011 %
1!
#374
0!
#375
b11100 %
1!
#376
0!
#377
b11101 %
1!
#378
0!
#379
b11110 %
1!
#380
0!
#381
b11111 %
1!
#382
0!
#383
b100000 %
1!
#384
0!
#385
b100001 %
1!
#386
0!
#387
b100010 %
1!
#388
0!
#389
b100011 %
1!
#390
0!
#391
b100100 %
1!
#392
0!
#393
b100101 %
1!
#394
0!
#395
b100110 %
1!
#396
0!
#397
b100111 %
1!
#398
0!
#399
b101000 %
1!
#400
0!
#401
b101001 %
1!
#402
0!
#403
b101010 %
1!
#404
0!
#405
b101011 %
1!
#406
0!
#407
b101100 %
1!
#408
0!
#409
b101101 %
1!
#410
0!
#411
b101110 %
1!
#412
0!
#413
b101111 %
1!
#414
0!
#415
b110000 %
1!
#416
0!
#417
b110001 %
1!
#418
0!
#419
b110010 %
1!
#420
0!
#421
0$
b1 %
1!
#422
0!
#423
b10 %
1!
#424
0!
#425
b11 %
1!
#426
0!
#427
b100 %
1!
#428
0!
#429
b101 %
1!
#430
0!
#431
b110 %
1!
#432
0!
#433
b111 %
1!
#434
0!
#435
b1000 %
1!
#436
0!
#437
b1001 %
1!
#438
0!
#439
b1010 %
1!
#440
0!
#441
b1011 %
1!
#442
0!
#443
b1100 %
1!
#444
0!
#445
b1101 %
1!
#446
0!
#447
b1110 %
1!
#448
0!
#449
b1111 %
1!
#450
0!
#451
b10000 %
1!
#452
0!
#453
b10001 %
1!
#454
0!
#455
b10010 %
1!
#456
0!
#457
b10011 %
1!
#458
0!
#459
b10100 %
1!
#460
0!
#461
b10101 %
1!
#462
0!
#463
b10110 %
1!
#464
0!
#465
b10111 %
1!
#466
0!
#467
b11000 %
1!
#468
0!
#469
b11001 %
1!
#470
0!
#471
b11010 %
1!
#472
0!
#473
b11011 %
1!
#474
0!
#475
b11100 %
1!
#476
0!
#477
b11101 %
1!
#478
0!
#479
b11110 %
1!
#480
0!
#481
b11111 %
1!
#482
0!
#483
b100000 %
1!
#484
0!
#485
b100001 %
1!
#486
0!
#487
b100010 %
1!
#488
0!
#489
b100011 %
1!
#490
0!
#491
b100100 %
1!
#492
0!
#493
b100101 %
1!
#494
0!
#495
b100110 %
1!
#496
0!
#497
b100111 %
1!
#498
0!
#499
b101000 %
1!
