FPGA-Game-D1-master/HW/RTL/06PCM-AUDIO-MICROFONO/Version_01/02 verilog/Otros/Audio-SB/03FIFO/fifo.v
// diseño de una fifo ciclica, para implementar en cada  bloque de proyecto
// ferney alberto beltran 2016 electrónica digital 1 universidad Nacional

module fifo
   #(
  	parameter adr_width = 5,
	parameter dat_width = 8
   )
   (
    input  clk, reset,
    input  rd1, wr1,
    input  [dat_width-1:0] data_in,
    output [dat_width-1:0] data_out,
    output empty, 
    output full
   );

   reg wr, rd;
   parameter depth = (1 << adr_width);

   //declaración de registros 
 
   reg [dat_width-1:0] array_reg [depth-1:0];// register array FIFO

   reg [adr_width-1:0] w_ptr_reg, w_ptr_next;
   reg [adr_width-1:0] r_ptr_reg, r_ptr_next;
   reg full_reg, empty_reg, full_next, empty_next;
   wire wr_en;
reg [31:0] count;
initial wr<=0;
initial rd<=0;
initial count<=0;

   assign data_out = array_reg[r_ptr_reg];
   assign wr_en = wr & ~full_reg;

   assign full = full_reg;
   assign empty = empty_reg;

   always @(posedge clk) begin
      if (wr_en)
         array_reg[w_ptr_reg] <= data_in;
   end

   // fifo control logic
   // register for read and write pointers
 always @(posedge clk) begin
wr=0;	
if (wr1==1)
	begin
		        if (count==0)
			begin
				wr <=~wr;
				count <= 2;
			end	
			else 
			begin
				count <=count-1;
			end
	end
	else 
	begin
	wr=0;
	end
 end
always @(negedge clk) begin
wr=0;	
if (wr1==1)
	begin
		        if (count==0)
			begin
				wr <=~wr;
				count <= 1;
			end	
			else 
			begin
				count <=count-1;
			end
	end
	else 
	begin
	wr=0;
	end
 end


 always @(posedge clk) begin
	if (rd1)
	begin
		        if (count==0)
			begin
				rd <=~rd;
				count <= 1;
			end	
			else 
			begin
				count <=count-1;
			end
	end
	else 
	begin
	rd=0;
	end
 end
 always @(posedge clk) begin
	if (rd1)
	begin
		        if (count==0)
			begin
				rd <=~rd;
				count <= 2;
			end	
			else 
			begin
				count <=count-1;
			end
	end
	else 
	begin
	rd=0;
	end
 end

   always @(posedge clk, posedge reset) begin
      if (reset)
         begin
            w_ptr_reg <= 0;
            r_ptr_reg <= 0;
            full_reg <= 1'b0;
            empty_reg <= 1'b1;
         end
      else
         begin
            w_ptr_reg <= w_ptr_next;
            r_ptr_reg <= r_ptr_next;
            full_reg <= full_next;
            empty_reg <= empty_next;
         end
   end


   
   always @(posedge reset, posedge wr, posedge rd)
   begin
      if (reset) begin
	w_ptr_next =  0;
        r_ptr_next =  0;       
      end else begin
	      full_next = full_reg;
	      empty_next = empty_reg;
	      case ({wr, rd})
		 2'b01: // read
		    if (~empty_reg) // not empty
		       begin
		          r_ptr_next = r_ptr_reg + 1;
		          full_next = 1'b0;
		          if (r_ptr_next==w_ptr_reg)
		             empty_next = 1'b1;
		       end
		 2'b10: // write
		    if (~full_reg) // not full
		       begin
		          w_ptr_next = w_ptr_reg + 1;
		          empty_next = 1'b0;
		          if (w_ptr_next==r_ptr_reg)
		             full_next = 1'b1;
		       end
		 2'b11: // write and read
		    begin
		       w_ptr_next =  w_ptr_reg + 1;
		       r_ptr_next = r_ptr_reg + 1;
		    end
	      endcase
	end
   end


  
endmodule

FPGA-Game-D1-master/HW/RTL/06PCM-AUDIO-MICROFONO/Version_01/02 verilog/Otros/Audio-SB/03FIFO/fifo_TB.v
//----------------------------------------------------------------------------
//`timescale 1 ns / 100 ps

module fifo_TB;

//----------------------------------------------------------------------------
// Parameter (may differ for physical synthesis)
//----------------------------------------------------------------------------
parameter tck              = 2;       // clock period in ns
//----------------------------------------------------------------------------
//----------------------------------------------------------------------------

reg clk;
reg rst;

reg rd,wr;
reg [7:0] data_in;

//----------------------------------------------------------------------------
// Device Under Test 
//------------------------------------------------------------------

fifo  uut(.reset(rst),.clk(clk),.rd1(rd),.wr1(wr),.data_in(data_in));


/* Clocking device */
initial begin
	clk <= 0;
	rst <=1;
	#(2*tck) rst=0;
	
end

always #(tck/2) clk <= ~clk;

initial begin
wr<=1'b0; #1 ;
wr<=1'b1; #100 ;
wr<=1'b0; #1 ;

end
initial begin
rd<=1'b0; #25 ;
rd<=1'b1; #1020 ;
rd<=1'b0; #2 ;

end

initial begin
#4;
data_in="h"; #1;
data_in="o"; #1; 
data_in="l"; #1;
data_in="a"; #1 ;
data_in=" "; #1 ;
data_in="m"; #1;
data_in="u"; #1 ;
data_in="n"; #1 ;
data_in="d"; #1 ;
data_in="o"; #1;
data_in="."; #1 ;
data_in="1"; #1 ;
data_in="2"; #1 ;
data_in="3"; #1 ;
data_in="4"; #1 ;
data_in="5"; #1 ;
data_in="6"; #1 ;
data_in="7"; #1;
data_in="8"; #1 ;
data_in="9"; #1 ;
data_in="0"; #1 ;


end
initial begin: TEST_CASE
     $dumpfile("fifo_TB.vcd");
     $dumpvars(-1, uut);
     #(200) $finish;
   end

endmodule //

FPGA-Game-D1-master/HW/RTL/06PCM-AUDIO-MICROFONO/Version_01/02 verilog/Otros/Audio-SB/03FIFO/simulation/fifo_TB.vcd
$date
	Wed Nov 22 02:01:39 2017
$end
$version
	Icarus Verilog
$end
$timescale
	1s
$end
$scope module fifo_TB $end
$scope module uut $end
$var wire 1 ! clk $end
$var wire 8 " data_in [7:0] $end
$var wire 8 # data_out [7:0] $end
$var wire 1 $ empty $end
$var wire 1 % full $end
$var wire 1 & rd1 $end
$var wire 1 ' reset $end
$var wire 1 ( wr1 $end
$var wire 1 ) wr_en $end
$var reg 32 * count [31:0] $end
$var reg 1 + empty_next $end
$var reg 1 , empty_reg $end
$var reg 1 - full_next $end
$var reg 1 . full_reg $end
$var reg 5 / r_ptr_next [4:0] $end
$var reg 5 0 r_ptr_reg [4:0] $end
$var reg 1 1 rd $end
$var reg 5 2 w_ptr_next [4:0] $end
$var reg 5 3 w_ptr_reg [4:0] $end
$var reg 1 4 wr $end
$upscope $end
$upscope $end
$enddefinitions $end
#0
$dumpvars
04
b0 3
b0 2
01
b0 0
b0 /
0.
x-
1,
x+
b0 *
0)
0(
1'
0&
0%
1$
bx #
bx "
0!
$end
#1
1)
b10 *
14
1(
1!
#2
b1 *
0)
04
0!
#3
b0 *
1!
#4
b1 2
0+
0-
1)
b1 *
14
0!
b1101000 "
0'
#5
0$
0,
b1 3
b1101111 #
b0 *
0)
04
1!
b1101111 "
#6
b10 2
1)
b1 *
14
0!
b1101100 "
#7
b10 3
b0 *
0)
04
1!
b1100001 "
#8
b11 2
1)
b1 *
14
0!
b100000 "
#9
b11 3
b0 *
0)
04
1!
b1101101 "
#10
b100 2
1)
b1 *
14
0!
b1110101 "
#11
b100 3
b0 *
0)
04
1!
b1101110 "
#12
b101 2
1)
b1 *
14
0!
b1100100 "
#13
b101 3
b0 *
0)
04
1!
b1101111 "
#14
b110 2
1)
b1 *
14
0!
b101110 "
#15
b110 3
b0 *
0)
04
1!
b110001 "
#16
b111 2
1)
b1 *
14
0!
b110010 "
#17
b111 3
b0 *
0)
04
1!
b110011 "
#18
b1000 2
1)
b1 *
14
0!
b110100 "
#19
b1000 3
b0 *
0)
04
1!
b110101 "
#20
b1001 2
1)
b1 *
14
0!
b110110 "
#21
b1001 3
b0 *
0)
04
1!
b110111 "
#22
b1010 2
1)
b1 *
14
0!
b111000 "
#23
b1010 3
b0 *
0)
04
1!
b111001 "
#24
b1011 2
1)
b1 *
14
0!
b110000 "
#25
b1011 3
b0 *
0)
04
1!
1&
#26
b1100 2
1)
b1 *
14
0!
#27
b1100 3
b0 *
0)
04
1!
#28
b1101 2
1)
b1 *
14
0!
#29
b1101 3
b0 *
0)
04
1!
#30
b1110 2
1)
b1 *
14
0!
#31
b1110 3
b0 *
0)
04
1!
#32
b1111 2
1)
b1 *
14
0!
#33
b1111 3
b0 *
0)
04
1!
#34
b10000 2
1)
b1 *
14
0!
#35
b10000 3
b0 *
0)
04
1!
#36
b10001 2
1)
b1 *
14
0!
#37
b10001 3
b0 *
0)
04
1!
#38
b10010 2
1)
b1 *
14
0!
#39
b10010 3
b0 *
0)
04
1!
#40
b10011 2
1)
b1 *
14
0!
#41
b10011 3
b0 *
0)
04
1!
#42
b10100 2
1)
b1 *
14
0!
#43
b10100 3
b0 *
0)
04
1!
#44
b10101 2
1)
b1 *
14
0!
#45
b10101 3
b0 *
0)
04
1!
#46
b10110 2
1)
b1 *
14
0!
#47
b10110 3
b0 *
0)
04
1!
#48
b10111 2
1)
b1 *
14
0!
#49
b10111 3
b0 *
0)
04
1!
#50
b11000 2
1)
b1 *
14
0!
#51
b11000 3
b0 *
0)
04
1!
#52
b11001 2
1)
b1 *
14
0!
#53
b11001 3
b0 *
0)
04
1!
#54
b11010 2
1)
b1 *
14
0!
#55
b11010 3
b0 *
0)
04
1!
#56
b11011 2
1)
b1 *
14
0!
#57
b11011 3
b0 *
0)
04
1!
#58
b11100 2
1)
b1 *
14
0!
#59
b11100 3
b0 *
0)
04
1!
#60
b11101 2
1)
b1 *
14
0!
#61
b11101 3
b0 *
0)
04
1!
#62
b11110 2
1)
b1 *
14
0!
#63
b11110 3
b0 *
0)
04
1!
#64
b11111 2
1)
b1 *
14
0!
#65
b11111 3
b0 *
0)
04
1!
#66
1-
b0 2
1)
b1 *
14
0!
#67
1%
1.
b0 3
b0 *
0)
04
1!
#68
b1 *
14
0!
#69
b0 *
04
1!
#70
b1 *
14
0!
#71
b0 *
04
1!
#72
b1 *
14
0!
#73
b0 *
04
1!
#74
b1 *
14
0!
#75
b0 *
04
1!
#76
b1 *
14
0!
#77
b0 *
04
1!
#78
b1 *
14
0!
#79
b0 *
04
1!
#80
b1 *
14
0!
#81
b0 *
04
1!
#82
b1 *
14
0!
#83
b0 *
04
1!
#84
b1 *
14
0!
#85
b0 *
04
1!
#86
b1 *
14
0!
#87
b0 *
04
1!
#88
b1 *
14
0!
#89
b0 *
04
1!
#90
b1 *
14
0!
#91
b0 *
04
1!
#92
b1 *
14
0!
#93
b0 *
04
1!
#94
b1 *
14
0!
#95
b0 *
04
1!
#96
b1 *
14
0!
#97
b0 *
04
1!
#98
b1 *
14
0!
#99
b0 *
04
1!
#100
b1 *
14
0!
#101
b0 *
04
1!
0(
#102
0!
#103
0-
b1 /
b10 *
11
1!
#104
0!
#105
0%
0.
b1100001 #
b1 0
b1 *
1!
#106
0!
#107
b0 *
1!
#108
0!
#109
b1 *
01
1!
#110
0!
#111
b0 *
1!
#112
0!
#113
b10 /
b1 *
11
1!
#114
0!
#115
b1101101 #
b10 0
b0 *
1!
#116
0!
#117
b1 *
01
1!
#118
0!
#119
b0 *
1!
#120
0!
#121
b11 /
b1 *
11
1!
#122
0!
#123
b1101110 #
b11 0
b0 *
1!
#124
0!
#125
b1 *
01
1!
#126
0!
#127
b0 *
1!
#128
0!
#129
b100 /
b1 *
11
1!
#130
0!
#131
b1101111 #
b100 0
b0 *
1!
#132
0!
#133
b1 *
01
1!
#134
0!
#135
b0 *
1!
#136
0!
#137
b101 /
b1 *
11
1!
#138
0!
#139
b110001 #
b101 0
b0 *
1!
#140
0!
#141
b1 *
01
1!
#142
0!
#143
b0 *
1!
#144
0!
#145
b110 /
b1 *
11
1!
#146
0!
#147
b110011 #
b110 0
b0 *
1!
#148
0!
#149
b1 *
01
1!
#150
0!
#151
b0 *
1!
#152
0!
#153
b111 /
b1 *
11
1!
#154
0!
#155
b110101 #
b111 0
b0 *
1!
#156
0!
#157
b1 *
01
1!
#158
0!
#159
b0 *
1!
#160
0!
#161
b1000 /
b1 *
11
1!
#162
0!
#163
b110111 #
b1000 0
b0 *
1!
#164
0!
#165
b1 *
01
1!
#166
0!
#167
b0 *
1!
#168
0!
#169
b1001 /
b1 *
11
1!
#170
0!
#171
b111001 #
b1001 0
b0 *
1!
#172
0!
#173
b1 *
01
1!
#174
0!
#175
b0 *
1!
#176
0!
#177
b1010 /
b1 *
11
1!
#178
0!
#179
b110000 #
b1010 0
b0 *
1!
#180
0!
#181
b1 *
01
1!
#182
0!
#183
b0 *
1!
#184
0!
#185
b1011 /
b1 *
11
1!
#186
0!
#187
b1011 0
b0 *
1!
#188
0!
#189
b1 *
01
1!
#190
0!
#191
b0 *
1!
#192
0!
#193
b1100 /
b1 *
11
1!
#194
0!
#195
b1100 0
b0 *
1!
#196
0!
#197
b1 *
01
1!
#198
0!
#199
b0 *
1!
