FPGA-Game-D1-master/HW/RTL/06PCM-AUDIO-MICROFONO/Version_02/02 verilog/proyecto directo/RegAcum/RegAcum.v
module RegAcum (RESET,BCLK,SET,COUNT);

	// ENTRADAS Y SALIDAS DEL SISTEMA

	input wire RESET;
	input wire BCLK;
	input wire SET;
	output reg [5:0] COUNT = 6'h00;

	//-- Registro

	always @(posedge BCLK)
		begin
		  if (RESET)
			COUNT = 6'h00;
		  else
			begin
				if (SET)
					COUNT = 6'h01;
				else
					COUNT = COUNT + 6'h01;				
			end
		end
endmodule

FPGA-Game-D1-master/HW/RTL/06PCM-AUDIO-MICROFONO/Version_02/02 verilog/ProyectoDigital1/RegDesp/RegAcum_TB.v
`timescale 1ns / 1ns
module RegAcum_TB;

	reg reset;
	reg bclk;
	reg set;
	wire [5:0] count;

	RegAcum DUT(
		.reset(reset),
		.bclk(bclk),
		.set(set),
		.count(count)
	);

	always
		begin
			#1 bclk = ~bclk;
		end	

	initial
		begin: TEST_CASE
   			$dumpfile("RegAcum_TB.vcd");
     		$dumpvars(-1, DUT);
			#(300) $finish;
		end
	
	initial
		begin
			bclk = 1'b0;
			reset = 1'b1;
			set = 1'b0;

			#5 reset = 1'b0;

			#37 set = 1'b1;
			#5 set = 1'b0;

			
			#10 reset = 1'b1;

		end

endmodule

FPGA-Game-D1-master/HW/RTL/06PCM-AUDIO-MICROFONO/Version_02/02 verilog/ProyectoDigital1/RegDesp/simulation/RegAcum_TB.vcd
$date
	Sat Sep 30 21:38:32 2017
$end
$version
	Icarus Verilog
$end
$timescale
	1ns
$end
$scope module RegAcum_TB $end
$scope module DUT $end
$var wire 1 ! BCLK $end
$var wire 1 " RESET $end
$var wire 1 # SET $end
$var reg 6 $ COUNT [5:0] $end
$upscope $end
$upscope $end
$enddefinitions $end
#0
$dumpvars
bx $
0#
1"
0!
$end
#1
b0 $
1!
#2
0!
#3
1!
#4
0!
#5
b1 $
1!
0"
#6
0!
#7
b10 $
1!
#8
0!
#9
b11 $
1!
#10
0!
#11
b100 $
1!
#12
0!
#13
b101 $
1!
#14
0!
#15
b110 $
1!
#16
0!
#17
b111 $
1!
#18
0!
#19
b1000 $
1!
#20
0!
#21
b1001 $
1!
#22
0!
#23
b1010 $
1!
#24
0!
#25
b1011 $
1!
#26
0!
#27
b1100 $
1!
#28
0!
#29
b1101 $
1!
#30
0!
#31
b1110 $
1!
#32
0!
#33
b1111 $
1!
#34
0!
#35
b10000 $
1!
#36
0!
#37
b10001 $
1!
#38
0!
#39
b10010 $
1!
#40
0!
#41
b10011 $
1!
#42
0!
1#
#43
b1 $
1!
#44
0!
#45
1!
#46
0!
#47
b10 $
1!
0#
#48
0!
#49
b11 $
1!
#50
0!
#51
b100 $
1!
#52
0!
#53
b101 $
1!
#54
0!
#55
b110 $
1!
#56
0!
#57
b0 $
1!
1"
