FPGA-Game-D1-master/HW/RTL/10KEYBOARD/Version_01/02 verilog/Touch/Bloquetouch/FIFO/fifo.v
// diseño de una fifo ciclica, para implementar en cada  bloque de proyecto
// ferney alberto beltran 2016 electrónica digital 1 universidad Nacional

module fifo
   #(
  	parameter adr_width = 4,
	parameter dat_width = 8
   )
   (
    input  clk, reset,
    input  rd, wr,
    input  [dat_width-1:0] data_in,
    output [dat_width-1:0] data_out,
    output empty, 
    output full
   );

   
   parameter depth = (1 << adr_width);

   //declaración de registros 
 
   reg [dat_width-1:0] array_reg [depth-1:0];// register array FIFO

   reg [adr_width-1:0] w_ptr_reg, w_ptr_next;
   reg [adr_width-1:0] r_ptr_reg, r_ptr_next;
   reg full_reg, empty_reg, full_next, empty_next;
   wire wr_en;
	reg	[1:0]	orden;


   assign data_out = array_reg[r_ptr_reg];
   assign wr_en = wr & ~full_reg;

   assign full = full_reg;
   assign empty = empty_reg;

   always @(posedge clk) begin
      if (wr_en)
         array_reg[w_ptr_reg] <= data_in;
   end

   // fifo control logic
   // register for read and write pointers
   always @(posedge clk, posedge reset) begin
      if (reset)
         begin
            w_ptr_reg <= 0;
            r_ptr_reg <= 0;
            full_reg <= 1'b0;
            empty_reg <= 1'b1;
         end
      else
         begin
            w_ptr_reg <= w_ptr_next;
            r_ptr_reg <= r_ptr_next;
            full_reg <= full_next;
            empty_reg <= empty_next;
         end
   end

	always @(posedge clk)
	begin
		if(!wr&&rd)
		begin
			orden = 2'b01;
		end
		if(wr&&!rd)
		begin
			orden = 2'b10;
		end
		if(wr&&rd)
		begin
			orden = 2'b11;
		end
	end

   
   //always @(posedge reset or posedge wr or posedge rd)
	always @(posedge clk)
   begin
      if (reset) begin
	w_ptr_next =  0;
        r_ptr_next =  0;       
      end else begin
	      full_next = full_reg;
	      empty_next = empty_reg;
	      case (orden)
		 2'b01: // read
		    if (~empty_reg) // not empty
		       begin
		          r_ptr_next = r_ptr_reg + 1;
		          full_next = 1'b0;
		          if (r_ptr_next==w_ptr_reg)
		             empty_next = 1'b1;
		       end
		 2'b10: // write
		    if (~full_reg) // not full
		       begin
		          w_ptr_next = w_ptr_reg + 1;
		          empty_next = 1'b0;
		          if (w_ptr_next==r_ptr_reg)
		             full_next = 1'b1;
		       end
		 2'b11: // write and read
		    begin
		       w_ptr_next =  w_ptr_reg + 1;
		       r_ptr_next = r_ptr_reg + 1;
		    end
	      endcase
	end
   end


  
endmodule

FPGA-Game-D1-master/HW/RTL/10KEYBOARD/Version_01/02 verilog/Touch/Bloquetouch/FIFO/fifo_TB.v
//----------------------------------------------------------------------------
`timescale 1 ns / 100 ps

module fifo_TB;

//----------------------------------------------------------------------------
// Parameter (may differ for physical synthesis)
//----------------------------------------------------------------------------
parameter tck              = 2;       // clock period in ns
//----------------------------------------------------------------------------
//----------------------------------------------------------------------------

reg clk;
reg rst;

reg rd,wr;
reg [7:0] data_in;

//----------------------------------------------------------------------------
// Device Under Test 
//------------------------------------------------------------------

fifo  uut(.reset(rst),.clk(clk),.rd(rd),.wr(wr),.data_in(data_in));


/* Clocking device */
initial begin
	clk <= 0;
	rst <=1;
	#(2*tck) rst=0;
	rd <=0;
	wr<=0;
end

always #(tck/2) clk <= ~clk;


initial begin
#4;
data_in="h"; #1 wr=1; #2 wr=0;
data_in="o"; #1 wr=1; #2 wr=0;
data_in="l"; #1 wr=1; #2 wr=0;
data_in="a"; #1 wr=1; #2 wr=0;
data_in=" "; #1 wr=1; #2 wr=0;
data_in="m"; #1 wr=1; #2 wr=0;
data_in="u"; #1 wr=1; #2 wr=0;
data_in="n"; #1 wr=1; #2 wr=0;
data_in="d"; #1 wr=1; #2 wr=0;
data_in="o"; #1 wr=1; #2 wr=0;
data_in="."; #1 wr=1; #2 wr=0;
data_in="1"; #1 wr=1; #2 wr=0;
data_in="2"; #1 wr=1; #2 wr=0;
data_in="3"; #1 wr=1; #2 wr=0;
data_in="4"; #1 wr=1; #2 wr=0;
data_in="5"; #1 wr=1; #2 wr=0;
data_in="6"; #1 wr=1; #2 wr=0;
data_in="7"; #1 wr=1; #2 wr=0;
data_in="8"; #1 wr=1; #2 wr=0;
data_in="9"; #1 wr=1; #2 wr=0;
data_in="0"; #1 wr=1; #2 wr=0;

#1 rd=1; #2 rd=0;
#1 rd=1; #2 rd=0;
#1 rd=1; #2 rd=0;

data_in="a"; #1 wr=1; #2 wr=0;
data_in="b"; #1 wr=1; #2 wr=0;
data_in="c"; #1 wr=1; #2 wr=0;
data_in="d"; #1 wr=1; #2 wr=0;

#1 rd=1; #2 rd=0;
#1 rd=1; #2 rd=0;
#1 rd=1; #2 rd=0;
#1 rd=1; #2 rd=0;
#1 rd=1; #2 rd=0;
#1 rd=1; #2 rd=0;
#1 rd=1; #2 rd=0;
#1 rd=1; #2 rd=0;
#1 rd=1; #2 rd=0;
#1 rd=1; #2 rd=0;
#1 rd=1; #2 rd=0;
#1 rd=1; #2 rd=0;
#1 rd=1; #2 rd=0;
#1 rd=1; #2 rd=0;
#1 rd=1; #2 rd=0;
#1 rd=1; #2 rd=0;
#1 rd=1; #2 rd=0;
#1 rd=1; #2 rd=0;

//Mío

#4;
data_in="D"; #1 wr=1; rd=1; #2 wr=0; rd=0;
data_in="a"; #1 wr=1; rd=1; #2 wr=0; rd=0;
data_in="m"; #1 wr=1; rd=1; #2 wr=0; rd=0;
data_in="i"; #1 wr=1; rd=1; #2 wr=0; rd=0;
data_in="t"; #1 wr=1; rd=1; #2 wr=0; rd=0;
data_in="a"; #1 wr=1; rd=1; #2 wr=0; rd=0;
data_in=","; #1 wr=1; rd=1; #2 wr=0; rd=0;
data_in=" "; #1 wr=1; rd=1; #2 wr=0; rd=0;
data_in="t"; #1 wr=1; rd=1; #2 wr=0; rd=0;
data_in="u"; #1 wr=1; rd=1; #2 wr=0; rd=0;
data_in=" "; #1 wr=1; rd=1; #2 wr=0; rd=0;
data_in="n"; #1 wr=1; rd=1; #2 wr=0; rd=0;
data_in="o"; #1 wr=1; rd=1; #2 wr=0; rd=0;
data_in="v"; #1 wr=1; rd=1; #2 wr=0; rd=0;
data_in="i"; #1 wr=1; rd=1; #2 wr=0; rd=0;
data_in="o"; #1 wr=1; rd=1; #2 wr=0; rd=0;
data_in=" "; #1 wr=1; rd=1; #2 wr=0; rd=0;
data_in="e"; #1 wr=1; rd=1; #2 wr=0; rd=0;
data_in="s"; #1 wr=1; rd=1; #2 wr=0; rd=0;
data_in=" "; #1 wr=1; rd=1; #2 wr=0; rd=0;
data_in="e"; #1 wr=1; rd=1; #2 wr=0; rd=0;


//Mío 2
#4;
rst=1;
#4;
rst=0;
#4;
data_in="s"; #1 wr=1; rd=1; #2 wr=0; rd=0;
data_in=" "; #1 wr=1; rd=1; #2 wr=0; rd=0;
data_in="e"; #1 wr=1; rd=1; #2 wr=0; rd=0;
data_in="l"; #1 wr=1; rd=1; #2 wr=0; rd=0;
data_in=" "; #1 wr=1; rd=1; #2 wr=0; rd=0;
data_in="h"; #1 wr=1; rd=1; #2 wr=0; rd=0;
data_in="o"; #1 wr=1; rd=1; #2 wr=0; rd=0;
data_in="m"; #1 wr=1; rd=1; #2 wr=0; rd=0;
data_in="b"; #1 wr=1; rd=1; #2 wr=0; rd=0;
data_in="r"; #1 wr=1; rd=1; #2 wr=0; rd=0;
data_in="e"; #1 wr=1; rd=1; #2 wr=0; rd=0;
data_in=" "; #1 wr=1; rd=1; #2 wr=0; rd=0;
data_in="m"; #1 wr=1; rd=1; #2 wr=0; rd=0;
data_in="a"; #1 wr=1; rd=1; #2 wr=0; rd=0;
data_in="s"; #1 wr=1; rd=1; #2 wr=0; rd=0;
data_in=" "; #1 wr=1; rd=1; #2 wr=0; rd=0;
data_in="a"; #1 wr=1; rd=1; #2 wr=0; rd=0;
data_in="f"; #1 wr=1; rd=1; #2 wr=0; rd=0;
data_in="o"; #1 wr=1; rd=1; #2 wr=0; rd=0;
data_in="r"; #1 wr=1; rd=1; #2 wr=0; rd=0;
data_in="t"; #1 wr=1; rd=1; #2 wr=0; rd=0;

//Mío 3

#4;
rst=1;
#4;
rst=0;
#4;
data_in="Q"; #1 wr=1; #2 wr=0;
data_in="u"; #1 wr=1; #2 wr=0;
data_in="e"; #1 wr=1; #2 wr=0;
data_in=" "; #1 wr=1; #2 wr=0;
data_in="l"; #1 wr=1; #2 wr=0;
data_in="a"; #1 wr=1; #2 wr=0;
data_in=" "; #1 wr=1; #2 wr=0;
data_in="v"; #1 wr=1; #2 wr=0;
data_in="i"; #1 wr=1; #2 wr=0;
data_in="d"; #1 wr=1; #2 wr=0;
data_in="a"; #1 wr=1; #2 wr=0;
data_in=" "; #1 wr=1; #2 wr=0;
data_in="s"; #1 wr=1; #2 wr=0;
data_in="e"; #1 wr=1; #2 wr=0;
data_in="a"; #1 wr=1; #2 wr=0;
data_in=" "; #1 wr=1; #2 wr=0;
data_in="m"; #1 wr=1; #2 wr=0;
data_in="a"; #1 wr=1; #2 wr=0;
data_in="s"; #1 wr=1; #2 wr=0;
data_in=" "; #1 wr=1; #2 wr=0;
data_in="p"; #1 wr=1; #2 wr=0;

//#1 rd=1; #2 rd=0;
//#1 rd=1; #2 rd=0;
//#1 rd=1; #2 rd=0;

//data_in="a"; #1 wr=1; #2 wr=0;
//data_in="b"; #1 wr=1; #2 wr=0;
//data_in="c"; #1 wr=1; #2 wr=0;
//data_in="d"; #1 wr=1; #2 wr=0;

#1 rd=1; #2 rd=0;
#1 rd=1; #2 rd=0;
#1 rd=1; #2 rd=0;
#1 rd=1; #2 rd=0;
#1 rd=1; #2 rd=0;
#1 rd=1; #2 rd=0;
#1 rd=1; #2 rd=0;
#1 rd=1; #2 rd=0;
#1 rd=1; #2 rd=0;
#1 rd=1; #2 rd=0;
#1 rd=1; #2 rd=0;
#1 rd=1; #2 rd=0;
#1 rd=1; #2 rd=0;
#1 rd=1; #2 rd=0;
#1 rd=1; #2 rd=0;
#1 rd=1; #2 rd=0;
#1 rd=1; #2 rd=0;
#1 rd=1; #2 rd=0;

#4;
data_in="Y"; #1 wr=1; #2 wr=0;
data_in="o"; #1 wr=1; #2 wr=0;
data_in=" "; #1 wr=1; #2 wr=0;
data_in="t"; #1 wr=1; #2 wr=0;
data_in="e"; #1 wr=1; #2 wr=0;
data_in=" "; #1 wr=1; #2 wr=0;
data_in="d"; #1 wr=1; #2 wr=0;
data_in="a"; #1 wr=1; #2 wr=0;
data_in="r"; #1 wr=1; #2 wr=0;
data_in="e"; #1 wr=1; #2 wr=0;
data_in=","; #1 wr=1; #2 wr=0;
data_in=" "; #1 wr=1; #2 wr=0;
data_in="t"; #1 wr=1; #2 wr=0;
data_in="e"; #1 wr=1; #2 wr=0;
data_in=" "; #1 wr=1; #2 wr=0;
data_in="d"; #1 wr=1; #2 wr=0;
data_in="a"; #1 wr=1; #2 wr=0;
data_in="r"; #1 wr=1; #2 wr=0;
data_in="e"; #1 wr=1; #2 wr=0;
data_in=" "; #1 wr=1; #2 wr=0;
data_in="m"; #1 wr=1; #2 wr=0;

//#1 rd=1; #2 rd=0;
//#1 rd=1; #2 rd=0;
//#1 rd=1; #2 rd=0;

//data_in="a"; #1 wr=1; #2 wr=0;
//data_in="b"; #1 wr=1; #2 wr=0;
//data_in="c"; #1 wr=1; #2 wr=0;
//data_in="d"; #1 wr=1; #2 wr=0;

#1 rd=1; #2 rd=0;
#1 rd=1; #2 rd=0;
#1 rd=1; #2 rd=0;
#1 rd=1; #2 rd=0;
#1 rd=1; #2 rd=0;
#1 rd=1; #2 rd=0;
#1 rd=1; #2 rd=0;
#1 rd=1; #2 rd=0;
#1 rd=1; #2 rd=0;
#1 rd=1; #2 rd=0;
#1 rd=1; #2 rd=0;
#1 rd=1; #2 rd=0;
#1 rd=1; #2 rd=0;
#1 rd=1; #2 rd=0;
#1 rd=1; #2 rd=0;
#1 rd=1; #2 rd=0;
#1 rd=1; #2 rd=0;
#1 rd=1; #2 rd=0;

////////////////////////////////////////////////////////////////////////////////////////////////////////////////////////////
//////////////// 			    ////////////////////////////////////////////////////////////////////////////////
////////////////    Mío, Con mayor Control  ////////////////////////////////////////////////////////////////////////////////
////////////////		 	    ////////////////////////////////////////////////////////////////////////////////
////////////////////////////////////////////////////////////////////////////////////////////////////////////////////////////

#4;
rst=1;
#4;
rst=0;
#4;
data_in="a"; #1 wr=1; #2 wr=0;//1
data_in="b"; #1 wr=1; #2 wr=0;//2
data_in="c"; #1 wr=1; #2 wr=0;//3
data_in="d"; #1 wr=1; #2 wr=0;//4
data_in="e"; #1 wr=1; #2 wr=0;//5
data_in="f"; #1 wr=1; #2 wr=0;//6
data_in="g"; #1 wr=1; #2 wr=0;//7
data_in="h"; #1 wr=1; #2 wr=0;//8
data_in="i"; #1 wr=1; #2 wr=0;//9
data_in="j"; #1 wr=1; #2 wr=0;//a
data_in="k"; #1 wr=1; #2 wr=0;//b
data_in="l"; #1 wr=1; #2 wr=0;//c
data_in="m"; #1 wr=1; #2 wr=0;//d
data_in="n"; #1 wr=1; #2 wr=0;//e
data_in="o"; #1 wr=1; #2 wr=0;//f
data_in="p"; #1 wr=1; #2 wr=0;//0


//#1 rd=1; #2 rd=0;
//#1 rd=1; #2 rd=0;
//#1 rd=1; #2 rd=0;

//data_in="a"; #1 wr=1; #2 wr=0;
//data_in="b"; #1 wr=1; #2 wr=0;
//data_in="c"; #1 wr=1; #2 wr=0;
//data_in="d"; #1 wr=1; #2 wr=0;

#1 rd=1; #2 rd=0;//0
#1 rd=1; #2 rd=0;//1
#1 rd=1; #2 rd=0;//2
#1 rd=1; #2 rd=0;//3
#1 rd=1; #2 rd=0;//4
#1 rd=1; #2 rd=0;//5
#1 rd=1; #2 rd=0;//6
#1 rd=1; #2 rd=0;//7
#1 rd=1; #2 rd=0;//8
#1 rd=1; #2 rd=0;//9
#1 rd=1; #2 rd=0;//a
#1 rd=1; #2 rd=0;//b
#1 rd=1; #2 rd=0;//c
#1 rd=1; #2 rd=0;//d
#1 rd=1; #2 rd=0;//e
#1 rd=1; #2 rd=0;//f

#1 rd=1; #2 rd=0;//0
#1 rd=1; #2 rd=0;//1
#1 rd=1; #2 rd=0;//2
#1 rd=1; #2 rd=0;//3
#1 rd=1; #2 rd=0;//4
#1 rd=1; #2 rd=0;//5
#1 rd=1; #2 rd=0;//6
#1 rd=1; #2 rd=0;//7
#1 rd=1; #2 rd=0;//8
#1 rd=1; #2 rd=0;//9
#1 rd=1; #2 rd=0;//a
#1 rd=1; #2 rd=0;//b
#1 rd=1; #2 rd=0;//c
#1 rd=1; #2 rd=0;//d
#1 rd=1; #2 rd=0;//e
#1 rd=1; #2 rd=0;//f

////////////////////////////////////////////////////////////////////////////////////////////////////////////////////////////
//////////////// 			    ////////////////////////////////////////////////////////////////////////////////
////////////////    Mío, Con mayor Control  ///////////////////////////             2              /////////////////////////
////////////////		 	    ////////////////////////////////////////////////////////////////////////////////
////////////////////////////////////////////////////////////////////////////////////////////////////////////////////////////
#4;
rst=1;
#4;
rst=0;
#4;
data_in="h"; #1 wr=1; #2 wr=0;
data_in="o"; #1 wr=1; #2 wr=0;
data_in="l"; #1 wr=1; #2 wr=0;
data_in="a"; #1 wr=1; #2 wr=0;
data_in=" "; #1 wr=1; #2 wr=0;
data_in="m"; #1 wr=1; #2 wr=0;
data_in="u"; #1 wr=1; #2 wr=0;
data_in="n"; #1 wr=1; #2 wr=0;
data_in="d"; #1 wr=1; #2 wr=0;
data_in="o"; #1 wr=1; #2 wr=0;
data_in="."; #1 wr=1; #2 wr=0;
data_in="1"; #1 wr=1; #2 wr=0;
data_in="2"; #1 wr=1; #2 wr=0;
data_in="3"; #1 wr=1; #2 wr=0;
data_in="4"; #1 wr=1; #2 wr=0;
data_in="5"; #1 wr=1; #2 wr=0;
data_in="6"; #1 wr=1; #2 wr=0;
data_in="7"; #1 wr=1; #2 wr=0;
data_in="8"; #1 wr=1; #2 wr=0;
data_in="9"; #1 wr=1; #2 wr=0;
data_in="0"; #1 wr=1; #2 wr=0;

#1 rd=1; #2 rd=0;
#1 rd=1; #2 rd=0;
#1 rd=1; #2 rd=0;

data_in="a"; #1 wr=1; #2 wr=0;
data_in="b"; #1 wr=1; #2 wr=0;
data_in="c"; #1 wr=1; #2 wr=0;
data_in="d"; #1 wr=1; #2 wr=0;

#4;
rst=1;
#4;
rst=0;

#1 rd=1; #2 rd=0;
#1 rd=1; #2 rd=0;
#1 rd=1; #2 rd=0;
#1 rd=1; #2 rd=0;
#1 rd=1; #2 rd=0;
#1 rd=1; #2 rd=0;
#1 rd=1; #2 rd=0;
#1 rd=1; #2 rd=0;
#1 rd=1; #2 rd=0;
#1 rd=1; #2 rd=0;
#1 rd=1; #2 rd=0;
#1 rd=1; #2 rd=0;
#1 rd=1; #2 rd=0;
#1 rd=1; #2 rd=0;
#1 rd=1; #2 rd=0;
#1 rd=1; #2 rd=0;
#1 rd=1; #2 rd=0;
#1 rd=1; #2 rd=0;

////////////////////////////////////////////////////////////////////////////////////////////////////////////////////////////
//////////////// 			    ////////////////////////////////////////////////////////////////////////////////
////////////////    Mío, Con mayor Control  ////////////////////////////////////////////////////////////////////////////////
////////////////		 	    ////////////////////////////////////////////////////////////////////////////////
////////////////////////////////////////////////////////////////////////////////////////////////////////////////////////////

#4;
rst=1;
#4;
rst=0;
#4;
data_in="a"; #1 wr=1; #2 wr=0;//1
data_in="b"; #1 wr=1; #2 wr=0;//2
data_in="c"; #1 wr=1; #2 wr=0;//3
data_in="d"; #1 wr=1; #2 wr=0;//4
data_in="e"; #1 wr=1; #2 wr=0;//5

#1 rd=1; #2 rd=0;
#1 rd=1; #2 rd=0;
#1 rd=1; #2 rd=0;
#1 rd=1; #2 rd=0;
#1 rd=1; #2 rd=0;
#1 rd=1; #2 rd=0;
#1 rd=1; #2 rd=0;
#1 rd=1; #2 rd=0;
#1 rd=1; #2 rd=0;
#1 rd=1; #2 rd=0;
#1 rd=1; #2 rd=0;
#1 rd=1; #2 rd=0;
#1 rd=1; #2 rd=0;
#1 rd=1; #2 rd=0;
#1 rd=1; #2 rd=0;
#1 rd=1; #2 rd=0;
#1 rd=1; #2 rd=0;
#1 rd=1; #2 rd=0;


end
initial begin: TEST_CASE
     $dumpfile("fifo_TB.vcd");
     $dumpvars(-1, uut);
     #(1200) $finish;
   end

endmodule //

FPGA-Game-D1-master/HW/RTL/10KEYBOARD/Version_01/02 verilog/Touch/Bloquetouch/FIFO/simulation/fifo_TB.vcd
$date
	Sun Nov 26 10:25:31 2017
$end
$version
	Icarus Verilog
$end
$timescale
	100ps
$end
$scope module fifo_TB $end
$scope module uut $end
$var wire 1 ! clk $end
$var wire 8 " data_in [7:0] $end
$var wire 8 # data_out [7:0] $end
$var wire 1 $ empty $end
$var wire 1 % full $end
$var wire 1 & rd $end
$var wire 1 ' reset $end
$var wire 1 ( wr $end
$var wire 1 ) wr_en $end
$var reg 1 * empty_next $end
$var reg 1 + empty_reg $end
$var reg 1 , full_next $end
$var reg 1 - full_reg $end
$var reg 2 . orden [1:0] $end
$var reg 4 / r_ptr_next [3:0] $end
$var reg 4 0 r_ptr_reg [3:0] $end
$var reg 4 1 w_ptr_next [3:0] $end
$var reg 4 2 w_ptr_reg [3:0] $end
$upscope $end
$upscope $end
$enddefinitions $end
#0
$dumpvars
b0 2
bx 1
b0 0
bx /
bx .
0-
x,
1+
x*
x)
x(
1'
x&
0%
1$
bx #
bx "
0!
$end
#10
b0 /
b0 1
1!
#20
0!
#30
1!
#40
0)
0!
0(
0&
b1101000 "
0'
#50
b1101000 #
x+
x$
x-
x%
b10 .
1*
0,
1!
x)
1(
#60
0!
#70
1+
1$
0-
0%
x*
x,
1!
0)
b1101111 "
0(
#80
0!
1)
1(
#90
x)
b1101111 #
x+
x$
x-
x%
b1 1
0*
0,
1!
#100
0!
0)
b1101100 "
0(
#110
0+
0$
0-
0%
b1 2
x*
x,
1!
1)
1(
#120
0!
#130
x+
x$
x-
x%
b10 1
0*
0,
1!
0)
b1100001 "
0(
#140
0!
x)
1(
#150
1)
0+
0$
0-
0%
b10 2
x*
x,
1!
#160
0!
0)
b100000 "
0(
#170
x+
x$
x-
x%
b11 1
0*
0,
1!
x)
1(
#180
0!
#190
0+
0$
0-
0%
b11 2
x*
x,
1!
0)
b1101101 "
0(
#200
0!
1)
1(
#210
x)
x+
x$
x-
x%
b100 1
0*
0,
1!
#220
0!
0)
b1110101 "
0(
#230
0+
0$
0-
0%
b100 2
x*
x,
1!
1)
1(
#240
0!
#250
x+
x$
x-
x%
b101 1
0*
0,
1!
0)
b1101110 "
0(
#260
0!
x)
1(
#270
1)
0+
0$
0-
0%
b101 2
x*
x,
1!
#280
0!
0)
b1100100 "
0(
#290
x+
x$
x-
x%
b110 1
0*
0,
1!
x)
1(
#300
0!
#310
0+
0$
0-
0%
b110 2
x*
x,
1!
0)
b1101111 "
0(
#320
0!
1)
1(
#330
x)
x+
x$
x-
x%
b111 1
0*
0,
1!
#340
0!
0)
b101110 "
0(
#350
0+
0$
0-
0%
b111 2
x*
x,
1!
1)
1(
#360
0!
#370
x+
x$
x-
x%
b1000 1
0*
0,
1!
0)
b110001 "
0(
#380
0!
x)
1(
#390
1)
0+
0$
0-
0%
b1000 2
x*
x,
1!
#400
0!
0)
b110010 "
0(
#410
x+
x$
x-
x%
b1001 1
0*
0,
1!
x)
1(
#420
0!
#430
0+
0$
0-
0%
b1001 2
x*
x,
1!
0)
b110011 "
0(
#440
0!
1)
1(
#450
x)
x+
x$
x-
x%
b1010 1
0*
0,
1!
#460
0!
0)
b110100 "
0(
#470
0+
0$
0-
0%
b1010 2
x*
x,
1!
1)
1(
#480
0!
#490
x+
x$
x-
x%
b1011 1
0*
0,
1!
0)
b110101 "
0(
#500
0!
x)
1(
#510
1)
0+
0$
0-
0%
b1011 2
x*
x,
1!
#520
0!
0)
b110110 "
0(
#530
x+
x$
x-
x%
b1100 1
0*
0,
1!
x)
1(
#540
0!
#550
0+
0$
0-
0%
b1100 2
x*
x,
1!
0)
b110111 "
0(
#560
0!
1)
1(
#570
x)
x+
x$
x-
x%
b1101 1
0*
0,
1!
#580
0!
0)
b111000 "
0(
#590
0+
0$
0-
0%
b1101 2
x*
x,
1!
1)
1(
#600
0!
#610
x+
x$
x-
x%
b1110 1
0*
0,
1!
0)
b111001 "
0(
#620
0!
x)
1(
#630
1)
0+
0$
0-
0%
b1110 2
x*
x,
1!
#640
0!
0)
b110000 "
0(
#650
x+
x$
x-
x%
b1111 1
0*
0,
1!
x)
1(
#660
0!
#670
0+
0$
0-
0%
b1111 2
x*
x,
1!
0)
0(
#680
0!
1&
#690
x+
x$
x-
x%
b1 .
b0 1
0*
1,
1!
#700
0!
0&
#710
0+
0$
1-
1%
b0 2
x*
x,
1!
1&
#720
0!
#730
x+
x$
x-
x%
b1 /
0*
0,
1!
0&
#740
0!
1&
#750
0+
0$
0-
0%
b1 0
bx #
x*
x,
1!
#760
0!
b1100001 "
0&
#770
x+
x$
x-
x%
b10 .
b10 /
0*
0,
1!
x)
1(
#780
0!
#790
0+
0$
0-
0%
b10 0
b100000 #
x*
x,
1!
0)
b1100010 "
0(
#800
0!
1)
1(
#810
x)
x+
x$
x-
x%
b1 1
0*
0,
1!
#820
0!
0)
b1100011 "
0(
#830
0+
0$
0-
0%
b1 2
x*
x,
1!
1)
1(
#840
0!
#850
x+
x$
x-
x%
b10 1
0*
1,
1!
0)
b1100100 "
0(
#860
0!
x)
1(
#870
0)
0+
0$
1-
1%
b10 2
x*
x,
1!
#880
0!
0(
#890
x+
x$
x-
x%
b1 .
0*
1,
1!
1&
#900
0!
#910
0+
0$
1-
1%
x*
x,
1!
0&
#920
0!
1&
#930
x+
x$
x-
x%
b11 /
0*
0,
1!
#940
0!
0&
#950
0+
0$
0-
0%
b11 0
b1101101 #
x*
x,
1!
1&
#960
0!
#970
x+
x$
x-
x%
b100 /
0*
0,
1!
0&
#980
0!
1&
#990
0+
0$
0-
0%
b100 0
bx #
x*
x,
1!
#1000
0!
0&
#1010
x+
x$
x-
x%
b101 /
0*
0,
1!
1&
#1020
0!
#1030
0+
0$
0-
0%
b101 0
b1100100 #
x*
x,
1!
0&
#1040
0!
1&
#1050
x+
x$
x-
x%
b110 /
0*
0,
1!
#1060
0!
0&
#1070
0+
0$
0-
0%
b110 0
b1101111 #
x*
x,
1!
1&
#1080
0!
#1090
x+
x$
x-
x%
b111 /
0*
0,
1!
0&
#1100
0!
1&
#1110
0+
0$
0-
0%
b111 0
bx #
x*
x,
1!
#1120
0!
0&
#1130
x+
x$
x-
x%
b1000 /
0*
0,
1!
1&
#1140
0!
#1150
0+
0$
0-
0%
b1000 0
b110010 #
x*
x,
1!
0&
#1160
0!
1&
#1170
x+
x$
x-
x%
b1001 /
0*
0,
1!
#1180
0!
0&
#1190
0+
0$
0-
0%
b1001 0
b110011 #
x*
x,
1!
1&
#1200
0!
#1210
x+
x$
x-
x%
b1010 /
0*
0,
1!
0&
#1220
0!
1&
#1230
0+
0$
0-
0%
b1010 0
bx #
x*
x,
1!
#1240
0!
0&
#1250
x+
x$
x-
x%
b1011 /
0*
0,
1!
1&
#1260
0!
#1270
0+
0$
0-
0%
b1011 0
b110110 #
x*
x,
1!
0&
#1280
0!
1&
#1290
x+
x$
x-
x%
b1100 /
0*
0,
1!
#1300
0!
0&
#1310
0+
0$
0-
0%
b1100 0
b110111 #
x*
x,
1!
1&
#1320
0!
#1330
x+
x$
x-
x%
b1101 /
0*
0,
1!
0&
#1340
0!
1&
#1350
0+
0$
0-
0%
b1101 0
bx #
x*
x,
1!
#1360
0!
0&
#1370
x+
x$
x-
x%
b1110 /
0*
0,
1!
1&
#1380
0!
#1390
0+
0$
0-
0%
b1110 0
b110000 #
x*
x,
1!
0&
#1400
0!
1&
#1410
x+
x$
x-
x%
b1111 /
0*
0,
1!
#1420
0!
0&
#1430
0+
0$
0-
0%
b1111 0
bx #
x*
x,
1!
#1440
0!
#1450
x+
x$
x-
x%
b0 /
0*
0,
1!
#1460
0!
b1000100 "
#1470
0+
0$
0-
0%
b0 0
b1100010 #
b11 1
x*
x,
b11 .
1!
1)
1&
1(
#1480
0!
#1490
x+
x$
x-
x%
b11 2
b1 /
0*
0,
1!
0)
b1100001 "
0&
0(
#1500
0!
x)
1&
1(
#1510
1)
0+
0$
0-
0%
b1 0
bx #
b100 1
x*
x,
1!
#1520
0!
0)
b1101101 "
0&
0(
#1530
x+
x$
x-
x%
b100 2
b10 /
0*
0,
1!
x)
1&
1(
#1540
0!
#1550
0+
0$
0-
0%
b10 0
b100000 #
b101 1
x*
x,
1!
0)
b1101001 "
0&
0(
#1560
0!
1)
1&
1(
#1570
x)
x+
x$
x-
x%
b101 2
b11 /
0*
0,
1!
#1580
0!
0)
b1110100 "
0&
0(
#1590
0+
0$
0-
0%
b11 0
b1101101 #
b110 1
x*
x,
1!
1)
1&
1(
#1600
0!
#1610
x+
x$
x-
x%
b110 2
b100 /
0*
0,
1!
0)
b1100001 "
0&
0(
#1620
0!
x)
1&
1(
#1630
1)
0+
0$
0-
0%
b100 0
b1101001 #
b111 1
x*
x,
1!
#1640
0!
0)
b101100 "
0&
0(
#1650
x+
x$
x-
x%
b111 2
b101 /
0*
0,
1!
x)
1&
1(
#1660
0!
#1670
0+
0$
0-
0%
b101 0
b1100100 #
b1000 1
x*
x,
1!
0)
b100000 "
0&
0(
#1680
0!
1)
1&
1(
#1690
x)
x+
x$
x-
x%
b1000 2
b110 /
0*
0,
1!
#1700
0!
0)
b1110100 "
0&
0(
#1710
0+
0$
0-
0%
b110 0
b101100 #
b1001 1
x*
x,
1!
1)
1&
1(
#1720
0!
#1730
x+
x$
x-
x%
b1001 2
b111 /
0*
0,
1!
0)
b1110101 "
0&
0(
#1740
0!
x)
1&
1(
#1750
1)
0+
0$
0-
0%
b111 0
b100000 #
b1010 1
x*
x,
1!
#1760
0!
0)
b100000 "
0&
0(
#1770
x+
x$
x-
x%
b1010 2
b1000 /
0*
0,
1!
x)
1&
1(
#1780
0!
#1790
0+
0$
0-
0%
b1000 0
b110010 #
b1011 1
x*
x,
1!
0)
b1101110 "
0&
0(
#1800
0!
1)
1&
1(
#1810
x)
x+
x$
x-
x%
b1011 2
b1001 /
0*
0,
1!
#1820
0!
0)
b1101111 "
0&
0(
#1830
0+
0$
0-
0%
b1001 0
b100000 #
b1100 1
x*
x,
1!
1)
1&
1(
#1840
0!
#1850
x+
x$
x-
x%
b1100 2
b1010 /
0*
0,
1!
0)
b1110110 "
0&
0(
#1860
0!
x)
1&
1(
#1870
1)
0+
0$
0-
0%
b1010 0
b1101110 #
b1101 1
x*
x,
1!
#1880
0!
0)
b1101001 "
0&
0(
#1890
x+
x$
x-
x%
b1101 2
b1011 /
0*
0,
1!
x)
1&
1(
#1900
0!
#1910
0+
0$
0-
0%
b1011 0
b110110 #
b1110 1
x*
x,
1!
0)
b1101111 "
0&
0(
#1920
0!
1)
1&
1(
#1930
x)
x+
x$
x-
x%
b1110 2
b1100 /
0*
0,
1!
#1940
0!
0)
b100000 "
0&
0(
#1950
0+
0$
0-
0%
b1100 0
b1101001 #
b1111 1
x*
x,
1!
1)
1&
1(
#1960
0!
#1970
x+
x$
x-
x%
b1111 2
b1101 /
0*
0,
1!
0)
b1100101 "
0&
0(
#1980
0!
x)
1&
1(
#1990
1)
0+
0$
0-
0%
b1101 0
b1101111 #
b0 1
x*
x,
1!
#2000
0!
0)
b1110011 "
0&
0(
#2010
x+
x$
x-
x%
b0 2
b1110 /
0*
0,
1!
x)
1&
1(
#2020
0!
#2030
0+
0$
0-
0%
b1110 0
b110000 #
b1 1
x*
x,
1!
0)
b100000 "
0&
0(
#2040
0!
1)
1&
1(
