FPGA-Game-D1-master/HW/RTL/06PCM-AUDIO-MICROFONO/Version_02/02 verilog/proyecto directo/Microfono/RegWS.v
module RegWS(RESET, SET32, WS);

	input wire RESET;
	input wire SET32;
	output reg WS;

	always@(negedge SET32)
	begin
		if(RESET)
			WS = 1'b0;
		else
			WS = ~WS;
	end

endmodule

FPGA-Game-D1-master/HW/RTL/06PCM-AUDIO-MICROFONO/Version_02/02 verilog/ProyectoDigital1/RegWS/RegWS_TB.v
`timescale 1ns / 1ns
module RegWS_TB;

	reg reset;
	reg set32;
	wire ws;

	RegWS DUT(
		.reset(reset),
		.set32(set32),
		.ws(ws)
	);

	initial
		begin: TEST_CASE
   			$dumpfile("RegWS_TB.vcd");
	     		$dumpvars(-1, DUT);
			#(300) $finish;
		end
	
	always
		#5 set32 = ~set32;

	initial
		begin
			reset = 1'b1;
			set32 = 1'b0;

			#60 reset = 1'b0;
			
			#60 reset = 1'b1;

		end

endmodule

FPGA-Game-D1-master/HW/RTL/06PCM-AUDIO-MICROFONO/Version_02/02 verilog/ProyectoDigital1/RegWS/simulation/RegWS_TB.vcd
$date
	Sat Sep 30 23:04:06 2017
$end
$version
	Icarus Verilog
$end
$timescale
	1ns
$end
$scope module RegWS_TB $end
$scope module DUT $end
$var wire 1 ! RESET $end
$var wire 1 " SET32 $end
$var reg 1 # WS $end
$upscope $end
$upscope $end
$enddefinitions $end
#0
$dumpvars
x#
0"
1!
$end
#5
0#
1"
#10
0"
#15
1"
#20
0"
#25
1"
#30
0"
#35
1"
#40
0"
#45
1"
#50
0"
#55
1"
#60
0"
0!
#65
1#
1"
#70
0"
#75
0#
1"
#80
0"
#85
1#
1"
#90
0"
#95
0#
1"
#100
0"
#105
1#
1"
#110
0"
#115
0#
1"
#120
0"
1!
#125
1"
#130
0"
#135
1"
#140
0"
#145
1"
#150
0"
#155
1"
#160
0"
#165
1"
#170
0"
#175
1"
#180
0"
#185
1"
#190
0"
#195
1"
#200
0"
#205
1"
#210
0"
#215
1"
#220
0"
#225
1"
#230
0"
#235
1"
#240
0"
#245
1"
#250
0"
#255
1"
#260
0"
#265
1"
#270
0"
#275
1"
#280
0"
#285
1"
#290
0"
#295
1"
#300
0"
