FPGA-Game-D1-master/HW/RTL/08ULTRASONIDO/Version_02/02 verilog/PorPruebas/BloquePruebaManual/contador.v
module contador		(
				output wire	[7:0] count,
				output reg	pulse,
				output reg	calculate,
				input	ECHO,
				//input	sign,
				input	ENABLE,
				input	CLKOUT,
				input	reset
			);
	reg [7:0] count0;
	reg logico;
	//reg calculate;
	initial 
	begin
		count0=0;
		pulse=0;
		calculate=0;
	end
	
	always@(reset or posedge CLKOUT or ENABLE)
	begin
		logico=(count0[7]||count0[6]||count0[5]||count0[4]||count0[3]||count0[2]||count0[1]||count0[0]);
		if(reset)
		begin
			count0=0;
			calculate=0;
			pulse=0;
		end
		//	Da la orden de mandar un pulso
		else
		begin
			if(ENABLE)
			begin
				pulse=1'b1;
			end
			//
			//	Cuenta el rango que tiene el pulso del ECHO del sensor
			//
			if(ECHO)
			begin
				count0=count0+1;
			end
			if(!ECHO && logico)
			begin
				calculate = 1;
			end
		end
	end
	assign count = count0;
endmodule

FPGA-Game-D1-master/HW/RTL/08ULTRASONIDO/Version_02/02 verilog/PorPruebas/ModulosBasicos/contador/contador_TB.v
module contador_TB;

	reg ECHO;
	reg ENABLE;
	reg CLKOUT;
	reg reset;
	contador  uut(.ECHO(ECHO),.ENABLE(ENABLE),.reset(reset),.CLKOUT(CLKOUT));

	always
	begin
		CLKOUT =1'b1;
		#1;
		CLKOUT =1'b0;
		#1;
	end

	initial 
	begin
		ECHO= 0;
		reset=1;
		ENABLE =1;
		#4;
		reset=0;
		ENABLE =1;
		#5;
		ECHO = 1;
		#50;
		ECHO =0;
		#20;
		
	end


initial begin: TEST_CASE
     $dumpfile("contador_TB.vcd");
     $dumpvars(-1, uut);
     #(200) $finish;
   end

endmodule //

FPGA-Game-D1-master/HW/RTL/08ULTRASONIDO/Version_02/02 verilog/PorPruebas/ModulosBasicos/contador/simulation/contador_TB.vcd
$date
	Sun Oct 22 18:51:06 2017
$end
$version
	Icarus Verilog
$end
$timescale
	1s
$end
$scope module contador_TB $end
$scope module uut $end
$var wire 1 ! CLKOUT $end
$var wire 1 " ECHO $end
$var wire 1 # ENABLE $end
$var wire 8 $ count [7:0] $end
$var wire 1 % reset $end
$var reg 1 & calculate $end
$var reg 8 ' count0 [7:0] $end
$var reg 1 ( logico $end
$var reg 1 ) pulse $end
$upscope $end
$upscope $end
$enddefinitions $end
#0
$dumpvars
0)
0(
b0 '
0&
1%
b0 $
1#
0"
1!
$end
#1
0!
#2
1!
#3
0!
#4
1)
1!
0%
#5
0!
#6
1!
#7
0!
#8
1!
#9
0!
1"
#10
b1 '
b1 $
1!
#11
0!
#12
b10 '
b10 $
1(
1!
#13
0!
#14
b11 '
b11 $
1!
#15
0!
#16
b100 '
b100 $
1!
#17
0!
#18
b101 '
b101 $
1!
#19
0!
#20
b110 '
b110 $
1!
#21
0!
#22
b111 '
b111 $
1!
#23
0!
#24
b1000 '
b1000 $
1!
#25
0!
#26
b1001 '
b1001 $
1!
#27
0!
#28
b1010 '
b1010 $
1!
#29
0!
#30
b1011 '
b1011 $
1!
#31
0!
#32
b1100 '
b1100 $
1!
#33
0!
#34
b1101 '
b1101 $
1!
#35
0!
#36
b1110 '
b1110 $
1!
#37
0!
#38
b1111 '
b1111 $
1!
#39
0!
#40
b10000 '
b10000 $
1!
#41
0!
#42
b10001 '
b10001 $
1!
#43
0!
#44
b10010 '
b10010 $
1!
#45
0!
#46
b10011 '
b10011 $
1!
#47
0!
#48
b10100 '
b10100 $
1!
#49
0!
#50
b10101 '
b10101 $
1!
#51
0!
#52
b10110 '
b10110 $
1!
#53
0!
#54
b10111 '
b10111 $
1!
#55
0!
#56
b11000 '
b11000 $
1!
#57
0!
#58
b11001 '
b11001 $
1!
#59
0!
0"
#60
1&
1!
