FPGA-Game-D1-master/HW/RTL/10KEYBOARD/Version_01/02 verilog/Touch/MódulosBásicos/PruebaPs2/ps2.v
module	ps2	(
			        input		            Rx,
			        input		            CLKOUT,
			        output	reg         Rx_error,
			        output	      [7:0]	DATA,
		        	output	reg	        DONE
		        );
	reg	[8:0]	regis;
	reg	[7:0]	regis0;
	reg	[3:0]	i;
	reg	[3:0]	j;
	reg	[1:0]	k;
	reg	init;
	reg	DoIt;
	//reg	NoDoIt;
	//reg	MakeIt=(DoIt && ~NoDoIt);
	initial
	begin
		i=0;
		j=0;
		init=0;
		regis=0;
		regis0=0;
		Rx_error=0;
		DONE=0;
		k=0;
		DoIt=1;
		//NoDoIt=0;
	end
	always@(posedge CLKOUT)
	begin
		if(!Rx&&!i)
		begin
			init<=1;
		end
//		lectura			//
//		lectura			//
//		lectura			//
		if(init)
		begin
			regis[i]=Rx;
			i<=i+1;
			if(regis[i]&&(i<8))
			begin
				j=j+1;
			end
		end
		if(DoIt)
		begin
			k<=k+1;
		end
		if(k==3)
		begin
			DONE=0;
			DoIt=0;
			Rx_error=0;
		end
		if(!DoIt)
		begin
			k<=0;
		end
		if(i==9)
		begin
			DoIt=1;
		end
		else
		begin
			
		end
//		finalizar		//
//		finalizar		//
//		finalizar		//
		if(i==9)
		begin
			if((!(j%2)&&(regis[8]))||((j%2)&&(!regis[8])))
			begin
				Rx_error=0;
				regis0={regis[7:0]};
				DONE=1;
			end
			else
			begin
				Rx_error=1;
				regis0=0;
				DONE=0;
			end
			j=0;
			i<=0;
			init=0;
		end
	end
	assign	DATA=regis0;
endmodule

FPGA-Game-D1-master/HW/RTL/10KEYBOARD/Version_01/02 verilog/Touch/Bloquetouch/touch/touch_TB.v
`timescale 1ns / 1ps
module ps2_TB;

	reg		Rx;
	reg		CLKOUT;
	ps2  uut(.CLKOUT(CLKOUT),.Rx(Rx));

	always
	begin
		CLKOUT =1'b1;
		#1;
		CLKOUT =1'b0;
		#1;
	end
	initial
	begin
		Rx=1;
		#10;
		Rx=0;
		#2;
		Rx=0;//1
		#2;
		Rx=0;
		#2;
		Rx=0;
		#2;
		Rx=1;
		#2;
		Rx=1;
		#2;
		Rx=1;
		#2;
		Rx=0;
		#2;
		Rx=0;//8
		#2;
		Rx=1;
		#2;
		Rx=1;
		#2;
		Rx=1;
		#10;
//	Otro
		Rx=0;
		#2;
		Rx=0;//1
		#2;
		Rx=0;
		#2;
		Rx=1;
		#2;
		Rx=1;
		#2;
		Rx=0;
		#2;
		Rx=0;
		#2;
		Rx=1;
		#2;
		Rx=0;//8
		#2;
		Rx=1;
		#2;
		Rx=1;
		#2;
		Rx=1;
		#10;
//	Seguidos
		Rx=0;
		#2;
		Rx=1;//1
		#2;
		Rx=0;
		#2;
		Rx=0;
		#2;
		Rx=1;
		#2;
		Rx=0;
		#2;
		Rx=0;
		#2;
		Rx=1;
		#2;
		Rx=1;//8
		#2;
		Rx=1;
		#2;
//	Continuación
		Rx=0;
		#2;
		Rx=1;//1
		#2;
		Rx=1;
		#2;
		Rx=1;
		#2;
		Rx=0;
		#2;
		Rx=0;
		#2;
		Rx=0;
		#2;
		Rx=0;
		#2;
		Rx=0;//8
		#2;
		Rx=1;
		#2;

//	Continuación
		Rx=0;
		#2;
		Rx=0;//1
		#2;
		Rx=0;
		#2;
		Rx=1;
		#2;
		Rx=1;
		#2;
		Rx=0;
		#2;
		Rx=0;
		#2;
		Rx=1;
		#2;
		Rx=0;//8
		#2;
		Rx=1;
		#2;

//	La Otra Prueba
		Rx=0;
		#2;
		Rx=0;//1
		#2;
		Rx=0;
		#2;
		Rx=1;
		#2;
		Rx=1;
		#2;
		Rx=1;
		#2;
		Rx=0;
		#2;
		Rx=1;
		#2;
		Rx=0;//8
		#2;
		Rx=1;
		#2;
		Rx=0;
		#2;
		Rx=0;//1
		#2;
		Rx=1;
		#2;
		Rx=1;
		#2;
		Rx=1;
		#2;
		Rx=0;
		#2;
		Rx=0;
		#2;
		Rx=1;
		#2;
		Rx=0;//8
		#2;
		Rx=1;
		#2;
	end

initial begin: TEST_CASE
     $dumpfile("ps2_TB.vcd");
     $dumpvars(-1, uut);
     #(400) $finish;
   end

endmodule //

FPGA-Game-D1-master/HW/RTL/10KEYBOARD/Version_01/02 verilog/Touch/MódulosBásicos/PruebaPs2/simulation/ps2_TB.vcd
$date
	Wed Nov 29 16:09:11 2017
$end
$version
	Icarus Verilog
$end
$timescale
	1ps
$end
$scope module ps2_TB $end
$scope module uut $end
$var wire 1 ! CLKOUT $end
$var wire 8 " DATA [7:0] $end
$var wire 1 # Rx $end
$var reg 1 $ DONE $end
$var reg 1 % DoIt $end
$var reg 1 & Rx_error $end
$var reg 4 ' i [3:0] $end
$var reg 1 ( init $end
$var reg 4 ) j [3:0] $end
$var reg 2 * k [1:0] $end
$var reg 9 + regis [8:0] $end
$var reg 8 , regis0 [7:0] $end
$upscope $end
$upscope $end
$enddefinitions $end
#0
$dumpvars
b0 ,
b0 +
b1 *
b0 )
0(
b0 '
0&
1%
0$
1#
b0 "
1!
$end
#1000
0!
#2000
b10 *
1!
#3000
0!
#4000
b11 *
1!
#5000
0!
#6000
b0 *
0%
1!
#7000
0!
#8000
1!
#9000
0!
#10000
1(
1!
0#
#11000
0!
#12000
b1 '
b0 +
1!
#13000
0!
#14000
b10 '
b0 +
1!
#15000
0!
#16000
b11 '
b0 +
1!
#17000
0!
#18000
b100 '
b1 )
b1000 +
1!
1#
#19000
0!
#20000
b101 '
b10 )
b11000 +
1!
#21000
0!
#22000
b110 '
b11 )
b111000 +
1!
#23000
0!
#24000
b111 '
b111000 +
1!
0#
#25000
0!
#26000
b1000 '
b111000 +
1!
#27000
0!
#28000
b1001 '
b100111000 +
1!
1#
#29000
0!
#30000
b0 '
0(
b0 )
1&
1%
1!
#31000
0!
#32000
b1 *
1!
#33000
0!
#34000
b10 *
1!
#35000
0!
#36000
b11 *
1!
#37000
0!
#38000
b0 *
0&
0%
1!
#39000
0!
#40000
1!
#41000
0!
#42000
1(
1!
0#
#43000
0!
#44000
b1 '
b100111000 +
1!
#45000
0!
#46000
b10 '
b100111000 +
1!
#47000
0!
#48000
b11 '
b1 )
b100111100 +
1!
1#
#49000
0!
#50000
b100 '
b10 )
b100111100 +
1!
#51000
0!
#52000
b101 '
b100101100 +
1!
0#
#53000
0!
#54000
b110 '
b100001100 +
1!
#55000
0!
#56000
b111 '
b11 )
b101001100 +
1!
1#
#57000
0!
#58000
b1000 '
b101001100 +
1!
0#
#59000
0!
#60000
b1001 '
b101001100 +
1!
1#
#61000
0!
#62000
b0 '
0(
b0 )
1&
1%
1!
#63000
0!
#64000
b1 *
1!
#65000
0!
#66000
b10 *
1!
#67000
0!
#68000
b11 *
1!
#69000
0!
#70000
b0 *
0&
0%
1!
#71000
0!
#72000
1!
#73000
0!
#74000
1(
1!
0#
#75000
0!
#76000
b1 '
b1 )
b101001101 +
1!
1#
#77000
0!
#78000
b10 '
b101001101 +
1!
0#
#79000
0!
#80000
b11 '
b101001001 +
1!
#81000
0!
#82000
b100 '
b10 )
b101001001 +
1!
1#
#83000
0!
#84000
b101 '
b101001001 +
1!
0#
#85000
0!
#86000
b110 '
b101001001 +
1!
#87000
0!
#88000
b111 '
b11 )
b101001001 +
1!
1#
#89000
0!
#90000
b1000 '
b100 )
b111001001 +
1!
#91000
0!
#92000
b1001 '
b111001001 +
1!
#93000
0!
#94000
b0 '
0(
b0 )
1$
b11001001 ,
b11001001 "
1%
1!
0#
#95000
0!
#96000
b1 *
1!
1#
#97000
0!
#98000
b10 *
1!
#99000
0!
#100000
b11 *
1!
#101000
0!
#102000
b0 *
1(
0%
0$
1!
0#
#103000
0!
#104000
b1 '
b111001000 +
1!
#105000
0!
#106000
b10 '
b111001000 +
1!
#107000
0!
#108000
b11 '
b111001000 +
1!
#109000
0!
#110000
b100 '
b111000000 +
1!
#111000
0!
#112000
b101 '
b1 )
b111010000 +
1!
1#
#113000
0!
#114000
b110 '
b111010000 +
1!
0#
#115000
0!
#116000
b111 '
b110010000 +
1!
#117000
0!
#118000
b1000 '
b100010000 +
1!
#119000
0!
#120000
b1001 '
b100010000 +
1!
1#
#121000
0!
#122000
b0 '
0(
b0 )
b0 ,
b0 "
1&
1%
1!
#123000
0!
#124000
b1 *
1(
1!
0#
#125000
0!
#126000
b10 *
b1 '
b100010000 +
1!
#127000
0!
#128000
b11 *
b10 '
b1 )
b100010010 +
1!
1#
#129000
0!
#130000
b0 *
b11 '
0&
0%
b100010010 +
1!
0#
#131000
0!
#132000
b100 '
b10 )
b100011010 +
1!
1#
#133000
0!
#134000
b101 '
b100001010 +
1!
0#
#135000
0!
#136000
b110 '
b100001010 +
1!
#137000
0!
#138000
b111 '
b100001010 +
1!
#139000
0!
#140000
b1000 '
b11 )
b110001010 +
1!
1#
#141000
0!
#142000
b1001 '
b110001010 +
1!
#143000
0!
#144000
b0 '
0(
b0 )
1&
1%
1!
#145000
0!
#146000
b1 *
1(
1!
0#
#147000
0!
#148000
b10 *
b1 '
b1 )
b110001011 +
1!
1#
#149000
0!
#150000
b11 *
b10 '
b110001001 +
1!
0#
#151000
0!
#152000
b0 *
b11 '
0&
0%
b10 )
b110001101 +
1!
1#
#153000
0!
#154000
b100 '
b110000101 +
1!
0#
#155000
0!
#156000
b101 '
b110000101 +
1!
#157000
0!
#158000
b110 '
b11 )
b110100101 +
1!
1#
#159000
0!
#160000
b111 '
b100 )
b111100101 +
1!
#161000
0!
#162000
b1000 '
b101 )
b111100101 +
1!
#163000
0!
#164000
b1001 '
b11100101 +
1!
0#
#165000
0!
#166000
b0 '
0(
b0 )
1$
b11100101 ,
b11100101 "
1%
1!
#167000
0!
#168000
b1 *
1!
1#
#169000
0!
#170000
b10 *
1(
1!
0#
#171000
0!
#172000
b11 *
b1 '
b1 )
b11100101 +
1!
1#
#173000
0!
#174000
b0 *
b10 '
0%
0$
b10 )
b11100111 +
1!
#175000
0!
#176000
b11 '
b11 )
b11100111 +
1!
#177000
0!
#178000
b100 '
b100 )
b11101111 +
1!
#179000
0!
#180000
b101 '
b101 )
b11111111 +
1!
#181000
0!
#182000
b110 '
b110 )
b11111111 +
1!
#183000
0!
#184000
b111 '
b111 )
b11111111 +
1!
#185000
0!
#186000
b1000 '
b1000 )
b11111111 +
1!
#187000
0!
#188000
b1001 '
b111111111 +
1!
#189000
0!
#190000
b0 '
0(
b0 )
1$
b11111111 ,
b11111111 "
1%
1!
#191000
0!
#192000
b1 *
1!
#193000
0!
#194000
b10 *
1!
#195000
0!
#196000
b11 *
1!
#197000
0!
#198000
b0 *
0%
0$
1!
