FPGA-Game-D1-master/HW/RTL/06PCM-AUDIO-MICROFONO/Version_01/02 verilog/Otros/Audio-SB/Microfono/div_freq.v
module div_freq #(
              parameter   fi     = 100000000 ,           
              parameter   fs	 = 20000000        
  )(input clk, output reg clkout,input reset);





reg [15:0] count;

always @(posedge  clk)
begin
	if (reset) begin
		count <= fi/fs;
		clkout <=0;
	end
	else begin
		count <=count-1;
		if (count==0)begin
			clkout <=~clkout;
			count <= fi/fs;
		end	
	end	
end


endmodule

FPGA-Game-D1-master/HW/RTL/06PCM-AUDIO-MICROFONO/Version_01/02 verilog/Otros/Audio-SB/v1/Microfono/microfono.v
module microfono
(
	input		enable,
	input		clk,
	output reg 	[17:0]  sdata,
	output		mclk,
	output		ws,
	input		dataint,
	input		reset,
	output		done

);

reg [0:31] count;
reg [17:0] sregt;
reg done;
reg ws=0;


div_freq df(.clk(clk), .reset(reset),.clkout(mclk));

always @(negedge  mclk, posedge enable)

	if (enable) 
	begin	
		done=0;
		count<=0;
		if (count<=17)  /* guarda 18 bits */
			begin
			sregt<= {sregt[16:0],dataint};
			count<=count+1;
			end
		
		else if(dataint<=1'b0) /* Verificar que despues del bit 18 todos sean 0 */
			begin
				if(count<=31) /* Verificar 32 bits de llegada*/
				begin		
				sdata<= sregt[17:0];
				count<=count+1;
				end
				else
				begin
				ws=!ws;     /* habilita canal R/L*/
				count<=0;   
				done=1;     /* confirma que ya esta el registro del canal*/
				end								
			end	
		else
			begin
			sregt<=0; /* si despues del bit 18 no sigue un 0 se pierde el registro */
			done=1;
				
		end	
						
	end	
	else
	begin
	end



endmodule

FPGA-Game-D1-master/HW/RTL/06PCM-AUDIO-MICROFONO/Version_01/02 verilog/Otros/Audio-SB/v1/Microfono/microfono_TB.v
module microfono_TB;

reg dataint;
reg clk;
reg enable;
reg mclk;
reg ws;
reg done;
reg reset;
microfono uut(.enable(enable),.reset(reset),.dataint(dataint),.clk(clk));

always
begin

clk =1'b1;
#2;
clk=1'b0;
#2;
end

initial
begin
reset =1'b1;
#10;
reset =1'b0;
end

initial begin
enable=0;
#10 enable=1;
end 
initial begin
dataint = 1'b0;
#40 dataint = 1'b1;
#40 dataint = 1'b0;
#40 dataint = 1'b1;
#40 dataint = 1'b0;
#40 dataint = 1'b0;
#40 dataint = 1'b1;
#40 dataint = 1'b0;
#40 dataint = 1'b1;
#40 dataint = 1'b0;
#40 dataint = 1'b1;
#40 dataint = 1'b0;
#40 dataint = 1'b1;
#40 dataint = 1'b1;
#40 dataint = 1'b0;
#40 dataint = 1'b1;
#70 dataint = 1'b0;
#650 dataint = 1'b0;
#40 dataint = 1'b1;
#40 dataint = 1'b0;
end
	
initial begin: TEST_CASE
     $dumpfile("microfono_TB.vcd");
     $dumpvars(-1, uut);
     #(10000) $finish;
   end

endmodule //

FPGA-Game-D1-master/HW/RTL/06PCM-AUDIO-MICROFONO/Version_01/02 verilog/Otros/Audio-SB/v1/Microfono/simulation/microfono_TB.vcd
$date
	Wed Oct 18 13:42:18 2017
$end
$version
	Icarus Verilog
$end
$timescale
	1s
$end
$scope module microfono_TB $end
$scope module uut $end
$var wire 1 ! clk $end
$var wire 1 " dataint $end
$var wire 1 # enable $end
$var wire 1 $ reset $end
$var wire 1 % mclk $end
$var reg 32 & count [0:31] $end
$var reg 1 ' done $end
$var reg 18 ( sdata [17:0] $end
$var reg 18 ) sregt [17:0] $end
$var reg 1 * ws $end
$scope module df $end
$var wire 1 ! clk $end
$var wire 1 $ reset $end
$var reg 1 % clkout $end
$var reg 16 + count [15:0] $end
$upscope $end
$upscope $end
$upscope $end
$enddefinitions $end
#0
$dumpvars
b100 +
0*
bx )
bx (
x'
bx &
0%
1$
0#
0"
1!
$end
#2
0!
#4
1!
#6
0!
#8
1!
#10
b0 &
1*
1'
0!
1#
0$
#12
b11 +
1!
#14
0!
#16
b10 +
1!
#18
0!
#20
b1 +
1!
#22
0!
#24
b0 +
1!
#26
0!
#28
1%
b100 +
1!
#30
0!
#32
b11 +
1!
#34
0!
#36
b10 +
1!
#38
0!
#40
b1 +
1!
1"
#42
0!
#44
b0 +
1!
#46
0!
#48
b1 &
bx1 )
0'
0%
b100 +
1!
#50
0!
#52
b11 +
1!
#54
0!
#56
b10 +
1!
#58
0!
#60
b1 +
1!
#62
0!
#64
b0 +
1!
#66
0!
#68
1%
b100 +
1!
#70
0!
#72
b11 +
1!
#74
0!
#76
b10 +
1!
#78
0!
#80
b1 +
1!
0"
#82
0!
#84
b0 +
1!
#86
0!
#88
bx10 )
b10 &
0%
b100 +
1!
#90
0!
#92
b11 +
1!
#94
0!
#96
b10 +
1!
#98
0!
#100
b1 +
1!
#102
0!
#104
b0 +
1!
#106
0!
#108
1%
b100 +
1!
#110
0!
#112
b11 +
1!
#114
0!
#116
b10 +
1!
#118
0!
#120
b1 +
1!
1"
#122
0!
#124
b0 +
1!
#126
0!
#128
bx101 )
b11 &
0%
b100 +
1!
#130
0!
#132
b11 +
1!
#134
0!
#136
b10 +
1!
#138
0!
#140
b1 +
1!
#142
0!
#144
b0 +
1!
#146
0!
#148
1%
b100 +
1!
#150
0!
#152
b11 +
1!
#154
0!
#156
b10 +
1!
#158
0!
#160
b1 +
1!
0"
#162
0!
#164
b0 +
1!
#166
0!
#168
bx1010 )
b100 &
0%
b100 +
1!
#170
0!
#172
b11 +
1!
#174
0!
#176
b10 +
1!
#178
0!
#180
b1 +
1!
#182
0!
#184
b0 +
1!
#186
0!
#188
1%
b100 +
1!
#190
0!
#192
b11 +
1!
#194
0!
#196
b10 +
1!
#198
0!
#200
b1 +
1!
#202
0!
#204
b0 +
1!
#206
0!
#208
bx10100 )
b101 &
0%
b100 +
1!
#210
0!
#212
b11 +
1!
#214
0!
#216
b10 +
1!
#218
0!
#220
b1 +
1!
#222
0!
#224
b0 +
1!
#226
0!
#228
1%
b100 +
1!
#230
0!
#232
b11 +
1!
#234
0!
#236
b10 +
1!
#238
0!
#240
b1 +
1!
1"
#242
0!
#244
b0 +
1!
#246
0!
#248
bx101001 )
b110 &
0%
b100 +
1!
#250
0!
#252
b11 +
1!
#254
0!
#256
b10 +
1!
#258
0!
#260
b1 +
1!
#262
0!
#264
b0 +
1!
#266
0!
#268
1%
b100 +
1!
#270
0!
#272
b11 +
1!
#274
0!
#276
b10 +
1!
#278
0!
#280
b1 +
1!
0"
#282
0!
#284
b0 +
1!
#286
0!
#288
bx1010010 )
b111 &
0%
b100 +
1!
#290
0!
#292
b11 +
1!
#294
0!
#296
b10 +
1!
#298
0!
#300
b1 +
1!
#302
0!
#304
b0 +
1!
#306
0!
#308
1%
b100 +
1!
#310
0!
#312
b11 +
1!
#314
0!
#316
b10 +
1!
#318
0!
#320
b1 +
1!
1"
#322
0!
#324
b0 +
1!
#326
0!
#328
bx10100101 )
b1000 &
0%
b100 +
1!
#330
0!
#332
b11 +
1!
#334
0!
#336
b10 +
1!
#338
0!
#340
b1 +
1!
#342
0!
#344
b0 +
1!
#346
0!
#348
1%
b100 +
1!
#350
0!
#352
b11 +
1!
#354
0!
#356
b10 +
1!
#358
0!
#360
b1 +
1!
0"
#362
0!
#364
b0 +
1!
#366
0!
#368
bx101001010 )
b1001 &
0%
b100 +
1!
#370
0!
#372
b11 +
1!
#374
0!
#376
b10 +
1!
#378
0!
#380
b1 +
1!
#382
0!
#384
b0 +
1!
#386
0!
#388
1%
b100 +
1!
#390
0!
#392
b11 +
1!
#394
0!
#396
b10 +
1!
#398
0!
#400
b1 +
1!
1"
#402
0!
#404
b0 +
1!
#406
0!
#408
bx1010010101 )
b1010 &
0%
b100 +
1!
#410
0!
#412
b11 +
1!
#414
0!
#416
b10 +
1!
#418
0!
#420
b1 +
1!
#422
0!
#424
b0 +
1!
#426
0!
#428
1%
b100 +
1!
#430
0!
#432
b11 +
1!
#434
0!
#436
b10 +
1!
#438
0!
#440
b1 +
1!
0"
#442
0!
#444
b0 +
1!
#446
0!
#448
bx10100101010 )
b1011 &
0%
b100 +
1!
#450
0!
#452
b11 +
1!
#454
0!
#456
b10 +
1!
#458
0!
#460
b1 +
1!
#462
0!
#464
b0 +
1!
#466
0!
#468
1%
b100 +
1!
#470
0!
#472
b11 +
1!
#474
0!
#476
b10 +
1!
#478
0!
#480
b1 +
1!
1"
#482
0!
#484
b0 +
1!
#486
0!
#488
bx101001010101 )
b1100 &
0%
b100 +
1!
#490
0!
#492
b11 +
1!
#494
0!
#496
b10 +
1!
#498
0!
#500
b1 +
1!
#502
0!
#504
b0 +
1!
#506
0!
#508
1%
b100 +
1!
#510
0!
#512
b11 +
1!
#514
0!
#516
b10 +
1!
#518
0!
#520
b1 +
1!
#522
0!
#524
b0 +
1!
#526
0!
#528
bx1010010101011 )
b1101 &
0%
b100 +
1!
#530
0!
#532
b11 +
1!
#534
0!
#536
b10 +
1!
#538
0!
#540
b1 +
1!
#542
0!
#544
b0 +
1!
#546
0!
#548
1%
b100 +
1!
#550
0!
#552
b11 +
1!
#554
0!
#556
b10 +
1!
#558
0!
#560
b1 +
1!
0"
#562
0!
#564
b0 +
1!
#566
0!
#568
bx10100101010110 )
b1110 &
0%
b100 +
1!
#570
0!
#572
b11 +
1!
#574
0!
#576
b10 +
1!
#578
0!
#580
b1 +
1!
#582
0!
#584
b0 +
1!
#586
0!
#588
1%
b100 +
1!
#590
0!
#592
b11 +
1!
#594
0!
#596
b10 +
1!
#598
0!
#600
b1 +
1!
1"
#602
0!
#604
b0 +
1!
#606
0!
#608
bx101001010101101 )
b1111 &
0%
b100 +
1!
#610
0!
#612
b11 +
1!
#614
0!
#616
b10 +
1!
#618
0!
#620
b1 +
1!
#622
0!
#624
b0 +
1!
#626
0!
#628
1%
b100 +
1!
#630
0!
#632
b11 +
1!
#634
0!
#636
b10 +
1!
#638
0!
#640
b1 +
1!
#642
0!
#644
b0 +
1!
#646
0!
#648
bx1010010101011011 )
b10000 &
0%
b100 +
1!
#650
0!
#652
b11 +
1!
#654
0!
#656
b10 +
1!
#658
0!
#660
b1 +
1!
#662
0!
#664
b0 +
1!
#666
0!
#668
1%
b100 +
1!
#670
0!
0"
#672
b11 +
1!
#674
0!
#676
b10 +
1!
#678
0!
#680
b1 +
1!
#682
0!
#684
b0 +
1!
#686
0!
#688
bx10100101010110110 )
b10001 &
0%
b100 +
1!
#690
0!
#692
b11 +
1!
#694
0!
#696
b10 +
1!
#698
0!
#700
b1 +
1!
#702
0!
#704
b0 +
1!
#706
0!
#708
1%
b100 +
1!
#710
0!
#712
b11 +
1!
#714
0!
#716
b10 +
1!
#718
0!
#720
b1 +
1!
#722
0!
#724
b0 +
1!
#726
0!
#728
b101001010101101100 )
b10010 &
0%
b100 +
1!
#730
0!
#732
b11 +
1!
#734
0!
#736
b10 +
1!
#738
0!
#740
b1 +
1!
#742
0!
#744
b0 +
1!
#746
0!
#748
1%
b100 +
1!
#750
0!
#752
b11 +
1!
#754
0!
#756
b10 +
1!
#758
0!
#760
b1 +
1!
#762
0!
#764
b0 +
1!
#766
0!
#768
b101001010101101100 (
b10011 &
0%
b100 +
1!
#770
0!
#772
b11 +
1!
#774
0!
#776
b10 +
1!
#778
0!
#780
b1 +
1!
#782
0!
#784
b0 +
1!
#786
0!
#788
1%
b100 +
1!
#790
0!
#792
b11 +
1!
#794
0!
#796
b10 +
1!
#798
0!
#800
b1 +
1!
#802
0!
#804
b0 +
1!
#806
0!
#808
b10100 &
0%
b100 +
1!
#810
0!
#812
b11 +
1!
#814
0!
#816
b10 +
1!
#818
0!
#820
b1 +
1!
#822
0!
#824
b0 +
1!
#826
0!
#828
1%
b100 +
1!
#830
0!
#832
b11 +
1!
#834
0!
#836
b10 +
1!
#838
0!
#840
b1 +
1!
#842
0!
#844
b0 +
1!
#846
0!
#848
b10101 &
0%
b100 +
1!
#850
0!
#852
b11 +
1!
#854
0!
#856
b10 +
1!
#858
0!
#860
b1 +
1!
#862
0!
#864
b0 +
1!
#866
0!
#868
1%
b100 +
1!
#870
0!
#872
b11 +
1!
#874
0!
#876
b10 +
1!
#878
0!
#880
b1 +
1!
#882
0!
#884
b0 +
1!
#886
0!
#888
b10110 &
0%
b100 +
1!
#890
0!
#892
b11 +
1!
#894
0!
#896
b10 +
1!
#898
0!
#900
b1 +
1!
#902
0!
#904
b0 +
1!
#906
0!
#908
1%
b100 +
1!
#910
0!
#912
b11 +
1!
#914
0!
#916
b10 +
1!
#918
0!
#920
b1 +
1!
#922
0!
#924
b0 +
1!
#926
0!
#928
b10111 &
0%
b100 +
1!
#930
0!
#932
b11 +
1!
#934
0!
#936
b10 +
1!
#938
0!
#940
b1 +
1!
#942
0!
#944
b0 +
1!
#946
0!
#948
1%
b100 +
1!
#950
0!
#952
b11 +
1!
#954
0!
#956
b10 +
1!
#958
0!
#960
b1 +
1!
#962
0!
#964
b0 +
1!
#966
0!
#968
b11000 &
0%
b100 +
1!
#970
0!
#972
b11 +
1!
#974
0!
#976
b10 +
1!
#978
0!
#980
b1 +
1!
#982
0!
#984
b0 +
1!
#986
0!
#988
1%
b100 +
1!
#990
0!
#992
b11 +
1!
#994
0!
#996
b10 +
1!
#998
0!
#1000
b1 +
1!
#1002
0!
#1004
b0 +
1!
#1006
0!
#1008
b11001 &
0%
b100 +
1!
#1010
0!
#1012
b11 +
1!
#1014
0!
#1016
b10 +
1!
#1018
0!
#1020
b1 +
1!
#1022
0!
#1024
b0 +
1!
#1026
0!
#1028
1%
b100 +
1!
#1030
0!
#1032
b11 +
1!
#1034
0!
#1036
b10 +
1!
#1038
0!
#1040
b1 +
1!
#1042
0!
#1044
b0 +
1!
#1046
0!
#1048
b11010 &
0%
b100 +
1!
#1050
0!
#1052
b11 +
1!
#1054
0!
#1056
b10 +
1!
#1058
0!
#1060
b1 +
1!
#1062
0!
#1064
b0 +
1!
#1066
0!
#1068
1%
b100 +
1!
#1070
0!
#1072
b11 +
1!
#1074
0!
#1076
b10 +
1!
#1078
0!
#1080
b1 +
1!
#1082
0!
#1084
b0 +
1!
#1086
0!
#1088
b11011 &
0%
b100 +
1!
#1090
0!
#1092
b11 +
1!
#1094
0!
#1096
b10 +
1!
#1098
0!
#1100
b1 +
1!
#1102
0!
#1104
b0 +
1!
#1106
0!
#1108
1%
b100 +
1!
#1110
0!
#1112
b11 +
1!
#1114
0!
#1116
b10 +
1!
#1118
0!
#1120
b1 +
1!
#1122
0!
#1124
b0 +
1!
#1126
0!
#1128
b11100 &
0%
b100 +
1!
#1130
0!
#1132
b11 +
1!
#1134
0!
#1136
b10 +
1!
#1138
0!
#1140
b1 +
1!
#1142
0!
#1144
b0 +
1!
#1146
0!
#1148
1%
b100 +
1!
#1150
0!
#1152
b11 +
1!
#1154
0!
#1156
b10 +
1!
#1158
0!
#1160
b1 +
1!
#1162
0!
#1164
b0 +
1!
#1166
0!
#1168
b11101 &
0%
b100 +
1!
#1170
0!
#1172
b11 +
1!
#1174
0!
#1176
b10 +
1!
#1178
0!
#1180
b1 +
1!
#1182
0!
#1184
b0 +
1!
#1186
0!
#1188
1%
b100 +
1!
#1190
0!
#1192
b11 +
1!
#1194
0!
#1196
b10 +
1!
#1198
0!
#1200
b1 +
1!
#1202
0!
#1204
b0 +
1!
#1206
0!
#1208
b11110 &
0%
b100 +
1!
#1210
0!
#1212
b11 +
1!
#1214
0!
#1216
b10 +
1!
#1218
0!
#1220
b1 +
1!
#1222
0!
#1224
b0 +
1!
#1226
0!
#1228
1%
b100 +
1!
#1230
0!
#1232
b11 +
1!
#1234
0!
#1236
b10 +
1!
#1238
0!
#1240
b1 +
1!
#1242
0!
#1244
b0 +
1!
#1246
0!
#1248
b11111 &
0%
b100 +
1!
#1250
0!
#1252
b11 +
1!
#1254
0!
#1256
b10 +
1!
#1258
0!
#1260
b1 +
1!
#1262
0!
#1264
b0 +
1!
#1266
0!
#1268
1%
b100 +
1!
#1270
0!
#1272
b11 +
1!
#1274
0!
#1276
b10 +
1!
#1278
0!
#1280
b1 +
1!
#1282
0!
#1284
b0 +
1!
#1286
0!
#1288
b100000 &
0%
b100 +
1!
#1290
0!
#1292
b11 +
1!
#1294
0!
#1296
b10 +
1!
#1298
0!
#1300
b1 +
1!
#1302
0!
#1304
b0 +
1!
#1306
0!
#1308
1%
b100 +
1!
#1310
0!
#1312
b11 +
1!
#1314
0!
#1316
b10 +
1!
#1318
0!
#1320
b1 +
1!
#1322
0!
#1324
b0 +
1!
#1326
0!
#1328
b0 &
1'
0*
0%
b100 +
1!
#1330
0!
#1332
b11 +
1!
#1334
0!
#1336
b10 +
1!
#1338
0!
#1340
b1 +
1!
#1342
0!
#1344
b0 +
1!
#1346
0!
#1348
1%
b100 +
1!
#1350
0!
#1352
b11 +
1!
#1354
0!
#1356
b10 +
1!
#1358
0!
#1360
b1 +
1!
1"
#1362
0!
#1364
b0 +
1!
#1366
0!
#1368
b1 &
b10010101011011001 )
0'
0%
b100 +
1!
#1370
0!
#1372
b11 +
1!
#1374
0!
#1376
b10 +
1!
#1378
0!
#1380
b1 +
1!
#1382
0!
#1384
b0 +
1!
#1386
0!
#1388
1%
b100 +
1!
#1390
0!
#1392
b11 +
1!
#1394
0!
#1396
b10 +
1!
#1398
0!
#1400
b1 +
1!
0"
#1402
0!
#1404
b0 +
1!
#1406
0!
#1408
b100101010110110010 )
b10 &
0%
b100 +
1!
#1410
0!
#1412
b11 +
1!
#1414
0!
#1416
b10 +
1!
#1418
0!
#1420
b1 +
1!
#1422
0!
#1424
b0 +
1!
#1426
0!
#1428
1%
b100 +
1!
#1430
0!
#1432
b11 +
1!
#1434
0!
#1436
b10 +
1!
#1438
0!
#1440
b1 +
1!
#1442
0!
#1444
b0 +
1!
#1446
0!
#1448
b1010101101100100 )
b11 &
0%
b100 +
1!
#1450
0!
#1452
b11 +
1!
#1454
0!
#1456
b10 +
1!
#1458
0!
#1460
b1 +
1!
#1462
0!
#1464
b0 +
1!
#1466
0!
#1468
1%
b100 +
1!
#1470
0!
#1472
b11 +
1!
#1474
0!
#1476
b10 +
1!
#1478
0!
#1480
b1 +
1!
#1482
0!
#1484
b0 +
1!
#1486
0!
#1488
b10101011011001000 )
b100 &
0%
b100 +
1!
#1490
0!
#1492
b11 +
1!
#1494
0!
#1496
b10 +
1!
#1498
0!
#1500
b1 +
1!
#1502
0!
#1504
b0 +
1!
#1506
0!
#1508
1%
b100 +
1!
#1510
0!
#1512
b11 +
1!
#1514
0!
#1516
b10 +
1!
#1518
0!
#1520
b1 +
1!
#1522
0!
#1524
b0 +
1!
#1526
0!
#1528
b101010110110010000 )
b101 &
0%
b100 +
1!
#1530
0!
#1532
b11 +
1!
#1534
0!
#1536
b10 +
1!
#1538
0!
#1540
b1 +
1!
#1542
0!
#1544
b0 +
1!
#1546
0!
#1548
1%
b100 +
1!
#1550
0!
#1552
b11 +
1!
#1554
0!
#1556
b10 +
1!
#1558
0!
#1560
b1 +
1!
#1562
0!
#1564
b0 +
1!
#1566
0!
#1568
b10101101100100000 )
b110 &
0%
b100 +
1!
#1570
0!
#1572
b11 +
1!
#1574
0!
#1576
b10 +
1!
#1578
0!
#1580
b1 +
1!
#1582
0!
#1584
b0 +
1!
#1586
0!
#1588
1%
b100 +
1!
#1590
0!
#1592
b11 +
1!
#1594
0!
#1596
b10 +
1!
#1598
0!
#1600
b1 +
1!
#1602
0!
#1604
b0 +
1!
#1606
0!
#1608
b101011011001000000 )
b111 &
0%
b100 +
1!
#1610
0!
#1612
b11 +
1!
#1614
0!
#1616
b10 +
1!
#1618
0!
#1620
b1 +
1!
#1622
0!
#1624
b0 +
1!
#1626
0!
#1628
1%
b100 +
1!
#1630
0!
#1632
b11 +
1!
#1634
0!
#1636
b10 +
1!
#1638
0!
#1640
b1 +
1!
#1642
0!
#1644
b0 +
1!
#1646
0!
#1648
b10110110010000000 )
b1000 &
0%
b100 +
1!
#1650
0!
#1652
b11 +
1!
#1654
0!
#1656
b10 +
1!
#1658
0!
#1660
b1 +
1!
#1662
0!
#1664
b0 +
1!
#1666
0!
#1668
1%
b100 +
1!
#1670
0!
#1672
b11 +
1!
#1674
0!
#1676
b10 +
1!
#1678
0!
#1680
b1 +
1!
#1682
0!
#1684
b0 +
1!
#1686
0!
#1688
b101101100100000000 )
b1001 &
0%
b100 +
1!
#1690
0!
#1692
b11 +
1!
#1694
0!
#1696
b10 +
1!
#1698
0!
#1700
b1 +
1!
#1702
0!
#1704
b0 +
1!
#1706
0!
#1708
1%
b100 +
1!
#1710
0!
#1712
b11 +
1!
#1714
0!
#1716
b10 +
1!
#1718
0!
#1720
b1 +
1!
#1722
0!
#1724
b0 +
1!
#1726
0!
#1728
b11011001000000000 )
b1010 &
0%
b100 +
1!
#1730
0!
#1732
b11 +
1!
#1734
0!
#1736
b10 +
1!
#1738
0!
#1740
b1 +
1!
#1742
0!
#1744
b0 +
1!
#1746
0!
#1748
1%
b100 +
1!
#1750
0!
#1752
b11 +
1!
#1754
0!
#1756
b10 +
1!
#1758
0!
#1760
b1 +
1!
#1762
0!
#1764
b0 +
1!
#1766
0!
#1768
b110110010000000000 )
b1011 &
0%
b100 +
1!
#1770
0!
#1772
b11 +
1!
#1774
0!
#1776
b10 +
1!
#1778
0!
#1780
b1 +
1!
#1782
0!
#1784
b0 +
1!
#1786
0!
#1788
1%
b100 +
1!
#1790
0!
#1792
b11 +
1!
#1794
0!
#1796
b10 +
1!
#1798
0!
#1800
b1 +
1!
#1802
0!
#1804
b0 +
1!
#1806
0!
#1808
b101100100000000000 )
b1100 &
0%
b100 +
1!
#1810
0!
#1812
b11 +
1!
#1814
0!
#1816
b10 +
1!
#1818
0!
#1820
b1 +
1!
#1822
0!
#1824
b0 +
1!
#1826
0!
#1828
1%
b100 +
1!
#1830
0!
#1832
b11 +
1!
#1834
0!
#1836
b10 +
1!
#1838
0!
#1840
b1 +
1!
#1842
0!
#1844
b0 +
1!
#1846
0!
#1848
b11001000000000000 )
b1101 &
0%
b100 +
1!
#1850
0!
#1852
b11 +
1!
#1854
0!
#1856
b10 +
1!
#1858
0!
#1860
b1 +
1!
#1862
0!
#1864
b0 +
1!
#1866
0!
#1868
1%
b100 +
1!
#1870
0!
#1872
b11 +
1!
#1874
0!
#1876
b10 +
1!
#1878
0!
#1880
b1 +
1!
#1882
0!
#1884
b0 +
1!
#1886
0!
#1888
b110010000000000000 )
b1110 &
0%
b100 +
1!
#1890
0!
#1892
b11 +
1!
#1894
0!
#1896
b10 +
1!
#1898
0!
#1900
b1 +
1!
#1902
0!
#1904
b0 +
1!
#1906
0!
#1908
1%
b100 +
1!
#1910
0!
#1912
b11 +
1!
#1914
0!
#1916
b10 +
1!
#1918
0!
#1920
b1 +
1!
#1922
0!
#1924
b0 +
1!
#1926
0!
#1928
b100100000000000000 )
b1111 &
0%
b100 +
1!
#1930
0!
#1932
b11 +
1!
#1934
0!
#1936
b10 +
1!
#1938
0!
#1940
b1 +
1!
#1942
0!
#1944
b0 +
1!
#1946
0!
#1948
1%
b100 +
1!
#1950
0!
#1952
b11 +
1!
#1954
0!
#1956
b10 +
1!
#1958
0!
#1960
b1 +
1!
#1962
0!
#1964
b0 +
1!
#1966
0!
#1968
b1000000000000000 )
b10000 &
0%
b100 +
1!
#1970
0!
#1972
b11 +
1!
#1974
0!
#1976
b10 +
1!
#1978
0!
#1980
b1 +
1!
#1982
0!
#1984
b0 +
1!
#1986
0!
#1988
1%
b100 +
1!
#1990
0!
#1992
b11 +
1!
#1994
0!
#1996
b10 +
1!
#1998
0!
#2000
b1 +
1!
#2002
0!
#2004
b0 +
1!
#2006
0!
#2008
b10000000000000000 )
b10001 &
0%
b100 +
1!
#2010
0!
#2012
b11 +
1!
#2014
0!
#2016
b10 +
1!
#2018
0!
#2020
b1 +
1!
#2022
0!
#2024
b0 +
1!
#2026
0!
#2028
1%
b100 +
1!
#2030
0!
#2032
b11 +
1!
#2034
0!
#2036
b10 +
1!
#2038
0!
#2040
b1 +
1!
#2042
0!
#2044
b0 +
1!
#2046
0!
#2048
b100000000000000000 )
b10010 &
0%
b100 +
1!
#2050
0!
#2052
b11 +
1!
#2054
0!
#2056
b10 +
1!
#2058
0!
#2060
b1 +
1!
#2062
0!
#2064
b0 +
1!
#2066
0!
#2068
1%
b100 +
1!
#2070
0!
#2072
b11 +
1!
#2074
0!
#2076
b10 +
1!
#2078
0!
#2080
b1 +
1!
#2082
0!
#2084
b0 +
1!
#2086
0!
#2088
b100000000000000000 (
b10011 &
0%
b100 +
1!
#2090
0!
#2092
b11 +
1!
#2094
0!
#2096
b10 +
1!
#2098
0!
#2100
b1 +
1!
#2102
0!
#2104
b0 +
1!
#2106
0!
#2108
1%
b100 +
1!
#2110
0!
#2112
b11 +
1!
#2114
0!
#2116
b10 +
1!
#2118
0!
#2120
b1 +
1!
#2122
0!
#2124
b0 +
1!
#2126
0!
#2128
b10100 &
0%
b100 +
1!
#2130
0!
#2132
b11 +
1!
#2134
0!
#2136
b10 +
1!
#2138
0!
#2140
b1 +
1!
#2142
0!
#2144
b0 +
1!
#2146
0!
#2148
1%
b100 +
1!
#2150
0!
#2152
b11 +
1!
#2154
0!
#2156
b10 +
1!
#2158
0!
#2160
b1 +
1!
#2162
0!
#2164
b0 +
1!
#2166
0!
#2168
b10101 &
0%
b100 +
1!
#2170
0!
#2172
b11 +
1!
#2174
0!
#2176
b10 +
1!
#2178
0!
#2180
b1 +
1!
#2182
0!
#2184
b0 +
1!
#2186
0!
#2188
1%
b100 +
1!
#2190
0!
#2192
b11 +
1!
#2194
0!
#2196
b10 +
1!
#2198
0!
#2200
b1 +
1!
#2202
0!
#2204
b0 +
1!
#2206
0!
#2208
b10110 &
0%
b100 +
1!
#2210
0!
#2212
b11 +
1!
#2214
0!
#2216
b10 +
1!
#2218
0!
#2220
b1 +
1!
#2222
0!
#2224
b0 +
1!
#2226
0!
#2228
1%
b100 +
1!
#2230
0!
#2232
b11 +
1!
#2234
0!
#2236
b10 +
1!
#2238
0!
#2240
b1 +
1!
#2242
0!
#2244
b0 +
1!
#2246
0!
#2248
b10111 &
0%
b100 +
1!
#2250
0!
#2252
b11 +
1!
#2254
0!
#2256
b10 +
1!
#2258
0!
#2260
b1 +
1!
#2262
0!
#2264
b0 +
1!
#2266
0!
#2268
1%
b100 +
1!
#2270
0!
#2272
b11 +
1!
#2274
0!
#2276
b10 +
1!
#2278
0!
#2280
b1 +
1!
#2282
0!
#2284
b0 +
1!
#2286
0!
#2288
b11000 &
0%
b100 +
1!
#2290
0!
#2292
b11 +
1!
#2294
0!
#2296
b10 +
1!
#2298
0!
#2300
b1 +
1!
#2302
0!
#2304
b0 +
1!
#2306
0!
#2308
1%
b100 +
1!
#2310
0!
#2312
b11 +
1!
#2314
0!
#2316
b10 +
1!
#2318
0!
#2320
b1 +
1!
#2322
0!
#2324
b0 +
1!
#2326
0!
#2328
b11001 &
0%
b100 +
1!
#2330
0!
#2332
b11 +
1!
#2334
0!
#2336
b10 +
1!
#2338
0!
#2340
b1 +
1!
#2342
0!
#2344
b0 +
1!
#2346
0!
#2348
1%
b100 +
1!
#2350
0!
#2352
b11 +
1!
#2354
0!
#2356
b10 +
1!
#2358
0!
#2360
b1 +
1!
#2362
0!
#2364
b0 +
1!
#2366
0!
#2368
b11010 &
0%
b100 +
1!
#2370
0!
#2372
b11 +
1!
#2374
0!
#2376
b10 +
1!
#2378
0!
#2380
b1 +
1!
#2382
0!
#2384
b0 +
1!
#2386
0!
#2388
1%
b100 +
1!
#2390
0!
#2392
b11 +
1!
#2394
0!
#2396
b10 +
1!
#2398
0!
#2400
b1 +
1!
#2402
0!
#2404
b0 +
1!
#2406
0!
#2408
b11011 &
0%
b100 +
1!
#2410
0!
#2412
b11 +
1!
#2414
0!
#2416
b10 +
1!
#2418
0!
#2420
b1 +
1!
#2422
0!
#2424
b0 +
1!
#2426
0!
#2428
1%
b100 +
1!
#2430
0!
#2432
b11 +
1!
#2434
0!
#2436
b10 +
1!
#2438
0!
#2440
b1 +
1!
#2442
0!
#2444
b0 +
1!
#2446
0!
#2448
b11100 &
0%
b100 +
1!
#2450
0!
#2452
b11 +
1!
#2454
0!
#2456
b10 +
1!
#2458
0!
#2460
b1 +
1!
#2462
0!
#2464
b0 +
1!
#2466
0!
#2468
1%
b100 +
1!
#2470
0!
#2472
b11 +
1!
#2474
0!
#2476
b10 +
1!
#2478
0!
#2480
b1 +
1!
#2482
0!
#2484
b0 +
1!
#2486
0!
#2488
b11101 &
0%
b100 +
1!
#2490
0!
#2492
b11 +
1!
#2494
0!
#2496
b10 +
1!
#2498
0!
#2500
b1 +
1!
#2502
0!
#2504
b0 +
1!
#2506
0!
#2508
1%
b100 +
1!
#2510
0!
#2512
b11 +
1!
#2514
0!
#2516
b10 +
1!
#2518
0!
#2520
b1 +
1!
#2522
0!
#2524
b0 +
1!
#2526
0!
#2528
b11110 &
0%
b100 +
1!
#2530
0!
#2532
b11 +
1!
#2534
0!
#2536
b10 +
1!
#2538
0!
#2540
b1 +
1!
#2542
0!
#2544
b0 +
1!
#2546
0!
#2548
1%
b100 +
1!
#2550
0!
#2552
b11 +
1!
#2554
0!
#2556
b10 +
1!
#2558
0!
#2560
b1 +
1!
#2562
0!
#2564
b0 +
1!
#2566
0!
#2568
b11111 &
0%
b100 +
1!
#2570
0!
#2572
b11 +
1!
#2574
0!
#2576
b10 +
1!
#2578
0!
#2580
b1 +
1!
#2582
0!
#2584
b0 +
1!
#2586
0!
#2588
1%
b100 +
1!
#2590
0!
#2592
b11 +
1!
#2594
0!
#2596
b10 +
1!
#2598
0!
#2600
b1 +
1!
#2602
0!
#2604
b0 +
1!
#2606
0!
#2608
b100000 &
0%
b100 +
1!
#2610
0!
#2612
b11 +
1!
#2614
0!
#2616
b10 +
1!
#2618
0!
