FPGA-Game-D1-master/HW/RTL/00EJEMPLOS/01shift_universal/shift_universal.v
module shift_universal #(parameter N=8)(input clk, input reset,input [N-1:0] d, input [1:0]ctrl, output [N-1:0] q);


// declaracion  de  variables
reg [N-1:0] r_reg;
reg [N-1:0] r_next;

//register
always @(posedge clk, posedge reset)
begin
if (reset)
	r_reg<=0;
else
	r_reg<=r_next;

end 
//Next_state
always  @(posedge reset, posedge clk)
begin
if(reset)
	r_next<=0;
else	
	case(ctrl)
	2'b00:r_next<=r_reg;
	2'b01:r_next<={r_reg[N-2:0], d[0]};
	2'b10:r_next<={d[N-1],r_reg[N-1:1]};
	2'b11: r_next<=d;
	endcase

end
// salida

assign q=r_reg ;




endmodule

FPGA-Game-D1-master/HW/RTL/00EJEMPLOS/01shift_universal/shift_universal_TB.v
module shift_universal_TB;

reg [7:0] d_s;
reg [1:0] ctrl;
reg clk;
reg reset;
shift_universal  uut(.d(d_s),.ctrl(ctrl),.reset(reset),.clk(clk));

always
begin
clk =1'b1;
#2;
clk=1'b0;
#2;
end

initial begin
d_s= 8'b10101110;

reset=1;
#4;
reset=0;
#3;
ctrl = 2'b00;
#5;
ctrl =2'b11;
#20;
ctrl =2'b01;



end


initial begin: TEST_CASE
     $dumpfile("shift_universal_TB.vcd");
     $dumpvars(-1, uut);
     #(200) $finish;
   end

endmodule //

FPGA-Game-D1-master/HW/RTL/00EJEMPLOS/01shift_universal/simulation/shift_universal_TB.vcd
$date
	Thu Oct 19 19:23:59 2017
$end
$version
	Icarus Verilog
$end
$timescale
	1s
$end
$scope module shift_universal_TB $end
$scope module uut $end
$var wire 1 ! clk $end
$var wire 2 " ctrl [1:0] $end
$var wire 8 # d [7:0] $end
$var wire 8 $ q [7:0] $end
$var wire 1 % reset $end
$var reg 8 & r_next [7:0] $end
$var reg 8 ' r_reg [7:0] $end
$upscope $end
$upscope $end
$enddefinitions $end
#0
$dumpvars
b0 '
b0 &
1%
b0 $
b10101110 #
bx "
1!
$end
#2
0!
#4
1!
0%
#6
0!
#7
b0 "
#8
1!
#10
0!
#12
b10101110 &
1!
b11 "
#14
0!
#16
b10101110 $
b10101110 '
1!
#18
0!
#20
1!
#22
0!
#24
1!
#26
0!
#28
1!
#30
0!
#32
b1011100 &
1!
b1 "
#34
0!
#36
b1011100 $
b1011100 '
1!
#38
0!
#40
b10111000 &
1!
#42
0!
#44
b10111000 $
b10111000 '
1!
#46
0!
#48
b1110000 &
1!
#50
0!
#52
b1110000 $
b1110000 '
1!
#54
0!
#56
b11100000 &
1!
#58
0!
#60
b11100000 $
b11100000 '
1!
#62
0!
#64
b11000000 &
1!
#66
0!
#68
b11000000 $
b11000000 '
1!
#70
0!
#72
b10000000 &
1!
#74
0!
#76
b10000000 $
b10000000 '
1!
#78
0!
#80
b0 &
1!
#82
0!
#84
b0 $
b0 '
1!
