FPGA-Game-D1-master/HW/RTL/06PCM-AUDIO-MICROFONO/Version_02/02 verilog/ProyectoDigital1/FSM/FSM.v
module FSM(reset,clk,enable,count18,count32,reset_int,done, en_bclk);

	input wire reset;
	input wire clk;
	input wire enable;
	input wire count18;
	input wire count32;
	output reg reset_int;
	output reg done;
	output reg en_bclk;

    localparam e_reset = 2'b00;
    localparam e_espera = 2'b01;
    localparam e_leer = 2'b11;

    reg [1:0] next_state =  e_reset;
    reg [1:0] state = e_reset;

	always@(reset, enable, count18, count32, state)
		begin
			if(reset)
				next_state = e_reset;
			    else
				if((state == e_reset) && enable)                
				    next_state = e_espera;
				else
				    if((state == e_espera) && count18)
				        next_state = e_leer;
				    else
				        if((state == e_leer) && count32)
				            next_state = e_espera;
				        else
				            next_state = state;
		end
    
    always@(posedge clk)
        if(reset)
            state = e_reset;
        else
            state = next_state;

    always@(state)
        case (state)
            e_reset:
                begin
                    done = 1'b0;
                    reset_int = 1'b1;
                    en_bclk = 1'b0;
                end
            e_espera:
                begin
                    done = 1'b0;
                    reset_int = 1'b0;
                    en_bclk = 1'b1;
                end
            e_leer:
                begin
                    done = 1'b1;
                    reset_int = 1'b0;
                    en_bclk = 1'b1;
                end
            default:
                begin
                    done = 1'b0;
                    reset_int = 1'b1;
                    en_bclk = 1'b0;
                end
		endcase
endmodule

FPGA-Game-D1-master/HW/RTL/06PCM-AUDIO-MICROFONO/Version_02/02 verilog/FSM_TB.v
`timescale 1ns / 1ns
module FSM_TB;

	reg reset;
	reg clk;
	reg enable;
	reg count18;
	reg count32;
	wire reset_int;
	wire done;
	wire en_bclk;

	FSM DUT(
		.reset(reset),
		.clk(clk),
		.enable(enable),
		.count18(count18),
		.count32(count32),
		.reset_int(reset_int),
		.done(done),
		.en_bclk(en_bclk)
	);

	always
		begin
			#1 clk = ~clk;
		end	

	initial
		begin: TEST_CASE
   			$dumpfile("FSM_TB.vcd");
     			$dumpvars(-1, DUT);
			#(500) $finish;
		end
	
	initial
		begin
			clk = 1'b0;
			reset = 1'b1;
			enable = 1'b0;
			count18 = 1'b0;
			count32 = 1'b0;

			#5 reset = 1'b0;

			#10 enable = 1'b1;
			#10 enable = 1'b0;

			#20 count18 = 1'b1;
			#2 count18 = 1'b0;

			#20 count32 = 1'b1;
			#2 count32 = 1'b0;

		end

endmodule

FPGA-Game-D1-master/HW/RTL/06PCM-AUDIO-MICROFONO/Version_02/02 verilog/ProyectoDigital1/FSM/simulation/FSM_TB.vcd
$date
	Wed Oct 18 07:15:36 2017
$end
$version
	Icarus Verilog
$end
$timescale
	1ns
$end
$scope module FSM_TB $end
$scope module DUT $end
$var wire 1 ! clk $end
$var wire 1 " count18 $end
$var wire 1 # count32 $end
$var wire 1 $ enable $end
$var wire 1 % reset $end
$var reg 1 & done $end
$var reg 1 ' en_bclk $end
$var reg 2 ( next_state [1:0] $end
$var reg 1 ) reset_int $end
$var reg 2 * state [1:0] $end
$upscope $end
$upscope $end
$enddefinitions $end
#0
$dumpvars
b0 *
1)
b0 (
0'
0&
1%
0$
0#
0"
0!
$end
#1
1!
#2
0!
#3
1!
#4
0!
#5
1!
0%
#6
0!
#7
1!
#8
0!
#9
1!
#10
0!
#11
1!
#12
0!
#13
1!
#14
0!
#15
1'
0)
b1 *
b1 (
1!
1$
#16
0!
#17
1!
#18
0!
#19
1!
#20
0!
#21
1!
#22
0!
#23
1!
#24
0!
#25
1!
0$
#26
0!
#27
1!
#28
0!
#29
1!
#30
0!
#31
1!
#32
0!
#33
1!
#34
0!
#35
1!
#36
0!
#37
1!
#38
0!
#39
1!
#40
0!
#41
1!
#42
0!
#43
1!
#44
0!
#45
1&
b11 *
b11 (
1!
1"
#46
0!
#47
1!
0"
#48
0!
#49
1!
#50
0!
#51
1!
#52
0!
#53
1!
#54
0!
#55
1!
#56
0!
#57
1!
#58
0!
#59
1!
#60
0!
#61
1!
#62
0!
#63
1!
#64
0!
#65
1!
#66
0!
#67
0&
b1 *
b1 (
1!
1#
#68
0!
#69
1!
0#
