FPGA-Game-D1-master/HW/RTL/00EJEMPLOS/00BCDtoSSeg/BCDtoSSeg.v
module BCDtoSSeg (clk, inBCD, SSeg);

  input clk;
  input [3:0] inBCD;
  output reg [6:0] SSeg;

always @ ( * ) begin
  case (inBCD)
    4'h0: SSeg = 7'b1111110;
    4'h1: SSeg = 7'b0110000;
    4'h2: SSeg = 7'b1101101;
    4'h3: SSeg = 7'b1111001;
    4'h4: SSeg = 7'b0110011;
    4'h5: SSeg = 7'b1011011;
    4'h6: SSeg = 7'b1011111;
    4'h7: SSeg = 7'b1110000;
    4'h8: SSeg = 7'b1111111;
    4'h9: SSeg = 7'b1111011;
    default:
    SSeg = 0;
  endcase
end

endmodule

FPGA-Game-D1-master/HW/RTL/00EJEMPLOS/00BCDtoSSeg/BCDtoSSeg_TB.v
module BCDtoSSeg_TB;

  reg [3:0] BCD;
  wire [6:0] SSeg;

BCDtoSSeg uut(.inBCD(BCD), .SSeg(SSeg));

initial begin

  BCD = 0; #10;
  BCD = 1; #10;
  BCD = 2; #10;
  BCD = 3; #10;
  BCD = 4; #10;
  BCD = 5; #10;
  BCD = 6; #10;
  BCD = 7; #10;
  BCD = 8; #10;
  BCD = 9; #10;

end

initial begin: TEST_CASE
     $dumpfile("BCDtoSSeg_TB.vcd");
     $dumpvars(-1, uut);
     #(200) $finish;
   end

endmodule //

FPGA-Game-D1-master/HW/RTL/00EJEMPLOS/00BCDtoSSeg/simulation/BCDtoSSeg_TB.vcd
$date
	Wed Mar  1 17:32:09 2017
$end
$version
	Icarus Verilog
$end
$timescale
	1s
$end
$scope module BCDtoSSeg_TB $end
$scope module uut $end
$var wire 1 ! clk $end
$var wire 4 " inBCD [3:0] $end
$var reg 7 # SSeg [6:0] $end
$upscope $end
$upscope $end
$enddefinitions $end
#0
$dumpvars
b1111110 #
b0 "
z!
$end
#10
b110000 #
b1 "
#20
b1101101 #
b10 "
#30
b1111001 #
b11 "
#40
b110011 #
b100 "
#50
b1011011 #
b101 "
#60
b1011111 #
b110 "
#70
b1110000 #
b111 "
#80
b1111111 #
b1000 "
#90
b1111011 #
b1001 "
