FPGA-Game-D1-master/HW/RTL/06PCM-AUDIO-MICROFONO/Version_02/02 verilog/ProyectoDigital1/FIFO/fifo.v
// diseño de una fifo ciclica, para implementar en cada  bloque de proyecto
// ferney alberto beltran 2016 electrónica digital 1 universidad Nacional

module fifo
   #(
  	parameter adr_width = 4,
	parameter dat_width = 8
   )
   (
    input  clk, reset,
    input  rd, wr,
    input  [dat_width-1:0] data_in,
    output [dat_width-1:0] data_out,
    output empty, 
    output full
   );

   
   parameter depth = (1 << adr_width);

   //declaración de registros 
 
   reg [dat_width-1:0] array_reg [depth-1:0];// register array FIFO

   reg [adr_width-1:0] w_ptr_reg, w_ptr_next;
   reg [adr_width-1:0] r_ptr_reg, r_ptr_next;
   reg full_reg, empty_reg, full_next, empty_next;
   wire wr_en;


   assign data_out = array_reg[r_ptr_reg];
   assign wr_en = wr & ~full_reg;

   assign full = full_reg;
   assign empty = empty_reg;

   always @(posedge clk) begin
      if (wr_en)
         array_reg[w_ptr_reg] <= data_in;
   end

   // fifo control logic
   // register for read and write pointers
   always @(posedge clk, posedge reset) begin
      if (reset)
         begin
            w_ptr_reg <= 0;
            r_ptr_reg <= 0;
            full_reg <= 1'b0;
            empty_reg <= 1'b1;
         end
      else
         begin
            w_ptr_reg <= w_ptr_next;
            r_ptr_reg <= r_ptr_next;
            full_reg <= full_next;
            empty_reg <= empty_next;
         end
   end


   
   always @(posedge reset, posedge wr, posedge rd)
   begin
      if (reset) begin
	w_ptr_next =  0;
        r_ptr_next =  0;       
      end else begin
	      full_next = full_reg;
	      empty_next = empty_reg;
	      case ({wr, rd})
		 2'b01: // read
		    if (~empty_reg) // not empty
		       begin
		          r_ptr_next = r_ptr_reg + 1;
		          full_next = 1'b0;
		          if (r_ptr_next==w_ptr_reg)
		             empty_next = 1'b1;
		       end
		 2'b10: // write
		    if (~full_reg) // not full
		       begin
		          w_ptr_next = w_ptr_reg + 1;
		          empty_next = 1'b0;
		          if (w_ptr_next==r_ptr_reg)
		             full_next = 1'b1;
		       end
		 2'b11: // write and read
		    begin
		       w_ptr_next =  w_ptr_reg + 1;
		       r_ptr_next = r_ptr_reg + 1;
		    end
	      endcase
	end
   end


  
endmodule

FPGA-Game-D1-master/HW/RTL/06PCM-AUDIO-MICROFONO/Version_02/02 verilog/ProyectoDigital1/Microfono/fifo_TB.v
//----------------------------------------------------------------------------
`timescale 1 ns / 100 ps

module fifo_TB;

//----------------------------------------------------------------------------
// Parameter (may differ for physical synthesis)
//----------------------------------------------------------------------------
parameter tck              = 2;       // clock period in ns
//----------------------------------------------------------------------------
//----------------------------------------------------------------------------

reg clk;
reg rst;

reg rd,wr;
reg [7:0] data_in;

//----------------------------------------------------------------------------
// Device Under Test 
//------------------------------------------------------------------

fifo  uut(.reset(rst),.clk(clk),.rd(rd),.wr(wr),.data_in(data_in));


/* Clocking device */
initial begin
	clk <= 0;
	rst <=1;
	#(2*tck) rst=0;
	rd <=0;
	wr<=0;
end

always #(tck/2) clk <= ~clk;


initial begin
#4;
data_in="h"; #1 wr=1; #2 wr=0;
data_in="o"; #1 wr=1; #2 wr=0;
data_in="l"; #1 wr=1; #2 wr=0;
data_in="a"; #1 wr=1; #2 wr=0;
data_in=" "; #1 wr=1; #2 wr=0;
data_in="m"; #1 wr=1; #2 wr=0;
data_in="u"; #1 wr=1; #2 wr=0;
data_in="n"; #1 wr=1; #2 wr=0;
data_in="d"; #1 wr=1; #2 wr=0;
data_in="o"; #1 wr=1; #2 wr=0;
data_in="."; #1 wr=1; #2 wr=0;
data_in="1"; #1 wr=1; #2 wr=0;
data_in="2"; #1 wr=1; #2 wr=0;
data_in="3"; #1 wr=1; #2 wr=0;
data_in="4"; #1 wr=1; #2 wr=0;
data_in="5"; #1 wr=1; #2 wr=0;
data_in="6"; #1 wr=1; #2 wr=0;
data_in="7"; #1 wr=1; #2 wr=0;
data_in="8"; #1 wr=1; #2 wr=0;
data_in="9"; #1 wr=1; #2 wr=0;
data_in="0"; #1 wr=1; #2 wr=0;

#1 rd=1; #2 rd=0;
#1 rd=1; #2 rd=0;
#1 rd=1; #2 rd=0;

data_in="a"; #1 wr=1; #2 wr=0;
data_in="b"; #1 wr=1; #2 wr=0;
data_in="c"; #1 wr=1; #2 wr=0;
data_in="d"; #1 wr=1; #2 wr=0;

#1 rd=1; #2 rd=0;
#1 rd=1; #2 rd=0;
#1 rd=1; #2 rd=0;
#1 rd=1; #2 rd=0;
#1 rd=1; #2 rd=0;
#1 rd=1; #2 rd=0;
#1 rd=1; #2 rd=0;
#1 rd=1; #2 rd=0;
#1 rd=1; #2 rd=0;
#1 rd=1; #2 rd=0;
#1 rd=1; #2 rd=0;
#1 rd=1; #2 rd=0;
#1 rd=1; #2 rd=0;
#1 rd=1; #2 rd=0;
#1 rd=1; #2 rd=0;
#1 rd=1; #2 rd=0;
#1 rd=1; #2 rd=0;
#1 rd=1; #2 rd=0;


end
initial begin: TEST_CASE
     $dumpfile("fifo_TB.vcd");
     $dumpvars(-1, uut);
     #(200) $finish;
   end

endmodule //

FPGA-Game-D1-master/HW/RTL/06PCM-AUDIO-MICROFONO/Version_02/02 verilog/ProyectoDigital1/FIFO/simulation/fifo_TB.vcd
$date
	Wed Oct 18 05:51:07 2017
$end
$version
	Icarus Verilog
$end
$timescale
	100ps
$end
$scope module fifo_TB $end
$scope module uut $end
$var wire 1 ! clk $end
$var wire 8 " data_in [7:0] $end
$var wire 8 # data_out [7:0] $end
$var wire 1 $ empty $end
$var wire 1 % full $end
$var wire 1 & rd $end
$var wire 1 ' reset $end
$var wire 1 ( wr $end
$var wire 1 ) wr_en $end
$var reg 1 * empty_next $end
$var reg 1 + empty_reg $end
$var reg 1 , full_next $end
$var reg 1 - full_reg $end
$var reg 4 . r_ptr_next [3:0] $end
$var reg 4 / r_ptr_reg [3:0] $end
$var reg 4 0 w_ptr_next [3:0] $end
$var reg 4 1 w_ptr_reg [3:0] $end
$upscope $end
$upscope $end
$enddefinitions $end
#0
$dumpvars
b0 1
b0 0
b0 /
b0 .
0-
x,
1+
x*
x)
x(
1'
x&
0%
1$
bx #
bx "
0!
$end
#10
1!
#20
0!
#30
1!
#40
0)
0!
0(
0&
b1101000 "
0'
#50
0+
0$
b1 1
b1101000 #
1!
1)
b1 0
0*
0,
1(
#60
0!
#70
1!
0)
b1101111 "
0(
#80
0!
1)
b10 0
1(
#90
b10 1
1!
#100
0!
0)
b1101100 "
0(
#110
b11 1
1!
1)
b11 0
1(
#120
0!
#130
1!
0)
b1100001 "
0(
#140
0!
1)
b100 0
1(
#150
b100 1
1!
#160
0!
0)
b100000 "
0(
#170
b101 1
1!
1)
b101 0
1(
#180
0!
#190
1!
0)
b1101101 "
0(
#200
0!
1)
b110 0
1(
#210
b110 1
1!
#220
0!
0)
b1110101 "
0(
#230
b111 1
1!
1)
b111 0
1(
#240
0!
#250
1!
0)
b1101110 "
0(
#260
0!
1)
b1000 0
1(
#270
b1000 1
1!
#280
0!
0)
b1100100 "
0(
#290
b1001 1
1!
1)
b1001 0
1(
#300
0!
#310
1!
0)
b1101111 "
0(
#320
0!
1)
b1010 0
1(
#330
b1010 1
1!
#340
0!
0)
b101110 "
0(
#350
b1011 1
1!
1)
b1011 0
1(
#360
0!
#370
1!
0)
b110001 "
0(
#380
0!
1)
b1100 0
1(
#390
b1100 1
1!
#400
0!
0)
b110010 "
0(
#410
b1101 1
1!
1)
b1101 0
1(
#420
0!
#430
1!
0)
b110011 "
0(
#440
0!
1)
b1110 0
1(
#450
b1110 1
1!
#460
0!
0)
b110100 "
0(
#470
b1111 1
1!
1)
b1111 0
1(
#480
0!
#490
1!
0)
b110101 "
0(
#500
0!
1)
1,
b0 0
1(
#510
0)
1-
1%
b0 1
1!
#520
0!
b110110 "
0(
#530
1!
1(
#540
0!
#550
1!
b110111 "
0(
#560
0!
1(
#570
1!
#580
0!
b111000 "
0(
#590
1!
1(
#600
0!
#610
1!
b111001 "
0(
#620
0!
1(
#630
1!
#640
0!
b110000 "
0(
#650
1!
1(
#660
0!
#670
1!
0(
#680
0!
0,
b1 .
1&
#690
0-
0%
b1 /
b1101111 #
1!
#700
0!
0&
#710
b10 /
b1101100 #
1!
b10 .
1&
#720
0!
#730
1!
0&
#740
0!
b11 .
1&
#750
b11 /
b1100001 #
1!
#760
0!
b1100001 "
0&
#770
b1 1
1!
1)
b1 0
1(
#780
0!
#790
1!
0)
b1100010 "
0(
#800
0!
1)
b10 0
1(
#810
b10 1
1!
#820
0!
0)
b1100011 "
0(
#830
1-
1%
b11 1
1!
0)
1,
b11 0
1(
#840
0!
#850
1!
b1100100 "
0(
#860
0!
1(
#870
1!
#880
0!
0(
#890
0-
0%
b100 /
b100000 #
1!
0,
b100 .
1&
#900
0!
#910
1!
0&
#920
0!
b101 .
1&
#930
b101 /
b1101101 #
1!
#940
0!
0&
#950
b110 /
b1110101 #
1!
b110 .
1&
#960
0!
#970
1!
0&
#980
0!
b111 .
1&
#990
b111 /
b1101110 #
1!
#1000
0!
0&
#1010
b1000 /
b1100100 #
1!
b1000 .
1&
#1020
0!
#1030
1!
0&
#1040
0!
b1001 .
1&
#1050
b1001 /
b1101111 #
1!
#1060
0!
0&
#1070
b1010 /
b101110 #
1!
b1010 .
1&
#1080
0!
#1090
1!
0&
#1100
0!
b1011 .
1&
#1110
b1011 /
b110001 #
1!
#1120
0!
0&
#1130
b1100 /
b110010 #
1!
b1100 .
1&
#1140
0!
#1150
1!
0&
#1160
0!
b1101 .
1&
#1170
b1101 /
b110011 #
1!
#1180
0!
0&
#1190
b1110 /
b110100 #
1!
b1110 .
1&
#1200
0!
#1210
1!
0&
#1220
0!
b1111 .
1&
#1230
b1111 /
b110101 #
1!
#1240
0!
0&
#1250
b0 /
b1100001 #
1!
b0 .
1&
#1260
0!
#1270
1!
0&
#1280
0!
b1 .
1&
#1290
b1 /
b1100010 #
1!
#1300
0!
0&
#1310
b10 /
b1100011 #
1!
b10 .
1&
#1320
0!
#1330
1!
0&
#1340
0!
1*
b11 .
1&
#1350
1+
1$
b11 /
b1100001 #
1!
#1360
0!
0&
#1370
1!
1&
#1380
0!
#1390
1!
0&
#1400
0!
1&
#1410
1!
#1420
0!
0&
