FPGA-Game-D1-master/HW/RTL/011J1G2/hdl/periferico_ultra/divisorfrecd.v
module	divisorfrecd	#(
				parameter top=11'b10110110110// top=100MHz/34.2kHz=2924, error: 0.0132%
			)
			(
				input           clk,
				output	reg	CLKOUTD
			);
	reg [10:0] count_1462;
	
	initial
	begin
		CLKOUTD=1'b1;
		count_1462=0;
	end
	
	always @(posedge clk) 
	begin
		count_1462 <= count_1462 + 1;
		if(count_1462 == top)
		begin
			count_1462<=0;
			CLKOUTD <= ~CLKOUTD;
		end
	end
endmodule

FPGA-Game-D1-master/HW/RTL/08ULTRASONIDO/Version_02/02 verilog/PorPruebas/ModulosBasicos/divisorfrecd/divisorfrecd_TB.v
`timescale 1ns / 1ps
module divisorfrecd_TB;

	reg		clk;
	divisorfrecd  uut(.clk(clk));

	always
	begin
		clk =1'b1;
		#2;
		clk =1'b0;
		#2;
	end


initial begin: TEST_CASE
     $dumpfile("divisorfrecd_TB.vcd");
     $dumpvars(-1, uut);
     #(100000) $finish;
   end

endmodule //

FPGA-Game-D1-master/HW/RTL/08ULTRASONIDO/Version_02/02 verilog/PorPruebas/ModulosBasicos/divisorfrecd/simulation/divisorfrecd_TB.vcd
$date
	Sun Oct 22 18:15:03 2017
$end
$version
	Icarus Verilog
$end
$timescale
	1ps
$end
$scope module divisorfrecd_TB $end
$scope module uut $end
$var wire 1 ! clk $end
$var reg 1 " CLKOUTD $end
$var reg 11 # count_1462 [10:0] $end
$upscope $end
$upscope $end
$enddefinitions $end
#0
$dumpvars
b1 #
1"
1!
$end
#2000
0!
#4000
b10 #
1!
#6000
0!
#8000
b11 #
1!
#10000
0!
#12000
b100 #
1!
#14000
0!
#16000
b101 #
1!
#18000
0!
#20000
b110 #
1!
#22000
0!
#24000
b111 #
1!
#26000
0!
#28000
b1000 #
1!
#30000
0!
#32000
b1001 #
1!
#34000
0!
#36000
b1010 #
1!
#38000
0!
#40000
b1011 #
1!
#42000
0!
#44000
b1100 #
1!
#46000
0!
#48000
b1101 #
1!
#50000
0!
#52000
b1110 #
1!
#54000
0!
#56000
b1111 #
1!
#58000
0!
#60000
b10000 #
1!
#62000
0!
#64000
b10001 #
1!
#66000
0!
#68000
b10010 #
1!
#70000
0!
#72000
b10011 #
1!
#74000
0!
#76000
b10100 #
1!
#78000
0!
#80000
b10101 #
1!
#82000
0!
#84000
b10110 #
1!
#86000
0!
#88000
b10111 #
1!
#90000
0!
#92000
b11000 #
1!
#94000
0!
#96000
b11001 #
1!
#98000
0!
#100000
b11010 #
1!
#102000
0!
#104000
b11011 #
1!
#106000
0!
#108000
b11100 #
1!
#110000
0!
#112000
b11101 #
1!
#114000
0!
#116000
b11110 #
1!
#118000
0!
#120000
b11111 #
1!
#122000
0!
#124000
b100000 #
1!
#126000
0!
#128000
b100001 #
1!
#130000
0!
#132000
b100010 #
1!
#134000
0!
#136000
b100011 #
1!
#138000
0!
#140000
b100100 #
1!
#142000
0!
#144000
b100101 #
1!
#146000
0!
#148000
b100110 #
1!
#150000
0!
#152000
b100111 #
1!
#154000
0!
#156000
b101000 #
1!
#158000
0!
#160000
b101001 #
1!
#162000
0!
#164000
b101010 #
1!
#166000
0!
#168000
b101011 #
1!
#170000
0!
#172000
b101100 #
1!
#174000
0!
#176000
b101101 #
1!
#178000
0!
#180000
b101110 #
1!
#182000
0!
#184000
b101111 #
1!
#186000
0!
#188000
b110000 #
1!
#190000
0!
#192000
b110001 #
1!
#194000
0!
#196000
b110010 #
1!
#198000
0!
#200000
b110011 #
1!
#202000
0!
#204000
b110100 #
1!
#206000
0!
#208000
b110101 #
1!
#210000
0!
#212000
b110110 #
1!
#214000
0!
#216000
b110111 #
1!
#218000
0!
#220000
b111000 #
1!
#222000
0!
#224000
b111001 #
1!
#226000
0!
#228000
b111010 #
1!
#230000
0!
#232000
b111011 #
1!
#234000
0!
#236000
b111100 #
1!
#238000
0!
#240000
b111101 #
1!
#242000
0!
#244000
b111110 #
1!
#246000
0!
#248000
b111111 #
1!
#250000
0!
#252000
b1000000 #
1!
#254000
0!
#256000
b1000001 #
1!
#258000
0!
#260000
b1000010 #
1!
#262000
0!
#264000
b1000011 #
1!
#266000
0!
#268000
b1000100 #
1!
#270000
0!
#272000
b1000101 #
1!
#274000
0!
#276000
b1000110 #
1!
#278000
0!
#280000
b1000111 #
1!
#282000
0!
#284000
b1001000 #
1!
#286000
0!
#288000
b1001001 #
1!
#290000
0!
#292000
b1001010 #
1!
#294000
0!
#296000
b1001011 #
1!
#298000
0!
#300000
b1001100 #
1!
#302000
0!
#304000
b1001101 #
1!
#306000
0!
#308000
b1001110 #
1!
#310000
0!
#312000
b1001111 #
1!
#314000
0!
#316000
b1010000 #
1!
#318000
0!
#320000
b1010001 #
1!
#322000
0!
#324000
b1010010 #
1!
#326000
0!
#328000
b1010011 #
1!
#330000
0!
#332000
b1010100 #
1!
#334000
0!
#336000
b1010101 #
1!
#338000
0!
#340000
b1010110 #
1!
#342000
0!
#344000
b1010111 #
1!
#346000
0!
#348000
b1011000 #
1!
#350000
0!
#352000
b1011001 #
1!
#354000
0!
#356000
b1011010 #
1!
#358000
0!
#360000
b1011011 #
1!
#362000
0!
#364000
b1011100 #
1!
#366000
0!
#368000
b1011101 #
1!
#370000
0!
#372000
b1011110 #
1!
#374000
0!
#376000
b1011111 #
1!
#378000
0!
#380000
b1100000 #
1!
#382000
0!
#384000
b1100001 #
1!
#386000
0!
#388000
b1100010 #
1!
#390000
0!
#392000
b1100011 #
1!
#394000
0!
#396000
b1100100 #
1!
#398000
0!
#400000
b1100101 #
1!
#402000
0!
#404000
b1100110 #
1!
#406000
0!
#408000
b1100111 #
1!
#410000
0!
#412000
b1101000 #
1!
#414000
0!
#416000
b1101001 #
1!
#418000
0!
#420000
b1101010 #
1!
#422000
0!
#424000
b1101011 #
1!
#426000
0!
#428000
b1101100 #
1!
#430000
0!
#432000
b1101101 #
1!
#434000
0!
#436000
b1101110 #
1!
#438000
0!
#440000
b1101111 #
1!
#442000
0!
#444000
b1110000 #
1!
#446000
0!
#448000
b1110001 #
1!
#450000
0!
#452000
b1110010 #
1!
#454000
0!
#456000
b1110011 #
1!
#458000
0!
#460000
b1110100 #
1!
#462000
0!
#464000
b1110101 #
1!
#466000
0!
#468000
b1110110 #
1!
#470000
0!
#472000
b1110111 #
1!
#474000
0!
#476000
b1111000 #
1!
#478000
0!
#480000
b1111001 #
1!
#482000
0!
#484000
b1111010 #
1!
#486000
0!
#488000
b1111011 #
1!
#490000
0!
#492000
b1111100 #
1!
#494000
0!
#496000
b1111101 #
1!
#498000
0!
#500000
b1111110 #
1!
#502000
0!
#504000
b1111111 #
1!
#506000
0!
#508000
b10000000 #
1!
#510000
0!
#512000
b10000001 #
1!
#514000
0!
#516000
b10000010 #
1!
#518000
0!
#520000
b10000011 #
1!
#522000
0!
#524000
b10000100 #
1!
#526000
0!
#528000
b10000101 #
1!
#530000
0!
#532000
b10000110 #
1!
#534000
0!
#536000
b10000111 #
1!
#538000
0!
#540000
b10001000 #
1!
#542000
0!
#544000
b10001001 #
1!
#546000
0!
#548000
b10001010 #
1!
#550000
0!
#552000
b10001011 #
1!
#554000
0!
#556000
b10001100 #
1!
#558000
0!
#560000
b10001101 #
1!
#562000
0!
#564000
b10001110 #
1!
#566000
0!
#568000
b10001111 #
1!
#570000
0!
#572000
b10010000 #
1!
#574000
0!
#576000
b10010001 #
1!
#578000
0!
#580000
b10010010 #
1!
#582000
0!
#584000
b10010011 #
1!
#586000
0!
#588000
b10010100 #
1!
#590000
0!
#592000
b10010101 #
1!
#594000
0!
#596000
b10010110 #
1!
#598000
0!
#600000
b10010111 #
1!
#602000
0!
#604000
b10011000 #
1!
#606000
0!
#608000
b10011001 #
1!
#610000
0!
#612000
b10011010 #
1!
#614000
0!
#616000
b10011011 #
1!
#618000
0!
#620000
b10011100 #
1!
#622000
0!
#624000
b10011101 #
1!
#626000
0!
#628000
b10011110 #
1!
#630000
0!
#632000
b10011111 #
1!
#634000
0!
#636000
b10100000 #
1!
#638000
0!
#640000
b10100001 #
1!
#642000
0!
#644000
b10100010 #
1!
#646000
0!
#648000
b10100011 #
1!
#650000
0!
#652000
b10100100 #
1!
#654000
0!
#656000
b10100101 #
1!
#658000
0!
#660000
b10100110 #
1!
#662000
0!
#664000
b10100111 #
1!
#666000
0!
#668000
b10101000 #
1!
#670000
0!
#672000
b10101001 #
1!
#674000
0!
#676000
b10101010 #
1!
#678000
0!
#680000
b10101011 #
1!
#682000
0!
#684000
b10101100 #
1!
#686000
0!
#688000
b10101101 #
1!
#690000
0!
#692000
b10101110 #
1!
#694000
0!
#696000
b10101111 #
1!
#698000
0!
#700000
b10110000 #
1!
#702000
0!
#704000
b10110001 #
1!
#706000
0!
#708000
b10110010 #
1!
#710000
0!
#712000
b10110011 #
1!
#714000
0!
#716000
b10110100 #
1!
#718000
0!
#720000
b10110101 #
1!
#722000
0!
#724000
b10110110 #
1!
#726000
0!
#728000
b10110111 #
1!
#730000
0!
#732000
b10111000 #
1!
#734000
0!
#736000
b10111001 #
1!
#738000
0!
#740000
b10111010 #
1!
#742000
0!
#744000
b10111011 #
1!
#746000
0!
#748000
b10111100 #
1!
#750000
0!
#752000
b10111101 #
1!
#754000
0!
#756000
b10111110 #
1!
#758000
0!
#760000
b10111111 #
1!
#762000
0!
#764000
b11000000 #
1!
#766000
0!
#768000
b11000001 #
1!
#770000
0!
#772000
b11000010 #
1!
#774000
0!
#776000
b11000011 #
1!
#778000
0!
#780000
b11000100 #
1!
#782000
0!
#784000
b11000101 #
1!
#786000
0!
#788000
b11000110 #
1!
#790000
0!
#792000
b11000111 #
1!
#794000
0!
#796000
b11001000 #
1!
#798000
0!
#800000
b11001001 #
1!
#802000
0!
#804000
b11001010 #
1!
#806000
0!
#808000
b11001011 #
1!
#810000
0!
#812000
b11001100 #
1!
#814000
0!
#816000
b11001101 #
1!
#818000
0!
#820000
b11001110 #
1!
#822000
0!
#824000
b11001111 #
1!
#826000
0!
#828000
b11010000 #
1!
#830000
0!
#832000
b11010001 #
1!
#834000
0!
#836000
b11010010 #
1!
#838000
0!
#840000
b11010011 #
1!
#842000
0!
#844000
b11010100 #
1!
#846000
0!
#848000
b11010101 #
1!
#850000
0!
#852000
b11010110 #
1!
#854000
0!
#856000
b11010111 #
1!
#858000
0!
#860000
b11011000 #
1!
#862000
0!
#864000
b11011001 #
1!
#866000
0!
#868000
b11011010 #
1!
#870000
0!
#872000
b11011011 #
1!
#874000
0!
#876000
b11011100 #
1!
#878000
0!
#880000
b11011101 #
1!
#882000
0!
#884000
b11011110 #
1!
#886000
0!
#888000
b11011111 #
1!
#890000
0!
#892000
b11100000 #
1!
#894000
0!
#896000
b11100001 #
1!
#898000
0!
#900000
b11100010 #
1!
#902000
0!
#904000
b11100011 #
1!
#906000
0!
#908000
b11100100 #
1!
#910000
0!
#912000
b11100101 #
1!
#914000
0!
#916000
b11100110 #
1!
#918000
0!
#920000
b11100111 #
1!
#922000
0!
#924000
b11101000 #
1!
#926000
0!
#928000
b11101001 #
1!
#930000
0!
#932000
b11101010 #
1!
#934000
0!
#936000
b11101011 #
1!
#938000
0!
#940000
b11101100 #
1!
#942000
0!
#944000
b11101101 #
1!
#946000
0!
#948000
b11101110 #
1!
#950000
0!
#952000
b11101111 #
1!
#954000
0!
#956000
b11110000 #
1!
#958000
0!
#960000
b11110001 #
1!
#962000
0!
#964000
b11110010 #
1!
#966000
0!
#968000
b11110011 #
1!
#970000
0!
#972000
b11110100 #
1!
#974000
0!
#976000
b11110101 #
1!
#978000
0!
#980000
b11110110 #
1!
#982000
0!
#984000
b11110111 #
1!
#986000
0!
#988000
b11111000 #
1!
#990000
0!
#992000
b11111001 #
1!
#994000
0!
#996000
b11111010 #
1!
#998000
0!
#1000000
b11111011 #
1!
#1002000
0!
#1004000
b11111100 #
1!
#1006000
0!
#1008000
b11111101 #
1!
#1010000
0!
#1012000
b11111110 #
1!
#1014000
0!
#1016000
b11111111 #
1!
#1018000
0!
#1020000
b100000000 #
1!
#1022000
0!
#1024000
b100000001 #
1!
#1026000
0!
#1028000
b100000010 #
1!
#1030000
0!
#1032000
b100000011 #
1!
#1034000
0!
#1036000
b100000100 #
1!
#1038000
0!
#1040000
b100000101 #
1!
#1042000
0!
#1044000
b100000110 #
1!
#1046000
0!
#1048000
b100000111 #
1!
#1050000
0!
#1052000
b100001000 #
1!
#1054000
0!
#1056000
b100001001 #
1!
#1058000
0!
#1060000
b100001010 #
1!
#1062000
0!
#1064000
b100001011 #
1!
#1066000
0!
#1068000
b100001100 #
1!
#1070000
0!
#1072000
b100001101 #
1!
#1074000
0!
#1076000
b100001110 #
1!
#1078000
0!
#1080000
b100001111 #
1!
#1082000
0!
#1084000
b100010000 #
1!
#1086000
0!
#1088000
b100010001 #
1!
#1090000
0!
#1092000
b100010010 #
1!
#1094000
0!
#1096000
b100010011 #
1!
#1098000
0!
#1100000
b100010100 #
1!
#1102000
0!
#1104000
b100010101 #
1!
#1106000
0!
#1108000
b100010110 #
1!
#1110000
0!
#1112000
b100010111 #
1!
#1114000
0!
#1116000
b100011000 #
1!
#1118000
0!
#1120000
b100011001 #
1!
#1122000
0!
#1124000
b100011010 #
1!
#1126000
0!
#1128000
b100011011 #
1!
#1130000
0!
#1132000
b100011100 #
1!
#1134000
0!
#1136000
b100011101 #
1!
#1138000
0!
#1140000
b100011110 #
1!
#1142000
0!
#1144000
b100011111 #
1!
#1146000
0!
#1148000
b100100000 #
1!
#1150000
0!
#1152000
b100100001 #
1!
#1154000
0!
#1156000
b100100010 #
1!
#1158000
0!
#1160000
b100100011 #
1!
#1162000
0!
#1164000
b100100100 #
1!
#1166000
0!
#1168000
b100100101 #
1!
#1170000
0!
#1172000
b100100110 #
1!
#1174000
0!
#1176000
b100100111 #
1!
#1178000
0!
#1180000
b100101000 #
1!
#1182000
0!
#1184000
b100101001 #
1!
#1186000
0!
#1188000
b100101010 #
1!
#1190000
0!
#1192000
b100101011 #
1!
#1194000
0!
#1196000
b100101100 #
1!
#1198000
0!
#1200000
b100101101 #
1!
#1202000
0!
#1204000
b100101110 #
1!
#1206000
0!
#1208000
b100101111 #
1!
#1210000
0!
#1212000
b100110000 #
1!
#1214000
0!
#1216000
b100110001 #
1!
#1218000
0!
#1220000
b100110010 #
1!
#1222000
0!
#1224000
b100110011 #
1!
#1226000
0!
#1228000
b100110100 #
1!
#1230000
0!
#1232000
b100110101 #
1!
#1234000
0!
#1236000
b100110110 #
1!
#1238000
0!
#1240000
b100110111 #
1!
#1242000
0!
#1244000
b100111000 #
1!
#1246000
0!
#1248000
b100111001 #
1!
#1250000
0!
#1252000
b100111010 #
1!
#1254000
0!
#1256000
b100111011 #
1!
#1258000
0!
#1260000
b100111100 #
1!
#1262000
0!
#1264000
b100111101 #
1!
#1266000
0!
#1268000
b100111110 #
1!
#1270000
0!
#1272000
b100111111 #
1!
#1274000
0!
#1276000
b101000000 #
1!
#1278000
0!
#1280000
b101000001 #
1!
#1282000
0!
#1284000
b101000010 #
1!
#1286000
0!
#1288000
b101000011 #
1!
#1290000
0!
#1292000
b101000100 #
1!
#1294000
0!
#1296000
b101000101 #
1!
#1298000
0!
#1300000
b101000110 #
1!
#1302000
0!
#1304000
b101000111 #
1!
#1306000
0!
#1308000
b101001000 #
1!
#1310000
0!
#1312000
b101001001 #
1!
#1314000
0!
#1316000
b101001010 #
1!
#1318000
0!
#1320000
b101001011 #
1!
#1322000
0!
#1324000
b101001100 #
1!
#1326000
0!
#1328000
b101001101 #
1!
#1330000
0!
#1332000
b101001110 #
1!
#1334000
0!
#1336000
b101001111 #
1!
#1338000
0!
#1340000
b101010000 #
1!
#1342000
0!
#1344000
b101010001 #
1!
#1346000
0!
#1348000
b101010010 #
1!
#1350000
0!
#1352000
b101010011 #
1!
#1354000
0!
#1356000
b101010100 #
1!
#1358000
0!
#1360000
b101010101 #
1!
#1362000
0!
#1364000
b101010110 #
1!
#1366000
0!
#1368000
b101010111 #
1!
#1370000
0!
#1372000
b101011000 #
1!
#1374000
0!
#1376000
b101011001 #
1!
#1378000
0!
#1380000
b101011010 #
1!
#1382000
0!
#1384000
b101011011 #
1!
#1386000
0!
#1388000
b101011100 #
1!
#1390000
0!
#1392000
b101011101 #
1!
#1394000
0!
#1396000
b101011110 #
1!
#1398000
0!
#1400000
b101011111 #
1!
#1402000
0!
#1404000
b101100000 #
1!
#1406000
0!
#1408000
b101100001 #
1!
#1410000
0!
#1412000
b101100010 #
1!
#1414000
0!
#1416000
b101100011 #
1!
#1418000
0!
#1420000
b101100100 #
1!
#1422000
0!
#1424000
b101100101 #
1!
#1426000
0!
#1428000
b101100110 #
1!
#1430000
0!
#1432000
b101100111 #
1!
#1434000
0!
#1436000
b101101000 #
1!
#1438000
0!
#1440000
b101101001 #
1!
#1442000
0!
#1444000
b101101010 #
1!
#1446000
0!
#1448000
b101101011 #
1!
#1450000
0!
#1452000
b101101100 #
1!
#1454000
0!
#1456000
b101101101 #
1!
#1458000
0!
#1460000
b101101110 #
1!
#1462000
0!
#1464000
b101101111 #
1!
#1466000
0!
#1468000
b101110000 #
1!
#1470000
0!
#1472000
b101110001 #
1!
#1474000
0!
#1476000
b101110010 #
1!
#1478000
0!
#1480000
b101110011 #
1!
#1482000
0!
#1484000
b101110100 #
1!
#1486000
0!
#1488000
b101110101 #
1!
#1490000
0!
#1492000
b101110110 #
1!
#1494000
0!
#1496000
b101110111 #
1!
#1498000
0!
#1500000
b101111000 #
1!
#1502000
0!
#1504000
b101111001 #
1!
#1506000
0!
#1508000
b101111010 #
1!
#1510000
0!
#1512000
b101111011 #
1!
#1514000
0!
#1516000
b101111100 #
1!
#1518000
0!
#1520000
b101111101 #
1!
#1522000
0!
#1524000
b101111110 #
1!
#1526000
0!
#1528000
b101111111 #
1!
#1530000
0!
#1532000
b110000000 #
1!
#1534000
0!
#1536000
b110000001 #
1!
#1538000
0!
#1540000
b110000010 #
1!
#1542000
0!
#1544000
b110000011 #
1!
#1546000
0!
#1548000
b110000100 #
1!
#1550000
0!
#1552000
b110000101 #
1!
#1554000
0!
#1556000
b110000110 #
1!
#1558000
0!
#1560000
b110000111 #
1!
#1562000
0!
#1564000
b110001000 #
1!
#1566000
0!
#1568000
b110001001 #
1!
#1570000
0!
#1572000
b110001010 #
1!
#1574000
0!
#1576000
b110001011 #
1!
#1578000
0!
#1580000
b110001100 #
1!
#1582000
0!
#1584000
b110001101 #
1!
#1586000
0!
#1588000
b110001110 #
1!
#1590000
0!
#1592000
b110001111 #
1!
#1594000
0!
#1596000
b110010000 #
1!
#1598000
0!
#1600000
b110010001 #
1!
#1602000
0!
#1604000
b110010010 #
1!
#1606000
0!
#1608000
b110010011 #
1!
#1610000
0!
#1612000
b110010100 #
1!
#1614000
0!
#1616000
b110010101 #
1!
#1618000
0!
#1620000
b110010110 #
1!
#1622000
0!
#1624000
b110010111 #
1!
#1626000
0!
#1628000
b110011000 #
1!
#1630000
0!
#1632000
b110011001 #
1!
#1634000
0!
#1636000
b110011010 #
1!
#1638000
0!
#1640000
b110011011 #
1!
#1642000
0!
#1644000
b110011100 #
1!
#1646000
0!
#1648000
b110011101 #
1!
#1650000
0!
#1652000
b110011110 #
1!
#1654000
0!
#1656000
b110011111 #
1!
#1658000
0!
#1660000
b110100000 #
1!
#1662000
0!
#1664000
b110100001 #
1!
#1666000
0!
#1668000
b110100010 #
1!
#1670000
0!
#1672000
b110100011 #
1!
#1674000
0!
#1676000
b110100100 #
1!
#1678000
0!
#1680000
b110100101 #
1!
#1682000
0!
#1684000
b110100110 #
1!
#1686000
0!
#1688000
b110100111 #
1!
#1690000
0!
#1692000
b110101000 #
1!
#1694000
0!
#1696000
b110101001 #
1!
#1698000
0!
#1700000
b110101010 #
1!
#1702000
0!
#1704000
b110101011 #
1!
#1706000
0!
#1708000
b110101100 #
1!
#1710000
0!
#1712000
b110101101 #
1!
#1714000
0!
#1716000
b110101110 #
1!
#1718000
0!
#1720000
b110101111 #
1!
#1722000
0!
#1724000
b110110000 #
1!
#1726000
0!
#1728000
b110110001 #
1!
#1730000
0!
#1732000
b110110010 #
1!
#1734000
0!
#1736000
b110110011 #
1!
#1738000
0!
#1740000
b110110100 #
1!
#1742000
0!
#1744000
b110110101 #
1!
#1746000
0!
#1748000
b110110110 #
1!
#1750000
0!
#1752000
b110110111 #
1!
#1754000
0!
#1756000
b110111000 #
1!
#1758000
0!
#1760000
b110111001 #
1!
#1762000
0!
#1764000
b110111010 #
1!
#1766000
0!
#1768000
b110111011 #
1!
#1770000
0!
#1772000
b110111100 #
1!
#1774000
0!
#1776000
b110111101 #
1!
#1778000
0!
#1780000
b110111110 #
1!
#1782000
0!
#1784000
b110111111 #
1!
#1786000
0!
#1788000
b111000000 #
1!
#1790000
0!
#1792000
b111000001 #
1!
#1794000
0!
#1796000
b111000010 #
1!
#1798000
0!
#1800000
b111000011 #
1!
#1802000
0!
#1804000
b111000100 #
1!
#1806000
0!
#1808000
b111000101 #
1!
#1810000
0!
#1812000
b111000110 #
1!
#1814000
0!
#1816000
b111000111 #
1!
#1818000
0!
#1820000
b111001000 #
1!
#1822000
0!
#1824000
b111001001 #
1!
#1826000
0!
#1828000
b111001010 #
1!
#1830000
0!
#1832000
b111001011 #
1!
#1834000
0!
#1836000
b111001100 #
1!
#1838000
0!
#1840000
b111001101 #
1!
#1842000
0!
#1844000
b111001110 #
1!
#1846000
0!
#1848000
b111001111 #
1!
#1850000
0!
#1852000
b111010000 #
1!
#1854000
0!
#1856000
b111010001 #
1!
#1858000
0!
#1860000
b111010010 #
1!
#1862000
0!
#1864000
b111010011 #
1!
#1866000
0!
#1868000
b111010100 #
1!
#1870000
0!
#1872000
b111010101 #
1!
#1874000
0!
#1876000
b111010110 #
1!
#1878000
0!
#1880000
b111010111 #
1!
#1882000
0!
#1884000
b111011000 #
1!
#1886000
0!
#1888000
b111011001 #
1!
#1890000
0!
#1892000
b111011010 #
1!
#1894000
0!
#1896000
b111011011 #
1!
#1898000
0!
#1900000
b111011100 #
1!
#1902000
0!
#1904000
b111011101 #
1!
#1906000
0!
#1908000
b111011110 #
1!
#1910000
0!
#1912000
b111011111 #
1!
#1914000
0!
#1916000
b111100000 #
1!
#1918000
0!
#1920000
b111100001 #
1!
#1922000
0!
#1924000
b111100010 #
1!
#1926000
0!
#1928000
b111100011 #
1!
#1930000
0!
#1932000
b111100100 #
1!
#1934000
0!
#1936000
b111100101 #
1!
#1938000
0!
#1940000
b111100110 #
1!
#1942000
0!
#1944000
b111100111 #
1!
#1946000
0!
#1948000
b111101000 #
1!
#1950000
0!
#1952000
b111101001 #
1!
#1954000
0!
#1956000
b111101010 #
1!
#1958000
0!
#1960000
b111101011 #
1!
#1962000
0!
#1964000
b111101100 #
1!
#1966000
0!
#1968000
b111101101 #
1!
#1970000
0!
#1972000
b111101110 #
1!
#1974000
0!
#1976000
b111101111 #
1!
#1978000
0!
#1980000
b111110000 #
1!
#1982000
0!
#1984000
b111110001 #
1!
#1986000
0!
#1988000
b111110010 #
1!
#1990000
0!
#1992000
b111110011 #
1!
#1994000
0!
#1996000
b111110100 #
1!
#1998000
0!
#2000000
b111110101 #
1!
#2002000
0!
#2004000
b111110110 #
1!
#2006000
0!
#2008000
b111110111 #
1!
#2010000
0!
#2012000
b111111000 #
1!
#2014000
0!
#2016000
b111111001 #
1!
#2018000
0!
#2020000
b111111010 #
1!
#2022000
0!
#2024000
b111111011 #
1!
#2026000
0!
#2028000
b111111100 #
1!
#2030000
0!
#2032000
b111111101 #
1!
#2034000
0!
#2036000
b111111110 #
1!
#2038000
0!
#2040000
b111111111 #
1!
#2042000
0!
#2044000
b1000000000 #
1!
#2046000
0!
#2048000
b1000000001 #
1!
#2050000
0!
#2052000
b1000000010 #
1!
#2054000
0!
#2056000
b1000000011 #
1!
#2058000
0!
#2060000
b1000000100 #
1!
#2062000
0!
#2064000
b1000000101 #
1!
#2066000
0!
#2068000
b1000000110 #
1!
#2070000
0!
#2072000
b1000000111 #
1!
#2074000
0!
#2076000
b1000001000 #
1!
#2078000
0!
#2080000
b1000001001 #
1!
#2082000
0!
#2084000
b1000001010 #
1!
#2086000
0!
#2088000
b1000001011 #
1!
#2090000
0!
#2092000
b1000001100 #
1!
#2094000
0!
#2096000
b1000001101 #
1!
#2098000
0!
#2100000
b1000001110 #
1!
#2102000
0!
#2104000
b1000001111 #
1!
#2106000
0!
#2108000
b1000010000 #
1!
#2110000
0!
#2112000
b1000010001 #
1!
#2114000
0!
#2116000
b1000010010 #
1!
#2118000
0!
#2120000
b1000010011 #
1!
#2122000
0!
#2124000
b1000010100 #
1!
#2126000
0!
#2128000
b1000010101 #
1!
#2130000
0!
#2132000
b1000010110 #
1!
#2134000
0!
#2136000
b1000010111 #
1!
#2138000
0!
#2140000
b1000011000 #
1!
#2142000
0!
#2144000
b1000011001 #
1!
#2146000
0!
#2148000
b1000011010 #
1!
#2150000
0!
#2152000
b1000011011 #
1!
#2154000
0!
#2156000
b1000011100 #
1!
#2158000
0!
#2160000
b1000011101 #
1!
#2162000
0!
#2164000
b1000011110 #
1!
#2166000
0!
#2168000
b1000011111 #
1!
#2170000
0!
#2172000
b1000100000 #
1!
#2174000
0!
#2176000
b1000100001 #
1!
#2178000
0!
#2180000
b1000100010 #
1!
#2182000
0!
#2184000
b1000100011 #
1!
#2186000
0!
#2188000
b1000100100 #
1!
#2190000
0!
#2192000
b1000100101 #
1!
#2194000
0!
#2196000
b1000100110 #
1!
#2198000
0!
#2200000
b1000100111 #
1!
#2202000
0!
#2204000
b1000101000 #
1!
#2206000
0!
#2208000
b1000101001 #
1!
#2210000
0!
#2212000
b1000101010 #
1!
#2214000
0!
#2216000
b1000101011 #
1!
#2218000
0!
#2220000
b1000101100 #
1!
#2222000
0!
#2224000
b1000101101 #
1!
#2226000
0!
#2228000
b1000101110 #
1!
#2230000
0!
#2232000
b1000101111 #
1!
#2234000
0!
#2236000
b1000110000 #
1!
#2238000
0!
#2240000
b1000110001 #
1!
#2242000
0!
#2244000
b1000110010 #
1!
#2246000
0!
#2248000
b1000110011 #
1!
#2250000
0!
#2252000
b1000110100 #
1!
#2254000
0!
#2256000
b1000110101 #
1!
#2258000
0!
#2260000
b1000110110 #
1!
#2262000
0!
#2264000
b1000110111 #
1!
#2266000
0!
#2268000
b1000111000 #
1!
#2270000
0!
#2272000
b1000111001 #
1!
#2274000
0!
#2276000
b1000111010 #
1!
#2278000
0!
#2280000
b1000111011 #
1!
#2282000
0!
#2284000
b1000111100 #
1!
#2286000
0!
#2288000
b1000111101 #
1!
#2290000
0!
#2292000
b1000111110 #
1!
#2294000
0!
#2296000
b1000111111 #
1!
#2298000
0!
#2300000
b1001000000 #
1!
#2302000
0!
#2304000
b1001000001 #
1!
#2306000
0!
#2308000
b1001000010 #
1!
#2310000
0!
#2312000
b1001000011 #
1!
#2314000
0!
#2316000
b1001000100 #
1!
#2318000
0!
#2320000
b1001000101 #
1!
#2322000
0!
#2324000
b1001000110 #
1!
#2326000
0!
#2328000
b1001000111 #
1!
#2330000
0!
#2332000
b1001001000 #
1!
#2334000
0!
#2336000
b1001001001 #
1!
#2338000
0!
#2340000
b1001001010 #
1!
#2342000
0!
#2344000
b1001001011 #
1!
#2346000
0!
#2348000
b1001001100 #
1!
#2350000
0!
#2352000
b1001001101 #
1!
#2354000
0!
#2356000
b1001001110 #
1!
#2358000
0!
#2360000
b1001001111 #
1!
#2362000
0!
#2364000
b1001010000 #
1!
#2366000
0!
#2368000
b1001010001 #
1!
#2370000
0!
#2372000
b1001010010 #
1!
#2374000
0!
#2376000
b1001010011 #
1!
#2378000
0!
#2380000
b1001010100 #
1!
#2382000
0!
#2384000
b1001010101 #
1!
#2386000
0!
#2388000
b1001010110 #
1!
#2390000
0!
#2392000
b1001010111 #
1!
#2394000
0!
#2396000
b1001011000 #
1!
#2398000
0!
#2400000
b1001011001 #
1!
#2402000
0!
#2404000
b1001011010 #
1!
#2406000
0!
#2408000
b1001011011 #
1!
#2410000
0!
#2412000
b1001011100 #
1!
#2414000
0!
#2416000
b1001011101 #
1!
#2418000
0!
#2420000
b1001011110 #
1!
#2422000
0!
#2424000
b1001011111 #
1!
#2426000
0!
#2428000
b1001100000 #
1!
#2430000
0!
#2432000
b1001100001 #
1!
#2434000
0!
#2436000
b1001100010 #
1!
#2438000
0!
#2440000
b1001100011 #
1!
#2442000
0!
#2444000
b1001100100 #
1!
#2446000
0!
#2448000
b1001100101 #
1!
#2450000
0!
#2452000
b1001100110 #
1!
#2454000
0!
#2456000
b1001100111 #
1!
#2458000
0!
#2460000
b1001101000 #
1!
#2462000
0!
#2464000
b1001101001 #
1!
#2466000
0!
#2468000
b1001101010 #
1!
#2470000
0!
#2472000
b1001101011 #
1!
#2474000
0!
#2476000
b1001101100 #
1!
#2478000
0!
#2480000
b1001101101 #
1!
#2482000
0!
#2484000
b1001101110 #
1!
#2486000
0!
#2488000
b1001101111 #
1!
#2490000
0!
#2492000
b1001110000 #
1!
#2494000
0!
#2496000
b1001110001 #
1!
#2498000
0!
#2500000
b1001110010 #
1!
#2502000
0!
#2504000
b1001110011 #
1!
#2506000
0!
#2508000
b1001110100 #
1!
#2510000
0!
#2512000
b1001110101 #
1!
#2514000
0!
#2516000
b1001110110 #
1!
#2518000
0!
#2520000
b1001110111 #
1!
#2522000
0!
#2524000
b1001111000 #
1!
#2526000
0!
#2528000
b1001111001 #
1!
#2530000
0!
#2532000
b1001111010 #
1!
#2534000
0!
#2536000
b1001111011 #
1!
#2538000
0!
#2540000
b1001111100 #
1!
#2542000
0!
#2544000
b1001111101 #
1!
#2546000
0!
#2548000
b1001111110 #
1!
